Workbook

Sheet Summary
A1: SUMMARY OF PENDING CP APPLICATIONS PER YEAR as of December 2025
A2: YEAR APPLIED | B2: CAR | C2: I | D2: II | E2: III | F2: IVA | G2: IVB | H2: V | I2: VI/VII | J2: IX | K2: X | L2: XI | M2: XII | N2: XIII | O2: TOTAL
A3: 1990 | I3: =COUNTIF('REGION 67'!$C$1:$C$35,1990) -> 0 | O3: =SUM(B3:N3) -> 0
A4: 2000 | I4: =COUNTIF('REGION 67'!$C$1:$C$35,200) -> 0 | O4: =SUM(B4:N4) -> 0
A5: 2001 | I5: =COUNTIF('REGION 67'!$C$1:$C$35,2001) -> 0 | O5: =SUM(B5:N5) -> 0
A6: 2002 | I6: =COUNTIF('REGION 67'!$C$1:$C$35,2002) -> 0 | O6: =SUM(B6:N6) -> 0
A7: 2003 | G7: 1 | I7: =COUNTIF('REGION 67'!$C$1:$C$35,2003) -> 0 | O7: =SUM(B7:N7) -> 1
A8: 2004 | I8: =COUNTIF('REGION 67'!$C$1:$C$35,2004) -> 0 | O8: =SUM(B8:N8) -> 0
A9: 2005 | I9: =COUNTIF('REGION 67'!$C$1:$C$35,2005) -> 0 | O9: =SUM(B9:N9) -> 0
A10: 2006 | I10: =COUNTIF('REGION 67'!$C$1:$C$35,2006) -> 0 | O10: =SUM(B10:N10) -> 0
A11: 2007 | I11: =COUNTIF('REGION 67'!$C$1:$C$35,2007) -> 1 | K11: 1 | L11: 1 | O11: =SUM(B11:N11) -> 3
A12: 2008 | I12: =COUNTIF('REGION 67'!$C$1:$C$35,1990) -> 0 | M12: 2 | O12: =SUM(B12:N12) -> 2
A13: 2009 | I13: =COUNTIF('REGION 67'!$C$1:$C$35,2009) -> 1 | O13: =SUM(B13:N13) -> 1
A14: 2010 | B14: 2 | C14: 3 | I14: =COUNTIF('REGION 67'!$C$1:$C$35,2010) -> 0 | K14: 4 | L14: 1 | M14: 1 | O14: =SUM(B14:N14) -> 11
A15: 2011 | C15: 7 | G15: 3 | I15: =COUNTIF('REGION 67'!$C$1:$C$35,2011) -> 2 | J15: 2 | K15: 3 | L15: 1 | O15: =SUM(B15:N15) -> 18
A16: 2012 | C16: 2 | G16: 5 | I16: =COUNTIF('REGION 67'!$C$1:$C$35,2012) -> 1 | L16: 1 | O16: =SUM(B16:N16) -> 9
A17: 2013 | C17: 1 | G17: 5 | I17: =COUNTIF('REGION 67'!$C$1:$C$35,2013) -> 0 | J17: 1 | M17: 2 | O17: =SUM(B17:N17) -> 9
A18: 2014 | B18: 1 | C18: 3 | G18: 7 | I18: =COUNTIF('REGION 67'!$C$1:$C$35,2014) -> 0 | L18: 2 | O18: =SUM(B18:N18) -> 13
A19: 2015 | B19: 1 | C19: 9 | G19: 15 | I19: =COUNTIF('REGION 67'!$C$1:$C$35,2015) -> 0 | K19: 6 | L19: 1 | O19: =SUM(B19:N19) -> 32
A20: 2016 | B20: 2 | C20: 7 | E20: 2 | G20: 4 | I20: =COUNTIF('REGION 67'!$C$1:$C$35,2016) -> 0 | J20: 1 | K20: 11 | O20: =SUM(B20:N20) -> 27
A21: 2017 | B21: 1 | C21: 6 | G21: 13 | I21: =COUNTIF('REGION 67'!$C$1:$C$35,2017) -> 0 | J21: 5 | K21: 7 | O21: =SUM(B21:N21) -> 32
A22: 2018 | B22: 7 | C22: 8 | E22: 21 | F22: 1 | G22: 20 | I22: =COUNTIF('REGION 67'!$C$1:$C$35,2018) -> 0 | J22: 2 | K22: 9 | L22: 2 | M22: 1 | O22: =SUM(B22:N22) -> 71
A23: 2019 | B23: 3 | C23: 8 | D23: 3 | G23: 52 | I23: =COUNTIF('REGION 67'!$C$1:$C$35,2019) -> 1 | J23: 9 | K23: 1 | L23: 1 | O23: =SUM(B23:N23) -> 78
A24: 2020 | B24: 2 | C24: 7 | D24: 4 | E24: 1 | F24: 2 | G24: 37 | I24: =COUNTIF('REGION 67'!$C$1:$C$35,2020) -> 0 | J24: 5 | M24: =1+2+1 -> 4 | O24: =SUM(B24:N24) -> 62
A25: 2021 | B25: 5 | C25: 1 | D25: 2 | E25: 13 | F25: 7 | G25: 37 | I25: =COUNTIF('REGION 67'!$C$1:$C$35,2021) -> 0 | J25: 68 | L25: 82 | M25: 7 | O25: =SUM(B25:N25) -> 222
A26: 2022 | B26: 6 | C26: 8 | D26: 3 | E26: 6 | F26: 3 | G26: 23 | I26: =COUNTIF('REGION 67'!$C$1:$C$35,2022) -> 3 | J26: 27 | L26: 92 | M26: 15 | O26: =SUM(B26:N26) -> 186
A27: 2023 | B27: 4 | C27: 10 | D27: 5 | E27: 3 | F27: 3 | H27: 3 | I27: =COUNTIF('REGION 67'!$C$1:$C$35,2023) -> 3 | J27: 37 | L27: 322 | M27: 5 | O27: =SUM(B27:N27) -> 395
A28: 2024 | B28: 20 | C28: 1 | D28: 22 | E28: 17 | F28: 3 | H28: 4 | I28: =COUNTIF('REGION 67'!$C$1:$C$35,2024) -> 4 | J28: 28 | K28: 15 | L28: =797+8 -> 805 | M28: 6 | N28: 151 | O28: =SUM(B28:N28) -> 1076
A29: 2025 | B29: 10 | C29: 0 | D29: 2 | E29: 30 | G29: 2 | H29: 1 | I29: =COUNTIF('REGION 67'!$C$1:$C$35,2025) -> 6 | J29: 1 | K29: 15 | L29: 615 | N29: 24 | O29: =SUM(B29:N29) -> 706
A30: TOTAL | B30: =SUM(B4:B29) -> 64 | C30: =SUM(C4:C29) -> 81 | D30: =SUM(D4:D29) -> 41 | E30: =SUM(E4:E29) -> 93 | F30: =SUM(F4:F29) -> 19 | G30: =SUM(G4:G29) -> 224 | H30: =SUM(H4:H29) -> 8 | I30: =SUM(I4:I29) -> 22 | ... N30: =SUM(N4:N29) -> 175 | O30: =SUM(O2:O29) -> 2954

Sheet Summary per project
A1: List of On-going CP Applications AS OF DECEMBER , 2025
A2: REGION | B2: Government Projects | C2: Mining/ Mineral processing project | D2: Energy Project | E2: Forest Management project | F2: EPR | G2: Research project | H2: Road projects | I2: Sand and Gravel | J2: Irrigation project | K2: Livelihood Programs | L2: Eco-Tourism Project | M2: FLGMA | N2: Telecommunication | O2: Carbon Trading | P2: Tree Cutting project | Q2: Plantation/ Pearl project | R2: Water System Project | S2: Others | T2: TOTAL
A3: CAR | B3: 3 | C3: 8 | D3: 23 | E3: 6 | I3: 1 | J3: 4 | L3: 0 | M3: 10 | N3: 9 | T3: =SUM(B3:S3) -> 64
A4: 1 | C4: 16 | D4: 21 | E4: 1 | G4: 6 | H4: 2 | I4: 17 | J4: 11 | N4: 1 | P4: 1 | Q4: 1 | R4: 1 | S4: 3 | T4: =SUM(B4:S4) -> 81
A5: 2 | B5: 7 | D5: 10 | E5: 6 | G5: 1 | H5: 3 | J5: 2 | L5: 5 | N5: 3 | Q5: 1 | R5: 1 | S5: 2 | T5: =SUM(B5:S5) -> 41
A6: 3 | B6: 4 | C6: 15 | D6: 22 | E6: 18 | F6: 1 | G6: 1 | H6: 10 | I6: 29 | P6: 2 | Q6: 1 | R6: 5 | S6: 6 | T6: =SUM(B6:S6) -> 114
A7: 4A | B7: 4 | C7: 1 | D7: 3 | H7: 1 | I7: 1 | L7: 9 | T7: =SUM(B7:S7) -> 19
A8: 4B | B8: 21 | C8: 7 | D8: 25 | E8: 8 | G8: 9 | H8: 22 | I8: 24 | J8: 7 | L8: 8 | M8: 8 | N8: 20 | Q8: 3 | R8: 9 | S8: 53 | T8: =SUM(B8:S8) -> 224
A9: 5 | B9: 1 | C9: 2 | D9: 1 | L9: 2 | M9: 1 | N9: 1 | T9: =SUM(B9:S9) -> 8
A10: 6&7 | B10: 4 | C10: 8 | D10: 4 | E10: 3 | I10: 2 | J10: 1 | T10: =SUM(B10:S10) -> 22
A11: 9 | B11: 21 | C11: 50 | D11: 12 | E11: 11 | F11: 2 | H11: 31 | I11: 38 | J11: 5 | R11: 3 | S11: 13 | T11: =SUM(B11:S11) -> 186
A12: 10 | B12: 6 | C12: 8 | D12: 9 | E12: 5 | H12: 13 | I12: 5 | J12: 2 | L12: 3 | M12: 1 | N12: 1 | Q12: 9 | R12: 5 | S12: 5 | T12: 72
A13: 11 | B13: 285 | C13: 11 | D13: 9 | E13: 28 | F13: 1 | G13: 22 | H13: 219 | I13: 71 | J13: 3 | K13: 2 | L13: 91 | N13: 15 | O13: 2 | P13: 3 | Q13: 3 | R13: 38 | S13: 1123 | T13: =SUM(B13:S13) -> 1926
A14: 12 | B14: 10 | C14: 7 | D14: 2 | F14: 1 | H14: 8 | I14: 4 | L14: 1 | N14: 2 | P14: 1 | R14: 2 | S14: 5 | T14: =SUM(B14:S14) -> 43
A15: 13 | B15: 58 | C15: 25 | D15: 5 | E15: 25 | F15: 5 | H15: 20 | I15: 11 | J15: 5 | R15: 3 | S15: 18 | T15: =SUM(B15:S15) -> 175
A16: TOTAL | B16: =SUM(B3:B15) -> 424 | C16: =SUM(C3:C15) -> 158 | D16: =SUM(D3:D15) -> 146 | E16: =SUM(E3:E15) -> 111 | F16: =SUM(F3:F15) -> 10 | G16: =SUM(G3:G15) -> 39 | H16: =SUM(H3:H15) -> 329 | I16: =SUM(I3:I15) -> 203 | ... S16: =SUM(S3:S15) -> 1228 | T16: =SUM(B16:S16) -> 2975

Sheet CAR
A1: No. | B1: REGION | C1: DATE OF FILING OF CP APPLICATION | D1: NAME OF PROPONENT | E1: NAME OF PROJECT | F1: Project Cost | G1: LOCATION | H1: Type of Project | I1: AFFECTED AD/ICC/IP (for CP with ongoing FPIC) | J1: STATUS OF APPLICATION | K1: STATUS
B3: ABRA | E3: ABRA | I3: ABRA | N3: ABRA
A4: =A3+1 -> 1 | B4: CAR | C4: 2010 | D4: MR. NESTOR ESPEJO | E4: Forest Land Grazing Management Agreement | F4: No data | G4: Mabungtot, Langiden, Abra | H4: FLGMA | J4: For compliance of RO to CEB's comment | K4: FPIC completed
A5: 2 | B5: CAR | C5: 11/26/2019 | D5: National Irrigation Administration (NIA) | E5: Ilocos Norte-Ilocos Sur-Abra Irrigation Project (INISAIP) | F5: No data | G5: Tineg/ Lagayan, Abra | H5: Irrigation Project | I5: Tinggian | J5: Forwarded Legal Advisory No. 309-10-30-25 to PO | K5: FPIC completed
A6: 3 | B6: CAR | C6: 12/14/2022 | D6: Benido L. Balao-as, Sr | E6: Renewal of Forest Land Grazing Management (FLGMA) | F6: No data | G6: Licuan-Baay, Abra | H6: FLGMA | I6: Tinggian | J6: 2nd RRT Report issued | K6: Ongoing FPIC process
A7: 4 | B7: CAR | C7: 2024 | D7: West Sea Mineral Resources | E7: EXPA No. 130 | F7: No data | G7: Tineg Abra | H7: Mining Project | J7: On-going FPIC Process | K7: Ongoing FPIC process
A8: 5 | B8: CAR | C8: 07/13/2023 | D8: Yamang Mineral Corp. | E8: EXPA-000-129-CAR | F8: No data | G8: Abra | H8: Mining Project | J8: Ongoing FPIC Process
A9: 6 | B9: CAR | C9: 01/21/2025 | D9: Ricardo B. Mactal | E9: SIFMA | F9: No data | G9: Penarubia, Abra | H9: SIFMA | J9: Issued memo to PO re FBI Review Report and re personnel recommendation for FPIC Team | K9: FBI completed
A10: =A9+1 -> 7 | B10: CAR | C10: 07/04/2025 | D10: Joseph Q. Abaya | E10: FLGMA | F10: No data | G10: Bulbula, Licuan-Baay, Abra | H10: FLGMA | J10: Notice of Termination issued | K10: Notice of Termination issued
B11: APAYAO | E11: APAYAO | I11: APAYAO | N11: APAYAO
A12: =A10+1 -> 8 | B12: CAR | C12: 2015 | D12: National Irrigation Administration (NIA) | E12: Lower Apayao River Irrigation Project (LARIP) | F12: No data | G12: Pudtol/ Flora, Apayao | H12: Irrigation Project | I12: Isnag | J12: Compliance of FPIC team to ADO Observation/Comment under review by RRT | K12: FPIC completed
A13: =A12+1 -> 9 | B13: CAR | C13: 06/05/2018 | D13: DENR-CAR | E13: Nagan-Maton Wildlife Critical Habitat | F13: No data | G13: Pudtol, Apayao | H13: Government project | I13: Isnag | J13: Compliance of FPIC Team to the RRT Review Report under review | K13: FPIC completed
A14: =A13+1 -> 10 | B14: CAR | C14: 04/17/2019 | D14: Strategic Power Development Corporation (SPDC) | E14: 10 MW Nabuangan Run-off-River Hydropower Project | F14: No data | G14: Conner, Apayao | H14: energy Project | I14: Isnag | J14: Held in abeyance | K14: For continuation of FPIC process
A15: =A14+1 -> 11 | B15: CAR | C15: 08/25/2022 | D15: Olivia Catral, Manuel Canipas (rep. by Roger Canipas), Bulawan Land Owner's Small Scale Mining Association (BLOSSMA rep by Alexander Bisin), Paul Delwasen (rep by Peter Paul Delwasen), Roman Austodillo, Reynaldo Bugnay | E15: Small Scale Mining Contract (SSMC) | F15: No data | G15: Manag, Conner; Butao, Calanasan; Talifugo, Conner; Eva Garden, Calanasan; Apayao | H15: mining project | I15: Isnag | J15: FPIC WO issued for Calanasan AD | K15: For FPIC process
A16: =A15+1 -> 12 | B16: CAR | C16: 01/06/2023 | D16: Lepanto Consolidated Mining Company and Far Southeast Gold Resources, Inc | E16: Renewal of MPSA No. 001-90-CAR | F16: No data | G16: Mankayan, Benguet | H16: mining project | I16: Kankana-ey | J16: On-going FPIC Process | K16: Ongoing FPIC process
A17: =A16+1 -> 13 | B17: CAR | C17: 03/30/2023 | D17: Apayao PLGU | E17: Inscription of Apayao as the 4th united nations educational scientific cultural organization (UNESCO) biosphere reserve of the Phils. | F17: No data | G17: Apayao | H17: Government project | I17: Isnag | J17: 02/19/2024- Received 2 copies of FBI report | K17: FBI completed
A18: =A17+1 -> 14 | B18: CAR | C18: 2024 | D18: National Power Corporation (NAPOCOR) | E18: Kabugao Diesel Power Plant | F18: No data | H18: Energy Project | J18: 02/14/2025- Transmitted Application Review report Transmitted to PO 02/22/2024- Received lacking documents to support application | K18: Ongoing Review of the application
A19: =A18+1 -> 15 | B19: CAR | C19: 2010 | D19: National Irrigation Administration (NIA) | E19: Small Reservior Irrigation Project (SRIP) | F19: No data | G19: Flora, Apayao | H19: Irrigation | J19: Conducted meeting with NIA. Since the project is already completed, it will undergo validation. | K19: FPIC completed
B20: BENGUET | E20: BENGUET | I20: BENGUET | N20: BENGUET
A21: 16 | B21: CAR | C21: 2016 | D21: COHECO Badeo Corporation | E21: 500MW Pump Storage Hydro Power Project | F21: No data | G21: Kibungan, Benguet | H21: Energy Project | I21: Kankana-ey | J21: Endorsed CP Application to CEB | K21: FPIC completed
A22: =A21+1 -> 17 | B22: CAR | C22: 02/23/2018 | D22: Hedcor Inc | E22: 2.4 MW Sal-angan HEPP | F22: No data | G22: Itogon, Benguet | H22: Energy Project | I22: Ibaloy, Kalanguya, Kankana-ey, Iwak | J22: 05/27/2025- Issued reconstituted FPIC Work Order for FPIC team | K22: For FPIC process
A23: =A22+1 -> 18 | B23: CAR | C23: 06/27/2018 | D23: River Flow Ventures and Power Energy Corporation | E23: 2.7MW Camp John Hay Mini-hydro Electric Power Plant | F23: No data | G23: Baguio City | H23: Energy Project | I23: Ibaloy | J23: 06/04/2025- Forwarded LAO Advisory No. 174-05-28-25 to PO for their compliance | K23: FPIC completed
A24: =A23+1 -> 19 | B24: CAR | C24: 07/13/2018 | D24: Hedcor Inc | E24: 4.5MW Bineng3 HEPP | F24: No data | G24: La Trinidad, Benguet | H24: Energy Project | I24: Ibaloy, Kalanguya, Kankana-ey | J24: Deliberated. For issuance of CP. | K24: FPIC completed
A25: =A24+1 -> 20 | B25: CAR | C25: 2018 | D25: AT Dinum Company | E25: Tublay1 HEPP | F25: No data | G25: Tublay, Benguet | H25: Energy Project | I25: Ibaloy, Kalanguya, Kankana-ey | J25: Deliberated. For issuance of CP. | K25: FPIC completed
A26: =A25+1 -> 21 | B26: CAR | C26: 2019 | D26: MCG Aggregates and Crushing Plant | E26: ISAG permit renewal | F26: No data | G26: Tuba, Benguet | H26: Sand and Gravel | I26: Ibaloy, Kalanguya, Kankana-ey | J26: FPIC Report under review | K26: FPIC completed
A27: =A26+1 -> 22 | B27: CAR | C27: 06/30/2020 | D27: Zak Green Energy Inc | E27: 6MW Naguey HEPP | F27: No data | G27: Atok, Benguet | H27: energy Project | I27: Ibaloy, Kankana-ey | J27: For termination | K27: For termination
A28: =A27+1 -> 23 | B28: CAR | C28: 09/06/2021 | D28: Converge ICT Solutions Inc & MetroWorks ICT Construction Inc | E28: Erection of Converge ICT Solutions Inc Poles and Aerial Installation of Fiber Optic Cable | F28: No data | G28: Tublay, Benguet | H28: Telecommunication Project | I28: Ibaloy, Kalanguya, Kankana-ey | J28: 02/15/2024- Received 2 copies of FBI for evaluation | K28: FBI completed
A29: 24 | B29: CAR | C29: 2021 | D29: SN Aboitiz Power, Inc. | E29: 105MW Ambuklao HEPP | F29: No data on record | G29: Bokod, Benguet | H29: energy project | I29: Ibaloy, Karao | J29: Resolution of non-consent was issued by the ICCs *Received Terminal Report- for review
A30: =A29+1 -> 25 | B30: CAR | C30: 2021 | D30: SN Aboitiz Power, Inc. | E30: 140MW Binga Hydro Electric PP - Upper Agno HEP | F30: No data on record | G30: Itogon, Benguet | H30: energy project | I30: Ibaloy, Kalanguya, Kankana-ey, Iwak | J30: FPIC Book transmitted to ADO per ADO Memo to review (parallel review) For guidance of ADO on issues raised by Bokod. | K30: FPIC completed
A31: =A30+1 -> 26 | B31: CAR | C31: 02/10/2022 | D31: Benguet Corporation | E31: Special Mines Permit covering Slide Fr and East Fr | F31: No data | G31: Itogon, Benguet | H31: Mining project | I31: Ibaloy, Kalanguya, Kankana-ey, Iwak | J31: 03/11/2024-Transmitted issued FPIC WO to PO | K31: For FPIC process
A32: =A31+1 -> 27 | B32: CAR | C32: 2024 | D32: HEDCOR INC. (HCI) Formerly Hedcor Cordillera | E32: 52 MW Kabayan 2 HEPP | F32: No data | G32: Kabayan Benguet | H32: Energy Project | J32: IPO issued Manifestation of No Consent | K32: Ongoing FPIC process
A33: 28 | B33: CAR | C33: 2024 | D33: National Grid Corporation of the Philippines (NGCP) | E33: Ordinary Repeater Relay station | F33: No data | G33: Cabuyao, Mt. Sto. Thomas Poblacion, Tuba Benguet | H33: Telecommunication project | J33: FPIC Validation report under review
A34: =A33+1 -> 29 | B34: CAR | C34: 2024 | D34: Tagel Corp | E34: 20 MW kabayan 4 Hydro electric power Project ( with issued HSC No. 2024-01-953) | F34: No data | G34: Acop, caponga, Tublay Benguet | H34: Energy Project | J34: 01/10/2025- Transmitted to ADO the Comment/Briefer re: Compliance of the FPIC Team and RRT relative to ADO Memorandum Order No. ADO RMD-2024-12-273 (Protest/Opposition to the issuance of CP Tagel Corp.) ***
A35: =A34+1 -> 30 | B35: CAR | C35: 2024 | D35: Phil-Tower Consortium, Inc | E35: Construction of Cellsite Tower | F35: No data | G35: Ucab, Itogon Pico, La Trinidad Benguet | H35: Telecommunication project | J35: Issued Show Cause to Proponent due to failure to conduct FBI activities | K35: In active CP application
A36: =A35+1 -> 31 | B36: CAR | C36: 2024 | D36: San Roque Hydropower, Inc. | E36: 800 MW Lower East Pumped Storage 800 MW West Pumped Storage | F36: No data | G36: Ampucao, Itogon, Benguet | H36: Energy Project | I36: Itogon AD | J36: FPIC-WFP forwarded to Chair for concurrence
A37: 32 | B37: CAR | C37: 2025 | D37: San Roque Hydropower, Inc. | E37: 600 MW Upper East Pumped Storage | F37: No data | G37: Dalupirip, Itogon, Benguet | H37: Energy Project | I37: Itogon AD | J37: FPIC-WFP forwarded to Chair for concurrence
A38: =A37+1 -> 33 | B38: CAR | C38: 2025 | D38: ISRI | E38: Renewal of MPSA No. 152-2000-CAR by ISRI | F38: No data | G38: Mankayan, Benguet | H38: Mining Project | J38: Sent letter to proponent acknowledging the receipt of submitted reports and informing them the constraints of the application for renewal | K38: Ongoing CP application
A39: =A38+1 -> 34 | B39: CAR | C39: 2021 | D39: Benguet Corporation | E39: Exploration Permit Application No. 122 | F39: No data | G39: Virac, Itogon | H39: Mining | J39: For submission of progress report | K39: In active CP application
A40: =A39+1 -> 35 | B40: CAR | C40: 2024 | D40: National Grid Corporation of the Philippines (NGCP) | E40: La Trinidad-Calot 69 KV Transmission Line | F40: No data | G40: Benguet | H40: Energy Project | J40: 01/03/2025- Received request for postponement of scheduled MOA negotiations from proponent due to unresolved issues with the ICCs/IPs and landowners affected | K40: Ongoing FPIC process
A41: =A40+1 -> 36 | B41: CAR | C41: 06/30/2025 | D41: Radio Network Phils., Inc. | E41: FLAG for Telecommunication Facility | F41: No data | G41: Sto. Tomas, Tuba, Benguet | H41: FLAG | I41: Tuba AD | J41: FBI Work Order issued | K41: For FPIC process
B42: IFUGAO | E42: IFUGAO | I42: IFUGAO | N42: IFUGAO
A43: =A41+1 -> 37 | B43: CAR | C43: 2017 | D43: National Irrigation Administration (NIA) | E43: Alfonso Lista Pump Irrigation Project (ALPIP) | F43: 5000000 | G43: Alfonso Lista, Ifugao | H43: Irrigation Project | J43: ADO/LAO Observations/ Comments submitted on Oct. 19, 2023 | K43: FPIC completed
A44: =A43+1 -> 38 | B44: CAR | C44: 2018 | D44: DENR | E44: Forestland Management Project (FMP) | F44: No data | G44: Hingyon, Hungduan, Banaue, Lagawe, Asipulo, Mayoyao, Aguinaldo, Ifugao | H44: FMP | I44: Kalanguya, Ayangan, Tuwali | J44: For compliance of LAO comments by the FPIC team | K44: FPIC completed
A45: =A44+1 -> 39 | B45: CAR | C45: 2018 | D45: Raul C. Tutaan | E45: renewal of Forest Land Grazing Management Agreement (FLGMA) | F45: No data | G45: Barangays Calupaan and San Juan, Municipality of Alfonso Lista, Province of Ifugao | H45: FLGMA | J45: For issuance of Notice of Termination (small scale project) | K45: In active CP application
A46: =A45+1 -> 40 | B46: CAR | C46: 2024 | D46: MIESCOR Infrastructure Development Corporation (MIDC) | E46: Telecommunication Tower Facility | F46: No data | G46: Tinoc, Ifugao | H46: Telecommunication project | J46: FPIC Report under review
A47: =A46+1 -> 41 | B47: CAR | C47: 2024 | D47: Intele Builders and Developmnet Corp | E47: Telecommunication project | F47: No data | G47: Ifugao | H47: Telecommunication project | J47: Concurred FBI WFP forwarded to PO
A48: =A47+1 -> 42 | B48: CAR | C48: 2024 | D48: Frontier Tower Associates Philippines | E48: Cellsite Tower | F48: No data | G48: Tinoc, Ifugao | H48: Telecommunication project | J48: 04/30/2025- Forwarded RRT Review Report to PO | K48: FPIC completed
A49: =A48+1 -> 43 | B49: CAR | C49: 2024 | D49: SN Aboitiz Power Magat, Inc. | E49: 10 MW Magat Floating Solar Power | F49: No data | G49: Alfonso Lista Ifugao | H49: Energy Project | J49: 12/12/2024- WO for Composition of FBI team to conduct FBI activities was issued | K49: For FPIC process
A50: =A49+1 -> 44 | B50: CAR | C50: 2024 | D50: Energy Development Corp. | E50: Buguias-Tinoc Geothermal Project | F50: No data | G50: Ifugao | H50: Energy Project | J50: Endorsed CP for concurrrence of Chair | K50: FPIC process completed
A51: =A50+1 -> 45 | B51: CAR | C51: 2020 | D51: Ibulao Mini Hydro Corp. | E51: 7.4 MW Ibulao 2 | F51: No data | G51: Ifugao | H51: Energy Project | J51: Issued Notice of Termination on April 11, 2025 | K51: In active CP application
A52: =A51+1 -> 46 | B52: CAR | C52: 2014 | D52: SN Aboitiz Power Ifugao, Inc. | E52: Alimit HEPP 120 MW (Alimit Hydropower Complex | F52: Estimated to be about 300-400 M USD (16- 17 Billion Php) | G52: Ifugao | H52: Energy Project | J52: Compliance of Proponent & FPIC Team to RRT under review - Proponent is not coordinating for the continuation of process | K52: FPIC completed
B53: KALINGA | E53: KALINGA | H53: KALINGA | N53: KALINGA
A54: =A52+1 -> 47 | B54: CAR | C54: 2016 | D54: Karayan Hydropower Corporation | E54: 52MW Chico River Hydro Power Project | F54: No data | G54: Tabuk, Kalinga | H54: Energy Project | I54: Kalinga | J54: FPIC Book endorsed to ADO on May 27, 2025 ADO/LAO compliances submitted on May 29, 2025 | K54: FPIC completed
A55: 48 | B55: CAR | C55: 07/02/2021 | D55: Globe Telecom/ EFB Geostrukt, Inc | E55: Construction of Globe Cell Site | F55: No data | G55: Balbalan, Kalinga | H55: Telecommunication Project | I55: Kalinga | J55: FPIC-WFP approved and forwarded to PO | K55: Ongoing FPIC process
A56: 49 | B56: CAR | C56: 01/05/2022 | D56: AQB Forest Management Project Inc | E56: Renewal of Socialized Industrial Forest Management Agreement (SIFMA) | F56: No data | G56: Gatab, Bantay, Tabuk City, Kalinga | H56: SIFMA | I56: Kalinga | J56: FPIC WO issued | K56: Ongoing FPIC process
A57: 50 | B57: CAR | C57: 2024 | D57: Guidance Management Corporation - Aragorn Power Energy Corp (GMC-APEC) | E57: Geothermal Project | F57: No data | G57: Dananao Kalinga | H57: Energy Project | J57: Received request letter for execution on 01/10/24 | K57: In active CP application
A58: =A57+1 -> 51 | B58: CAR | C58: 2024 | D58: Triangle Energy | E58: Petrolium Service Contract Petroleum Exploration Project | F58: No data | G58: Kalinga-MP and Ifugao | H58: Energy Project | J58: No compliance from proponent re submission of Affidavit of Undertaking | K58: In active CP application
A59: =A58+1 -> 52 | B59: CAR | C59: 2024 | D59: CREI Phil Inc. | E59: Telecommunication Tower | F59: No data | G59: Tabuk City Kalinga | H59: Telecommunication project | J59: 03/20/2024- Work Order was issued 03/20/2024- Progress/Status Report to IEN Phils., Inc. | K59: In active CP application
A60: =A59+1 -> 53 | B60: CAR | C60: 02/03/2025 | D60: Antonio L. Canao II | E60: Forest Land Grazing Management Agreement (FLGMA) | F60: No data | G60: Magsuso, Bulo, Tabuk City | H60: FLGMA | J60: 03/12/2025- Issued 2nd CP/CNO Application Report to PO | K60: Ongoing evaluation of CP application
A61: =A60+1 -> 54 | B61: CAR | C61: 02/04/2025 | D61: Vivian T. Bangsara | E61: SIFMA | F61: No data | G61: Sitio Mindayon, Brgy. Malalao, Tabuk City, Kalinga | H61: SIFMA | J61: Received payment of FBI Fee. For conduct of FBI activities
A62: =A61+1 -> 55 | B62: CAR | C62: 02/05/2025 | D62: Marie Ann T. Dalayday | E62: SIFMA | F62: No data | G62: Sitio Talaca, Brgy. Agbannawag, Tabuk City, Kalinga | H62: SIFMA | J62: Received payment of FBI Fee. For conduct of FBI activities
A63: =A62+1 -> 56 | B63: CAR | C63: 02/06/2025 | D63: Cathrine Ann T. Iniego | E63: SIFMA | F63: No data | G63: Sitio Mindayon, Brgy. Malalao, Tabuk City, Kalinga | H63: SIFMA | J63: Received payment of FBI Fee. For conduct of FBI activities
A64: 57 | B64: CAR | C64: 2024 | D64: Markham Resources Corp. | E64: HEPP | F64: No data | G64: Kalinga | H64: Energy Project | J64: 11/08/2024- Recieved CP Application | K64: In active CP application
A65: =A64+1 -> 58 | B65: CAR | C65: 2024 | D65: Demetrio Bangcoleng | E65: FLGMA | F65: No data | G65: Tabuk City Kalinga | H65: FLGMA | J65: 07/16/2025- Issued memo to PO re personnel recommendation for the composition of FPIC Team | K65: FBI completed
C66: MOUNTAIN PROVINCE | G66: MOUNTAIN PROVINCE | J66: MOUNTAIN PROVINCE
A67: =A65+1 -> 59 | B67: CAR | C67: 08/23/2022 | D67: HEDCOR Sabangan, Inc. | E67: FLGMA | F67: No data | G67: Bauko, Mountain, Province | H67: FLGMA | J67: CP endorsed to Chair for concurrence | K67: FPIC process completed
A68: 60 | B68: CAR | C68: 12/27/2022 | D68: Annie Rita del Rosario | E68: Forest Land Grazing Management Agreement (FLGMA) | F68: No data | G68: Paracelis, Mountain Province | H68: FLGMA | J68: 04/23/2025- Issued memo to PO re submission of progress report | K68: In active CP application
A69: =A68+1 -> 61 | B69: CAR | C69: 04/17/2023 | D69: Phil-Tower Consortium, Inc | E69: Construction of 5 cell site towers | F69: No data | G69: Bangaan & Suyo (Sagada); Tapapan & Calutit (Bauko); Tambingan (Sabangan), MP | H69: Telecommunication project | J69: Issued Show Cause Order to proponent | K69: In active CP application
A70: =A69+1 -> 62 | B70: CAR | C70: 2024 | D70: Marilyn E. Wanason | E70: FLGMA | F70: No data | G70: Bananao Paracelis Mt. Province | H70: FLGMA | J70: ADO Memo for compliance of FPIC Team | K70: FPIC completed
A71: =A70+1 -> 63 | B71: CAR | C71: 2024 | D71: Miescor Infrastructure Development Corporation (MIDC) | E71: Telecommunication Tower Facility | F71: No data | G71: Mountain Province | H71: Telecommunication project | J71: FPIC Report under review
A72: =A71+1 -> 64 | B72: CAR | C72: 2025 | D72: Fred L. Fangonon | E72: SIFMA | F72: No data | G72: Paracelis, Mountain Province | H72: SIFMA | J72: FPIC WO issued | K72: For conduct of FPIC activities

Sheet REGION 1
A1: t | B1: REGION | C1: DATE OF FILING OF CP APPLICATION | D1: NAME OF PROPONENT | E1: NAME OF PROJECT | F1: Project Cost | G1: LOCATION | H1: Type of Project | I1: AFFECTED AD/ICC/IP (for CP with ongoing FPIC) | J1: STATUS OF APPLICATION | K1: STATUS
A3: 1 | B3: 1 | C3: 2010 | D3: Mina Fortuna | E3: EXPA | H3: Mining Project | J3: due to inaction of the proponent | K3: In active CP application
A4: =+A3+1 -> 2 | B4: 1 | C4: 2010 | D4: Benguet Corp. | E4: FTAA | G4: Adams, Ilocos Norte | H4: Mining Project | J4: ICCs/ Ips issued Resolution of Non-Consent | K4: Ongoing FPIC process
A5: =+A4+1 -> 3 | B5: 1 | C5: 2010 | D5: Benguet Corp.- Cabittauran & Sto Nino Nueva Era | E5: FTAA | G5: Cabittauran & Sto Niño, Nueva Era IN | H5: Mining Project | J5: Issued WO/Memo to Proceed with the FPIC | K5: Ongoing FPIC process
A6: =+A5+1 -> 4 | B6: 1 | C6: 2011 | D6: Malibato Mining Co. Inc. | E6: FYPA-016-1, | G6: Lamag & Patiacan, Quirino, IS | H6: Mining Project | I6: Kankanaey | J6: Stop Operation/No permit issued | K6: In active CP application
A7: =+A6+1 -> 5 | B7: 1 | C7: 2011 | D7: Phil. Great minerals Corp. | E7: Expa 068, | G7: Vintar IN | H7: Mining Project | I7: Imalawa | J7: Stp[ Operation/Finish Contract | K7: In active CP application
A8: =+A7+1 -> 6 | B8: 1 | C8: 2011 | D8: Benguet Corp- Dasar, Isic-Isic, Vintar | E8: FTAA den. ATTA# 003 | G8: Dasar, Isic-isic, Vintar, Ilocos Norte | H8: Mining Project | I8: Imalawa | J8: Issued WO/Memo to Proceed with the FPIC | K8: Ongoing FPIC process
A9: =+A8+1 -> 7 | B9: 1 | C9: 2011 | D9: Benguet Corp- Manalpac & Maan-anteng, Solosona | E9: FTAA den. ATTA# 003 | G9: Manalpac & Maan-anteng, Solsona, Ilocos Norte | H9: Mining Project | I9: Isnag | J9: Issued WO/Memo to Proceed with the FPIC | K9: Ongoing FPIC process
A10: =+A9+1 -> 8 | B10: 1 | C10: 2011 | D10: Primasiera Minerals Inc. ( Reynaldo Guillermo) | E10: FTAA | G10: Cacafean, Marcos, Ilocos Norte | H10: Mining Project | I10: Isnag | J10: no response from ADO after compliance of the recommendations & Findings | K10: In active CP application
A11: =+A10+1 -> 9 | B11: 1 | C11: 2011 | D11: NL UPC Asia | E11: Wind Farm | G11: Ilocos Norte | H11: Energy Project | J11: for en banc deliberation | K11: FPIC completed
A12: =+A11+1 -> 10 | B12: 1 | C12: 2011 | D12: Skymark Mining & Min. Corp.- Monitoring | E12: SLRP & RRW | G12: Sto. Niño, Nueva Era, Ilocos Norte | H12: Mining Project | I12: Tingguian | J12: no response from ADO after compliance of the recommendations & Findings | K12: In active CP application
A13: =+A12+1 -> 11 | B13: 1 | C13: 2012 | D13: Rizal Silica Corp. | E13: Expa 37 | G13: Nueva Era, Ilocos Norte | H13: Mining Project | I13: Tingguian | J13: no response from ADO after compliance of the recommendations & Findings | K13: In active CP application
A14: =+A13+1 -> 12 | B14: 1 | C14: 2012 | D14: Skymark Mining & Min. Corp.- Monitoring | E14: SLUP & Small Scale Mining | G14: Cabittauran, Nueva Era, Ilocos Norte | H14: Mining Project | I14: Tingguian | J14: no response from ADO after compliance of the recommendations & Findings | K14: In active CP application
A15: =+A14+1 -> 13 | B15: 1 | C15: 2013 | D15: South Ocean Mining Corp. | E15: AMPP | G15: Quirino, Ilocos Sur | H15: Mining Project | I15: Kankanaey | J15: no response from ADO after compliance of the recommendations & Findings | K15: In active CP application
A16: =+A15+1 -> 14 | B16: 1 | C16: 2014 | D16: Cordillera Exploration Co. Inc CEXci | E16: Expa 116 | G16: Cervantes, Ilocos Sur | H16: Mining Project | I16: Kankanaey | J16: Issued notice to proceed with the FPIC | K16: Ongoing FPIC process
A17: =+A16+1 -> 15 | B17: 1 | C17: 2014 | D17: North Luzon Renewable Energy | E17: Flag App Windfarm & Transmission Line Right of way located IN | G17: Bangui, Burgos, Ilocos Norte | H17: Energy Project | J17: Waiting submission of the report | K17: FPIC completed
A18: =+A17+1 -> 16 | B18: 1 | C18: 2014 | D18: Lilian Cruz | E18: ISAGPA 317 | G18: Bued, River, Esperanza, Sison, Pangasinan | H18: Sand and Gravel | I18: Ibaloi, Bago & Kankanaey | J18: ISAG application was converted to CSAG and as per last information from the field office a permit was already issued by the Provincial Government of Pangasinan despite the absence of a CP. NCIP coordinated with DENR regarding this issue, and the PENRO undertook to prepare a letter to the Provincial Mining and Regulatory Board Pangasinan requiring them to undergo FPIC prior to the renewal of their permits. This is in compliance with the agreement contained in the Joint Operational Agreement executed by the NCIP R1 and DENR R1 to address contentious issues in the implementation of their respective mandates. The issued permit by the Province of Pangasinan no longer required the CP, hence proponent no longer pursued its issuance with the NCIP. Despite this, proponents are still complying with the provisions of the MOA. | K18: In active CP application
A19: =+A18+1 -> 17 | B19: 1 | C19: 2014 | D19: Jaen Rose Payba & Blessilda Jarasa | E19: ISAGPA# 318 & 319 located | G19: Esperanza, Sison Pangasinan | H19: Sand and Gravel | I19: Ibaloi, Bago & Kankanaey | J19: ISAG application was converted to CSAG and as per last information from the field office a permit was already issued by the Provincial Government of Pangasinan despite the absence of a CP. NCIP coordinated with DENR regarding this issue, and the PENRO undertook to prepare a letter to the Provincial Mining and Regulatory Board Pangasinan requiring them to undergo FPIC prior to the renewal of their permits. This is in compliance with the agreement contained in the Joint Operational Agreement executed by the NCIP R1 and DENR R1 to address contentious issues in the implementation of their respective mandates. The issued permit by the Province of Pangasinan no longer required the CP, hence proponent no longer pursued its issuance with the NCIP. Despite this, proponents are still complying with the provisions of the MOA. | K19: In active CP application
A20: =+A19+1 -> 18 | B20: 1 | C20: 2015 | D20: SAN HAI Aggregates | E20: ISAGPA# 329 & 330 | G20: Esperanza, Sison Pangasinan | H20: Sand and Gravel | I20: Ibaloi, Bago & Kankanaey | J20: Proponent has not complied yet with the submission of documents (Board Resolution and Posting of Bond) as required by Legal Opinion No. 49-07-06-18. | K20: In active CP application
A21: =+A20+1 -> 19 | B21: 1 | C21: 2015 | D21: Darwin Angeles | E21: ISAGPA #329 | G21: Esperanza Sison Pangasinan | H21: Sand and Gravel | I21: Ibaloi, Bago & Kankanaey | J21: ISAG application was converted to CSAG and as per last information from the field office a permit was already issued by the Provincial Government of Pangasinan despite the absence of a CP. NCIP coordinated with DENR regarding this issue, and the PENRO undertook to prepare a letter to the Provincial Mining and Regulatory Board Pangasinan requiring them to undergo FPIC prior to the renewal of their permits. This is in compliance with the agreement contained in the Joint Operational Agreement executed by the NCIP R1 and DENR R1 to address contentious issues in the implementation of their respective mandates. The issued permit by the Province of Pangasinan no longer required the CP, hence proponent no longer pursued its issuance with the NCIP. Despite this, proponents are still complying with the provisions of the MOA. | K21: In active CP application
A22: =+A21+1 -> 20 | B22: 1 | C22: 2015 | D22: SAN HAI Aggregates | E22: Crushing Plant | G22: Cauringan Sison Pangasinan | H22: Sand and Gravel | I22: Ibaloi, Bago & Kankanaey | J22: Proponent has not complied yet with the submission of documents (Board Resolution and Posting of Bond) as required by Legal Opinion No. 49-07-06-18. | K22: In active CP application
A23: =+A22+1 -> 21 | B23: 1 | C23: 2015 | D23: Marita Pascual | E23: ISAGPA no 316 | G23: Cauringan Sison Pangasinan | H23: Sand and Gravel | I23: Ibaloi, Bago & Kankanaey | J23: ISAG application was converted to CSAG and as per last information from the field office a permit was already issued by the Provincial Government of Pangasinan despite the absence of a CP. NCIP coordinated with DENR regarding this issue, and the PENRO undertook to prepare a letter to the Provincial Mining and Regulatory Board Pangasinan requiring them to undergo FPIC prior to the renewal of their permits. This is in compliance with the agreement contained in the Joint Operational Agreement executed by the NCIP R1 and DENR R1 to address contentious issues in the implementation of their respective mandates. The issued permit by the Province of Pangasinan no longer required the CP, hence proponent no longer pursued its issuance with the NCIP. Despite this, proponents are still complying with the provisions of the MOA. | K23: In active CP application
A24: =+A23+1 -> 22 | B24: 1 | C24: 2015 | D24: Blessilda Jarasa | E24: ISAGPA no 318 | G24: Cauringan Sison Pangasinan | H24: Sand and Gravel | I24: Ibaloi, Bago & Kankanaey | J24: Proponent failed to comply as to the comments stated in the Legal Opinion. Proponent has stopped operating since 2017 | K24: In active CP application
A25: =+A24+1 -> 23 | B25: 1 | C25: 2015 | D25: Mathew Liis | E25: ISAGPA | G25: Dungon Sison Pangasinan | H25: Sand and Gravel | I25: Ibaloi, Bago & Kankanaey | J25: Proponent abandoned his application | K25: In active CP application
A26: =+A25+1 -> 24 | B26: 1 | C26: 2015 | D26: Mathew Liis | E26: ISAGPA | G26: Dungon, Sison, Pangasinan | H26: Sand and Gravel | I26: Ibaloi, Bago & Kankanaey | J26: proponent abandoned his application | K26: In active CP application
A27: =+A26+1 -> 25 | B27: 1 | C27: 2015 | D27: Aboitiz Power Corp. | E27: F7.5 MW Cervantes Mankayan-Bakun Hydroelectric Power Project (CMB-HEPP) | G27: Cervantes Mankayan-Bakun | H27: Energy Project | I27: Kankanaey | J27: proponent abandoned their application | K27: In active CP application
A28: 26 | B28: 1 | C28: 2015 | D28: NLREC | E28: Transmission line right of way & windmill | G28: located at Caunayan, Saguigui, Saliksik, Dampig, Mun. Pagudpud & Sitio Masamuyao Payac Bangui Ilocos Norte | H28: Energy Project | I28: Yapayao | J28: waiting for submission of FPIC report | K28: FPIC completed
A29: =+A28+1 -> 27 | B29: 1 | C29: 2016 | D29: Piddig Municipality-Ilocos Norte | E29: FLAg-Piddig Arabica Coffee Plantation | G29: Sitio Lammin, Piddig, Ilocos Norte | H29: Plantation Project | I29: Yapayao | J29: Proponent abandoned their application | K29: In active CP application
A30: 28 | B30: 1 | C30: 2016 | D30: Energy Development Corporation | E30: FFlag Application for Wind Power Project | G30: Caunayan & Balaoi, Pagudpud, Ilocos Norte | H30: Energy Project | I30: Yapayao | J30: Waiting submission of FPIC Report | K30: FPIC completed
A31: =+A30+1 -> 29 | B31: 1 | C31: 2016 | D31: STA CLARA POWER CORPORATION | E31: Hydroelectric Power Plant Project | G31: San Emilio, Ilocos Sur | H31: Energy Project | I31: Itneg & Bago | J31: Recommended for the conduct of FPICProponent abandoned their application | K31: In active CP application
A32: =+A31+1 -> 30 | B32: 1 | C32: 2016 | D32: PHILNEWRIVER POWER CORP | E32: Hydroelectric Power Plant Project | G32: Quirino, Ilocos Sur | H32: Energy Project | I32: Kankanaey | J32: Recommended for the conduct of FPICProponent abandoned their application | K32: In active CP application
A33: =+A32+1 -> 31 | B33: 1 | C33: 2016 | D33: PHILNEWRIVER POWER CORP | E33: Hydroelectric Power Plant Project | G33: Sugpon, Ilocos Sur | H33: Energy Project | I33: Bago & Kankanaey | J33: Recommended for the conduct of FPICProponent abandoned their application | K33: In active CP application
A34: =+A33+1 -> 32 | B34: 1 | C34: 2016 | D34: PHILNEWRIVER POWER CORP | E34: Hydroelectric Power Plant Project | G34: Alilem, Ilocos Sur | H34: Energy Project | I34: Bago & Kankanaey | J34: Recommended for the conduct of FPICProponent abandoned their application | K34: In active CP application
A35: =+A34+1 -> 33 | B35: 1 | C35: 2016 | D35: FOUNDATION FOR THE PHIL ENVIRONMENT | E35: Validation of RSEA-KPNP l | G35: Adams, Ilocos Norte | H35: Others | I35: Isnag & Yapayao | J35: Recommended for the conduct of FPICProponent abandoned their application | K35: In active CP application
A36: =+A35+1 -> 34 | B36: 1 | C36: 2017 | D36: PRYZE GASES, INC. | E36: Special Land Use Permit (SLUP) | G36: Palina, Pigo, La Union | H36: Others | I36: Ibaloi, Bago & Kankanaey | J36: proponent abandoned their application | K36: In active CP application
A37: =+A36+1 -> 35 | B37: 1 | C37: 2017 | D37: Sta. Clara Power Corporation | E37: Hydro-Electric Power Project | G37: Matibuey, San Emilio, Ilocos Sur | H37: Energy Project | I37: Itneg & Bago | J37: proponent abandoned their application | K37: In active CP application
A38: 36 | B38: 1 | C38: 2017 | D38: E.H. Sison Engineers, Co. | E38: GACO Small Reservoir Irrigation Project | G38: Cacadiran, Cabugao, Ilocos Sur | H38: Irrigation Project | I38: Tingguian | J38: on-going FPIC | K38: Ongoing FPIC process
A39: 37 | B39: 1 | C39: 2017 | D39: Anthony Fernand Sunga (Solid Rock Aggregates) | E39: ISAGPA | G39: Agat, Sison, Pangasinan | H39: Sand and Gravel | I39: Ibaloi, Bago & Kankanaey | J39: recommended for the conduct of FPIC | K39: For FPIC process
A40: =+A39+1 -> 38 | B40: 1 | C40: 2017 | D40: NIA C/o E.H. Sison Engineers, CO. | E40: GACO Small Reservoir Irrigation Project | G40: Brgy., Cacadiran & Nagsincaoan, Cabugao Ilocos Sur | H40: Irrigation Project | I40: Tingguian | J40: on-going FPIC | K40: Ongoing FPIC process
A41: =+A40+1 -> 39 | B41: 1 | C41: 2017 | D41: Philnew River Power Corporation | E41: Hydro-electric Power Plant | G41: Brgy. Danac, Sugpon, Ilocos Sur | H41: Energy Project | I41: Bago & Kankanaey | J41: proponent abandoned their application | K41: In active CP application
A42: =+A41+1 -> 40 | B42: 1 | C42: 2018 | D42: SATRAP POWER CORPORATION | E42: 3.0 MW Hydro Electric Power Project . | G42: Man-atong, Suyo, Ilocos Sur | H42: Energy Project | I42: Bago & Kankanaey | J42: Recommended for FPIC Process | K42: For FPIC process
A43: =+A42+1 -> 41 | B43: 1 | C43: 2018 | D43: Philnew River Power Corporation | E43: Hydro Electric Power Project . | G43: Quirino, Ilocos Sur | H43: Energy Project | I43: Kankanaey | J43: proponent abandoned their application | K43: In active CP application
A44: =+A43+1 -> 42 | B44: 1 | C44: 2018 | D44: Philnew River Power Corporation | E44: Hydro Electric Power Project . | G44: at Alilem, Ilocos Sur | H44: Energy Project | I44: Bago & Kankanaey | J44: proponent abandoned their application | K44: In active CP application
A45: =+A44+1 -> 43 | B45: 1 | C45: 2018 | D45: Northern Cement Corporation | E45: Exploration Permit Application . | G45: Bila, Labayug & Inmalog, Sison, Pangasinan | H45: Mining Project | I45: Ibaloi, Bago & Kankanaey | J45: It has undergone CEB first deliberation, and the comments by the CEB particularly on project’s final technical description were not complied by the proponent. They applied for adjustment of technical description instead. The proponents were advised on the possible implication of amending their project's technical description as it would affect the ongoing CEB deliberation and it may be treated as different project. | K45: In active CP application
A46: =+A45+1 -> 44 | B46: 1 | C46: 2018 | D46: National Irrigation Administration | E46: Ilocos Norte Irrigation Project-2 (INIP-2) | G46: Nueva Era, Dingras, & Solsona, Ilocos Norte | H46: Irrigation Project | I46: Tingguian | J46: FPIC Report submitted, but result of RRT review under compliance of the Proponent, specifically the Minimum Performance Specifications Standards (MPSS) of the project. In addition, NIA-INISAIP committed to include and ensure that 636 hectares will be included in the service area of the project which will appear in the MPSS, otherwise the MOA shall be considered null and void or no effect from the beginning. NIA to submit Affidavit of Undertaking regarding this matter. | K46: FPIC completed
A47: =+A46+1 -> 45 | B47: 1 | C47: 2018 | D47: National Irrigation Administration | E47: Ilocos Norte Irrigation Project-2 (INIP-2) | G47: Nueva Era, Dingras, & Sinait, Ilocos Norte | H47: Irrigation Project | I47: Tingguian | J47: FPIC Report submitted, but result of RRT review under compliance of the Proponent, specifically the Minimum Performance Specifications Standards (MPSS) of the project. In addition, NIA-INISAIP committed to include and ensure that 636 hectares will be included in the service area of the project which will appear in the MPSS, otherwise the MOA shall be considered null and void or no effect from the beginning. NIA to submit Affidavit of Undertaking regarding this matter. | K47: FPIC completed
A48: =+A47+1 -> 46 | B48: 1 | C48: 2018 | D48: Northern Cement Corporation | E48: IKSP of Kankanaey and Ibaloi of Mapita ICCs on Upland Rainfed Farming | G48: Mapita, Laoag, Aguilar, Pangasinan | H48: Research | J48: ? | K48: No status indicated
A49: =+A48+1 -> 47 | B49: 1 | C49: 2018 | D49: Elvira Castillo | E49: ISAGPA | G49: Dungon, Sison Pangasinan | H49: Sand and Gravel | I49: Ibaloi, Bago & Kankanaey | J49: on going FPIC (MOA Negotiation) | K49: Ongoing FPIC process
A50: =+A49+1 -> 48 | B50: 1 | C50: 2019 | D50: Northern Cement Corporation | E50: Special Cutting Permit Application | G50: Labayug, Sison, Pangasinan | H50: Tree Cutting | I50: Ibaloi, Bago & Kankanaey | J50: Recommended for FPIC Process | K50: For FPIC process
A51: =+A50+1 -> 49 | B51: 1 | C51: 2019 | D51: FDC Renewable Corp. | E51: 26 MW Pampanga Hydro Power Plant Project | G51: Fianza, San Nicolas, Pangasinan | H51: Energy Project | I51: Iwak | J51: on-going FPIC | K51: Ongoing FPIC process
A52: =+A51+1 -> 50 | B52: 1 | C52: 2019 | D52: Mariano Marcos State University | E52: Anti-inflamatory Activity and Toxicity Profile of Ethanolic Extracts from Indigenous Plants in Ilocos Norte | G52: Adams, Ilocos Norte | H52: Research | I52: Isnag/yapayao | J52: Compliance to Legal Advisory No. 22-02-04-22 was forwarded to ADO and copy furnished to LAO through a Compliance dated August 05, 2022, with Control No. RO1-2022-08-156 | K52: In active CP application
A53: 51 | B53: 1 | C53: 2019 | D53: National Irrigation Administration | E53: Ilocos Norte Irrigation Project-2 (INIP-2) | G53: municipalities of Solsona; Dingras Marcos; and Nueva Era, Ilocos Norte | H53: Irrigation Project | I53: Isnag, Yapayao & Tingguian | J53: waiting submission of the report | K53: FPIC completed
A54: 52 | B54: 1 | C54: 2019 | D54: Amihan Renewable Energy Corporation | E54: Wind Farm Energy Project | G54: Caparispisan, Pagudpud, Ilocos Norte | H54: Energy Project | I54: Yapayao | J54: Recommended for FPIC Process | K54: For FPIC process
A55: 53 | B55: 1 | C55: 2019 | D55: Zak Green Energy Inc | E55: Feasibiity study for Mini Hydro Powr Projects | G55: Vintar, Ilocos Norte | H55: Research | I55: Imalawa | J55: The application has already undergone its first CEB deliberation last February 08, 2023 but there were comments/lacking data during the CEB that must be complied with by the proponent and FPIC Team. (favorable LGU and Community Resolutions among others) | K55: Ongoing FPIC process
A56: 54 | B56: 1 | C56: 2019 | D56: Northern Cement Corporation | E56: Payment of CASH BOND as stated in the MOA between the ICCs/Ips of Sison, Pangasinan with Northern Cement Corporation entered on Aug. 15, 2019 re: Exploration Permit Application of NCC | G56: Sison, Pangasinan | H56: Mining Project | I56: Ibaloi, Bago & Kankanaey | J56: waiting for the 3rd and final reading schedule | K56: FPIC completed
A57: 55 | B57: 1 | C57: 2019 | D57: Energy Logics Philippines Inc. | E57: Wind & TROW | G57: Sitio Gubang, Canaan & Sitio Dasar Isic IsicVintar Ilocos Norte | H57: Energy Project | I57: Imalawa | J57: waiting for the FPIC Report | K57: FPIC completed
A58: =+A57+1 -> 56 | B58: 1 | C58: 2020 | D58: LGU-Pagudpud, Ilocos Norte | E58: Potable Water System Project | G58: Brgy. Saguigui, Pagudpud, Ilocos Norte | H58: Water System | I58: Yapayao | J58: non-submission of pertinent documents | K58: In active CP application
A59: 57 | B59: 1 | C59: 2020 | D59: FDC Renewable Corp. | E59: 26 MW Pampang Hydro Power Plant Project | G59: Fianza, San Nicolas, Pangasinan. | H59: Energy Project | J59: on-going FPIC Process(MOA Negotiation) | K59: Ongoing FPIC process
A60: 58 | B60: 1 | C60: 2020 | D60: Golden Aggregates & Crashing Plant | E60: ISAGPA | G60: Agat, Sison, Pangasinan | H60: Sand and Gravel | I60: Ibaloi, Bago & Kankanaey | J60: waiting for the confirmation of CP by the Chair | K60: FPIC completed
A61: 59 | B61: 1 | C61: 2020 | D61: San Miguel Northern Cement Inc. | E61: Line A & B Cement Manufacturing Plant | G61: Labayug, Sison, Pangasinan | H61: Mineral Processing | I61: Ibaloi, Bago & Kankanaey | J61: Recommended for the conduct of FPIC | K61: For FPIC process
A62: 60 | B62: 1 | C62: 2020 | D62: National Irrigation Administration/Fernandez, Rosemarie Angeline | E62: Refund of ck. No. 1858377 3/10 Cash advance for Negotiation & MOA drafting re: NIA-INIP Phase II - 3/9-13/2020 | G62: Nueva Era, Ilocos Norte | H62: Irrigation Project | I62: Tingguian | J62: Waiting for the FPIC Report | K62: FPIC completed
A63: 61 | B63: 1 | C63: 2020 | D63: Golden Aggregates & Crashing Plant | E63: Crashing Plant | G63: Dungon, Sison Pangasinan | H63: Sand and Gravel | I63: Ibaloi, Bago & Kankanaey | J63: waiting for the confirmation of CP by the Chair | K63: FPIC completed
A64: 62 | B64: 1 | C64: 2020 | D64: Zak Green Energy Inc | E64: 7.OMW Tamdagan 1 & 2 Hydro Electric Power Project | G64: Canaam & Isic-isic, Vintar, Ilocos Norte | H64: Energy Project | I64: Imalawa | J64: waiting for schedule of 2nd Reading of Comm en Banc | K64: Ongoing FPIC process
A65: 63 | B65: 1 | C65: 2021 | D65: DEPARTMENT OF PUBLIC WORKS AND HIGHWAYS | E65: Construction of Missing link/New Road, San Manuel (Pang.) - Itogon (Benguet) Road, Pangasinan | G65: San Mauel & Part of Fianza | H65: Road Project | I65: Iwak | J65: Recommended for FPIC Process | K65: For FPIC process
A66: 64 | B66: 1 | C66: 2022 | D66: DPWH | E66: Construction of Missing Link/ New Road San Manuel (Pangasinan)- (Benguet) Road, Pangasinan | G66: Fianza, San Nicolas, Pangasinan | H66: Road Project | I66: Iwak | J66: MOA Negotiation | K66: Ongoing FPIC process
A67: 65 | B67: 1 | C67: 2022 | D67: ELVIRA S. CASTILLO | E67: ISAGPA | G67: Dungon, Sison, Pangasinan | H67: Sand and Gravel | I67: Ibaloi, Bago & Kankanaey | J67: FPIC Report endorse to ADO April 11, 2023 | K67: FPIC completed
A68: 66 | B68: 1 | C68: 2022 | D68: MCG AGGREGATES AND CRUSHING PLANT | E68: ISAGPA | G68: Dungon, Sison, Pangasinan | H68: Sand and Gravel | I68: Ibaloi, Bago & Kankanaey | J68: FPIC Report endorse to ADO aApril 24, 2023 | K68: FPIC completed
A69: 67 | B69: 1 | C69: 2022 | D69: Romulo Flores | E69: ISAGPA(IPA 372) | G69: Brgy. Ilocano, Sudipen, La Union | H69: Sand and Gravel | I69: Bago | J69: on-going FPIC Process(MOA Negotiation) | K69: Ongoing FPIC process
A70: 68 | B70: 1 | C70: 2022 | D70: Green Indigenous Environment Dev't. Corp (GIEDCO) | E70: Bagulin Hydro Electric Power Plant | G70: Bagulin, La Union | H70: Energy Project | I70: Kankanaey | J70: At present, the proponent is negotiating with private IP land owners for the execution of individual lease agreements. The proponent informed this office that they are almost 80% done with the individual negotiations. To be endorsed immediately after compliance with the proponent. | K70: Ongoing FPIC process
A71: 69 | B71: 1 | C71: 2022 | D71: Transcend Towers Infrastructure Phils. Inc. | E71: Cellsite Installation Project | G71: Bumbuneg, San Gabriel, La Union | H71: Telecommunication | I71: Bago & Kankanaey | J71: on-going FPIC Process(MOA Negotiation) | K71: Ongoing FPIC process
... A83: 81 | B83: 1 | C83: 2024 | D83: One Ilocos Norte Energy Corp. | E83: Solar | G83: Brgy. Poblacion & Naguillan. Nueva Era, Ilocos Norte | H83: Energy Project | I83: Tinguian | J83: on-going FPIC (as of April 2025) | K83: Ongoing FPIC process

Sheet REGION 2
A1: NO | B1: REGION | C1: DATE OF FILING OF CP APPLICATION | D1: NAME OF PROPONENT | E1: NAME OF PROJECT | F1: Project Cost | G1: LOCATION | H1: Type of Project | I1: AFFECTED AD/ICC/IP (for CP with ongoing FPIC) | J1: STATUS OF APPLICATION | K1: STATUS
A3: 1 | B3: II | C3: 43543 | D3: Felicisimo Seatriz Jr. | E3: FLAGT located in Nangaramoan Environmental Protectors Association San Vicente, Sta. Ana, Cagayan | G3: Sta. Ana, Cagayan | H3: Eco-Tourism | I3: Agta | J3: On-going FPIC process | K3: Ongoing FPIC process
A4: =A3+1 -> 2 | B4: II | C4: 43752 | D4: Sharif Madmo H. Hasim | E4: NELEX sub project feasibility study | G4: Dupax, Sta Fe and Aritao, Nueva Vizcaya | H4: Research | J4: For completion of compliance re: ADO and LAO comments | K4: FPIC completed
A5: =A4+1 -> 3 | B5: II | C5: 43558 | D5: Juan Eugenio L. Roxas | E5: Application for CP FDC Renewables Corp. for the proposed 26 MW Pampang Hydropower project | G5: Kayapa and Sta. Fe, Nueva Vizcaya | H5: Energy | I5: Kalanguya, Iwak, Ibaloi; Kalanguya-Ikalahan | J5: FPIC report and MOA submitted to CO | K5: FPIC completed
A6: =A5+1 -> 4 | B6: II | C6: 44008 | D6: NIA Region 2 | E6: Ilaguen Multipurpose Irrigation and Power Project (IMIPP), San Mariano, Isabela | G6: San Mariano, Isabela | H6: Energy | I6: Agta | J6: On-going FPIC process; conflict resolution with IPC | K6: Ongoing FPIC process
A7: =A6+1 -> 5 | B7: II | C7: 44180 | D7: RBG Electronics | E7: Installation of 20ft Antenna Pole for Internet Connectivity in Ganao, Dupax Del Sur | G7: Dupax del Sur, Nueva Vizcaya | H7: Telecommunication | I7: Bugkalot | J7: On-going FPIC | K7: Ongoing FPIC process
A8: =A7+1 -> 6 | B8: II | C8: 44188 | D8: AT Dinum Energy Inc. | E8: 2.5 Canili HPP | G8: Alfonso Castaneda, Nueva Vizcaya | H8: Energy | I8: Bugkalot | J8: Suspended FPIC process; conflict resolution of concerned ICCs/IPs | K8: Ongoing FPIC process
A9: =A8+1 -> 7 | B9: II | C9: 44008 | D9: Raymundo B. Apil, CESE | E9: Palanan Irrigation Project (PIP) in the Municipality of Palanan | G9: Palanan, Isabela | H9: Irrigation Project | I9: Agta | J9: On-going FPIC | K9: Ongoing FPIC process
A10: =A9+1 -> 8 | B10: II | C10: 44258 | D10: Philippines Air Force | E10: Radar System | G10: Sta. Ana, Cagayan | I10: Agta | J10: For signing of MOA | K10: Ongoing FPIC process
A11: =A10+1 -> 9 | B11: II | C11: 44511 | D11: Mega Philippines, Inc. | E11: Northern Cagayan Geothermal Power Project (GSC No. 2019-02-061) | G11: Lal-lo, Gattaran, Baggao, Penablanca, Cagayan | H11: Energy | I11: Agta | J11: On-going FPIC process | K11: Ongoing FPIC process
A12: =A11+1 -> 10 | B12: II | C12: 44894 | D12: Balibago Waterworks System, Inc. | E12: 1500 CMD Rated Capacity-Water Treatment Plant and Supply System | G12: Banagan, Poblacion and Darapidap, Aritao | H12: Water System | J12: On-going FPIC process | K12: Ongoing FPIC process
A13: =A12+1 -> 11 | B13: II | C13: 44777 | D13: Suzette Padilla | E13: FLAGT | G13: San Vicente, Sta. Ana | H13: Eco-Tourism | I13: Agta | J13: On-going FPIC process | K13: Ongoing FPIC process
A14: =A13+1 -> 12 | B14: II | C14: 44803 | D14: San Jose San Mariano Livelihood Assoc. Inc. | E14: Enhanced NGP | G14: Sitio Diwagden, San Jose, San Mariano, Isabela | H14: Plantation | I14: Agta | J14: On-going FPIC process | K14: Ongoing FPIC process
A15: =A14+1 -> 13 | B15: II | C15: 45086 | D15: DPWH Region II | E15: Road Widening/Off-Carriageway Improvement along NV-Pangasinan Road | G15: Sta. Fe, Nueva Vizcaya | H15: Road Project | J15: On-going FPIC process | K15: Ongoing FPIC process
A16: =A15+1 -> 14 | B16: II | C16: 45054 | D16: NGCP | E16: Ambuklao-Bayombong 230 kV | G16: Bambang and Kayapa | H16: Energy | I16: Kalanguya, Iwak, Ibaloi | J16: On-going FBV | K16: Ongoing Validation Process
A17: =A16+1 -> 15 | B17: II | C17: 45148 | D17: DPWH 2 | E17: Construction of ProposedSan Mariano-Palanan Road | G17: San Mariano and Palanan | H17: Road Project | I17: Agta | J17: On-going FPIC process | K17: Ongoing Validation Process
A18: =A17+1 -> 16 | B18: II | C18: 44952 | D18: DSWD FO2 | E18: KALAHI CIDSS | G18: Babuyan Claro, Calayan | H18: Government Project | I18: Ibatan | J18: On-going FBV process | K18: Ongoing Validation Process
A19: =A18+1 -> 17 | B19: II | C19: 45020 | D19: NGCP | E19: Northern Luzon 230Kv Loop Project | G19: Sta. Praxedes, Claveria, Sanchez Mira, Pamplona, Abulug, Ballesteros, Allacapan and Lal-lo, Cagayan | H19: Energy | I19: Agta, Ibanag, Yapayao | J19: On-going FBV process | K19: Ongoing Validation Process
A20: =A19+1 -> 18 | B20: II | C20: 45534 | D20: Edgepoint Towers Inc | E20: Construction of Cell Tower | G20: Basco, Batanes | H20: Telecommunication | I20: Ivatan | J20: On-going FPIC process | K20: Ongoing Validation Process
A21: =A20+1 -> 19 | B21: II | C21: 45608 | D21: CSU-Carig | E21: Batanes Smart Tourism: Structural Strength of Smart Engineered Greenhouse Across Varying Wind Loads in the Island of Batanes project | G21: Uyugan, Batanes | H21: Eco-Tourism | I21: Ivatan | J21: On-going FBV process | K21: Ongoing Validation Process
A22: =A21+1 -> 20 | B22: II | C22: 45616 | D22: LGU Itbayat | E22: Construction of Logistics Hub | G22: Itbayat, Batanes | H22: Government Project | I22: Ivatan | J22: On-going FBV process | K22: Ongoing Validation Process
A23: =A22+1 -> 21 | B23: II | C23: 45649 | D23: Ludgoron Mining Corporation | E23: EPA (EPA000180II) | G23: Babuyan Claro, Calayan | H23: Energy | I23: Ibatan | J23: On going FBI | K23: Ongoing FBI
A24: =A23+1 -> 22 | B24: II | C24: 45649 | D24: JDVC Resources Corp. | E24: Application for Financial Technical Assistance | G24: Buguey, Cagayan | H24: Energy | I24: n/a | J24: On going FBI | K24: Ongoing FBI
A25: =A24+1 -> 23 | B25: II | C25: 45614 | D25: RIDAI | E25: CBFMA | G25: Rizal, San Guillermo | H25: Forest Management Project | I25: Agta | J25: On going FBI | K25: Ongoing FBI
A26: =A25+1 -> 24 | B26: II | C26: 45630 | D26: BKS Green Energy Corporation | E26: Transmission Line of Limbauan SPP | G26: Cabagan and San Pablo, Isabela | H26: Energy | I26: n/a | J26: On going FBI | K26: Ongoing FBI
A27: =A26+1 -> 25 | B27: II | C27: 45523 | D27: LGU Dupax del Sur | E27: Slaughter House | G27: Palabotan, Dupax del Sur | H27: Government Project | I27: Bugkalot | J27: On going FBV | K27: Ongoing Validation Process
... A43: =A42+1 -> 41 | B43: II | C43: 45677 | D43: OGPI | E43: Various Infra projects | G43: Bambang, Dupax del Norte and del Sur, Bayombong, Bagabag, Diadi and Solano | H43: Infrastructure | I43: Isinai | J43: On going FBV | K43: Ongoing Validation Process

Sheet REGION 3
A1: NO | B1: REGION | C1: DATE OF FILING OF CP APPLICATION | D1: NAME OF PROPONENT | E1: NAME OF PROJECT | F1: PROJECT COST | G1: LOCATION | H1: Type of Project | I1: AFFECTED AD/ICC/IP (for CP with ongoing FPIC) | J1: STATUS OF APPLICATION | K1: STATUS
A3: 1 | B3: III | C3: 2016 | D3: National Grid Corporation of the Philippines (NGCP) | E3: San Jose -Angat 115KV Transmission Line Upgrading Project (SJATLUP) | G3: Norzagaray, Bulacan | H3: Energy Project | J3: Issued RMD-ADO-37-2019-8 dated August 6, 2019 forwarding Legal Opinion 31-08-02-19; no compliance submitted. | K3: FPIC Completed | L3: =COUNTIF(K1:K178, "FPIC completed") -> 7
A4: 2 | B4: III | C4: 2016 | D4: OCEAN BUSINESS CORPORATION & THE MELECIAS | E4: Community Solicited Project for Fruit Tree Plantation Project | G4: Entablado, Brgy. Aglao, San Marcelino, Zambales | H4: Plantation Project | J4: Waiting for compliance to legal opinion no.22-03-12 | K4: FPIC Completed
A5: 3 | B5: III | C5: 2018 | D5: IP Community of Sitio Monicayo, Brgy. Calumpang, City of Mabalacat Pampanga | E5: Community Solicited Projects (Potable Water Supply) | G5: Sitio Monicayo, Brgy. Calumpang, City of Mabalacat Pampanga | H5: Water System | J5: Waiting for Legal Opinion | K5: FPIC Completed
A6: 4 | B6: III | C6: 2018 | D6: Blue Rock Aggregates Corp. | E6: Mabalacat, Pampanga | G6: Sitio Lukutang Malaki, San Isidro, Rodriguez, Rizal | H6: Sand and Gravel | J6: Awaiting compliance of RIV-A; Amend map to exclude R3 area; Waiting for the submission from the project proponent. | K6: In active CP application | L6: =COUNTIF(K1:K178, "In active CP Application") -> 4
A7: 5 | B7: III | C7: 2018 | D7: Mr. Dexter Ivan Lee | E7: Quarry Permit (AQP-B-851-21) | G7: Brgy Banaban Angat Bulacan | H7: Sand and Gravel | J7: MOA Negotiation | K7: Ongoing FPIC process | L7: =COUNTIF(K1:K178, "Ongoing FPIC Process") -> 10
A8: 6 | B8: III | C8: 2018 | D8: Mr. Bobby Millera | E8: Commercial Sand and Gravel Permit | G8: Brgy Maamot San Jose Tarlac | H8: Sand and Gravel | J8: ongoing lateral review of MOA | K8: Ongoing FPIC process
A9: 7 | B9: III | C9: 2018 | D9: Ms. Ruzen Mae Sarah Pasual | E9: Commercial Sand and Gravel Permit | G9: Brgy Maamot San Jose Tarlac | H9: Sand and Gravel | J9: on going madatory activity | K9: Ongoing FPIC process
A10: 8 | B10: III | C10: 2018 | D10: Ms. Sheryl Montaño | E10: Commercial Sand and Gravel Permit | G10: Brgy Maamot San Jose Tarlac | H10: Sand and Gravel | J10: on going madatory activity | K10: Ongoing FPIC process
A11: 9 | B11: III | C11: 2018 | D11: Mr. Michael Santos | E11: Commercial Sand and Gravel Permit | G11: Brgy Maamot San Jose Tarlac | H11: Sand and Gravel | J11: on going madatory activity | K11: Ongoing FPIC process
A12: 10 | B12: III | C12: 2018 | D12: Local Goverment Unit of Bagac, Bataan in Coordination with National Housing Authority (NHA) | E12: Housing Assistance Program for the Indigenous Peoples (HAPIP) of NHA | G12: Sitio Matalangao, Brgy Banawang, and Sitio Duhat Brgy Saysain, Bagac, Bataan | H12: Government Project | J12: - Validation report reviewed - all pertinent documents already transmitted to NHA as per their requirements - MOAs are for Review of NHA | K12: FPIC Completed
A13: 11 | B13: III | C13: 2018 | D13: Local Goverment Unit of Dinalupihan , Bataan in Coordination with National Housing Authority (NHA) | E13: Housing Assistance Program for the Indigenous Peoples (HAPIP) of NHA | G13: Bgry Tubo Tubo, Dinalupihan, Bataan | H13: Government Project | J13: -Validation report reviewed - all pertinent documents transmitted to NHA as per their requirements - MOAs are for Review of NHA | K13: FPIC Completed
A14: 12 | B14: III | C14: 2018 | D14: STKG Trading | E14: Industrial Sand and Gravel Permit Denominated as IPA000319 III | G14: Brgy Lawy Capas Tarlac | H14: Sand and Gravel | J14: For Conduct of Pre FBI conference | K14: Ongoing FPIC process
A15: 13 | B15: III | C15: 2018 | D15: DEPARTMENT OF PUBLIC WORKS AND HIGHWAYS (DPWH) | E15: Improvement/ Contruction of Culat- Cozo- San Ildefonzo road with Bridge. | G15: Brgy. Culat, Cozo and San ildefonzo, Casiguran Aurora. | H15: Road Project | J15: Follow up to field office | K15: In active CP application
A16: 14 | B16: III | C16: 2018 | D16: DEPARTMENT OF PUBLIC WORKS AND HIGHWAYS (DPWH) | E16: Rehabilitation and Improvement of the Dibut Farm to Market Road | G16: Brgy. Dibut San Luis, Aurora | H16: Road Project | J16: for review | K16: In active CP application
A17: 15 | B17: III | C17: 2018 | D17: Luvy Duenas | E17: Industrial Sand and Gravel Permit Denominated as IPA000340 III | G17: Brgy ODonnel Capas Tarlac | H17: Sand and Gravel | J17: FBI Conducted | K17: For FPIC process | L17: =COUNTIF(K1:K178, "For FPIC process") -> 16
A18: 16 | B18: III | C18: 2018 | D18: Ms. Shela Mae Lape Boromeo | E18: Industrial Sand and Gravel Permit Denominated as IPA000271 III | G18: Brgy Iba San Jose Tarlac | H18: Sand and Gravel | J18: FBI Conducted | K18: For FPIC process
A19: 17 | B19: III | C19: 2018 | D19: Zstone enterprises Inc. | E19: Industrial Sand and Gravel Permit Denominated as IPA000272 III | G19: Brgy Iba San Jose Tarlac | H19: Sand and Gravel | J19: FBI Conducted | K19: For FPIC process
A20: 18 | B20: III | C20: 2018 | D20: Mr. Joseph M. Domacena | E20: Industrial Sand and gravel Permit denominated as IPA000396 | G20: Brgy San Juan, Botolan, Zambales | H20: Sand and Gravel | J20: FBI Conducted | K20: For FPIC process
A21: 19 | B21: III | C21: 2018 | D21: Ms. Marilyn F. Dial | E21: Industrial Sand and gravel Permit denominated as IPA000394 | G21: Brgy San Juan, Botolan, Zambales | H21: Sand and Gravel | J21: FBI Conducted | K21: For FPIC process
A22: 20 | B22: III | C22: 2018 | D22: Mr. Edison T. Dagan | E22: Industrial Sand and gravel Permit denominated as IPA000395 | G22: Brgy San Juan, Botolan, Zambales | H22: Sand and Gravel | J22: FBI Conducted | K22: For FPIC process
A23: 21 | B23: III | C23: 2018 | D23: Mr. Jeremay B. Aguilar | E23: Industrial Sand and gravel Permit denominated as IPA000393 | G23: Brgy San Juan, Botolan, Zambales | H23: Sand and Gravel | J23: FBI Conducted | K23: For FPIC process
A24: 22 | B24: III | C24: 2018 | D24: Premium resource and Exploration | E24: Industrial Sand and Gravel Permit IPA000224 III | G24: Brgy. Carael, Botolan, Zambales | H24: Sand and Gravel | J24: FBI Conducted | K24: For FPIC process
A25: 23 | B25: III | C25: 2018 | D25: Mega Boulder Exploration and Resource | E25: Industrial Sand and Gravel Permit IPA000222 III | G25: Brgy. Carael, Botolan, Zambales | H25: Sand and Gravel | J25: FBI Conducted | K25: For FPIC process
A26: 24 | B26: III | C26: 2020 | D26: Ore Asia Mining and Development Corporation | E26: Mineral Production Sharing Agreement Denominated as APSA000410 III | G26: Brgy Camachin DRT, Bulacan | H26: Mining Project | J26: For Conduct of FBI with approved WFP | K26: For FBI | L26: =COUNTIF(K1:K178, "For FBI") -> 13
A27: 25 | B27: III | C27: 2021 | D27: Gruppo International Mining Co., Inc. | E27: Exploration Permit denominated as EXPA000229 | G27: Brgy. Calabgan Casiguran, Aurora | H27: Mining Project | J27: For Conduct of Pre FBI conference | K27: Ongoing FBI | L27: 9
A28: 26 | B28: III | C28: 2021 | D28: Verion Global Mining, Inc. | E28: Exploration Permit Denominated as EXPA 000222 III | G28: Brgy Kalawakan, DRT, Bulacan | H28: Mining Project | J28: For Conduct of Pre FBI conference | K28: Ongoing FBI
A29: 27 | B29: III | C29: 2021 | D29: One Thousand Years Corporation | E29: Exploration Permit Denominated as EXPA 000228 III | G29: Brgys Casalat, Bayabas, and Bukol, DRT, Bulacan | H29: Mining Project | J29: For Conduct of Pre FBI conference | K29: Ongoing FBI
A30: 28 | B30: III | C30: 2021 | D30: Abraham Benson Terry Wong | E30: Industrial Sand and Gravel Permit Denominated as IPA000210 III | G30: Brgy. Manuali Porac Pampanga | H30: Sand and Gravel | J30: for compliance of FBI team | K30: For FPIC process
A31: 29 | B31: III | C31: 2021 | D31: Topmines Quarry Resources | E31: Industrial Sand and Gravel Permit Denominated as IPA00209 III | G31: Brgy Manuali, Porac, Pampanga | H31: Sand and Gravel | J31: for compliance of FBI team | K31: For FPIC process
A32: 30 | B32: III | C32: 2021 | D32: Ian Benson Terry Wong | E32: Industrial Sand and Gravel Permit Denominated as IPA000211 III | G32: Brgy Manuali, Porac, Pampanga | H32: Sand and Gravel | J32: for compliance of FBI team | K32: For FPIC process
A33: 31 | B33: III | C33: 2021 | D33: Metropolitan Waterworks and sewerage system (MWSS) | E33: Angat Water Transmission Improvement Project (AWTIP) – Tunnel 5 | G33: Brgy San Lorenzo, San Mateo and Bigte Norzagaray, Bulacan | H33: Energy Project | J33: FPIC report submitted to ADO | K33: FPIC Completed
A34: 32 | B34: III | C34: 2021 | D34: DEPARTMENT OF PUBLIC WORKS AND HIGHWAYS (DPWH) | E34: Bareto by pass project | G34: Continuation of Naugsol – Tipo – Dinalupihan By- Pass Road | H34: Road Project | J34: For conduct of FBI | K34: For FBI
A35: 33 | B35: III | C35: 2021 | D35: DEPARTMENT OF PUBLIC WORKS AND HIGHWAYS (DPWH) | E35: Construction of Bypass Road Freeport Area of Bataan (FAB) to Bagac – Mariveles Road, Mariveles Bataan | G35: Bagac – Mariveles Road, Mariveles Bataan | H35: Road Project | J35: For Conduct of Pre FBI conference | K35: For FBI
A36: 34 | B36: III | C36: 2021 | D36: DPWH Nueva Ecija 1st District Engineering Office | E36: Construction of Road | G36: Brgy Capintalan Carranglan Nueva Ecija | H36: Road Project | J36: For Conduct of Pre FBI conference | K36: For FBI
A37: 35 | B37: III | C37: 2021 | D37: DEPARTMENT OF PUBLIC WORKS AND HIGHWAYS (DPWH) | E37: Road Construction Project of Department of Public Works and Highways (DPWH) | G37: Brgy Paltic to Brgy Dikapanikian, Dingalan, Aurora | H37: Road Project | J37: for review of compliance | K37: Validation completed | L37: =COUNTIF(K1:K178, "Validation completed") -> 4
A38: 36 | B38: III | C38: 2021 | D38: DEPARTMENT OF PUBLIC WORKS AND HIGHWAYS (DPWH) | E38: Rehabilitation of Water system project | G38: So. Dipontian, Brgy. Cozo, Casiguran Aurora | H38: Water System | J38: for review of compliance | K38: Validation completed
A39: 37 | B39: III | C39: 2021 | D39: Dinalupihan Water District | E39: New Water Source System | G39: Brgy Payangan, Dinalupihan, Bataan | H39: Water System | J39: for review of compliance | K39: Validation completed
A40: 38 | B40: III | C40: 2022 | D40: Oriental Petroleum and Mineral Corporation | E40: Exploration Permit EXPA000231 III, EXPA000240 III | G40: Candelaria, Cabangan, Botolan, Sta Cruz, San Antonio, Masinloc Zambales | H40: Mining Project | J40: for review of compliance | K40: Validation completed
A41: 39 | B41: III | C41: 2022 | D41: NATIONAL GRID CORPORATION OF THE PHILIPPINES (NGCP) | E41: CASTELLEJOS 230 KV SUBSTATION PROJECT | G41: CASTILLEJOS, Zambales | H41: Energy Project | J41: for compliance of FBI team | K41: For FPIC process
A42: 40 | B42: III | C42: 2022 | D42: NATIONAL GRID CORPORATION OF THE PHILIPPINES (NGCP) | E42: WESTERN LUZON 500 KV BACKBONE PROJECT – STAGE 2 | G42: Municipalities of Castillejos, San Marcelino, San Narciso, San Felipe, Cabangan, Botolan, Iba, Palauig, Masinloc, Candelaria and Sta Cruz, Zambales | H42: Energy Project | J42: \On going mandatory FPIC activity- MOA Negotiation | K42: Ongoing FPIC process
A43: 41 | B43: III | C43: 2022 | D43: NATIONAL GRID CORPORATION OF THE PHILIPPINES (NGCP) | E43: 230KV Substation Project and Construction of 230 KV Transmission line (Pampanga Side) | G43: Floridablanca, Porac, Angeles and Mabalacat City, Pampanga | H43: Energy Project | J43: Follow up Memo to FBI Team dated June 22, 2022 | K43: Ongoing FBI
A44: 42 | B44: III | C44: 2022 | D44: DPWH | E44: Capas-Botolan Road Project | G44: Tarlac and Zambales | H44: Road Project | J44: ongoing mandatory FPIC activities | K44: Ongoing FPIC process
A45: 43 | B45: III | C45: 2022 | D45: Kahariam Realty and Farm Inc | E45: INTEGRATED FOREST MANAGEMENT AGREEMENT | G45: Brgy. Malomboy, Botolan, Zambales | H45: Forest Management Project | J45: ongoing mandatory FPIC activities(MOA negotiation) | K45: Ongoing FPIC process
A46: 44 | B46: III | C46: 2023 | D46: DPWH ADOE | E46: Construction of Bayanihan - Quirino Provincial Road | G46: Bayanihan to Quirino | H46: Road Project | J46: FBI conducted; For FPIC | K46: For FPIC process
A47: 45 | B47: III | C47: 2023 | D47: MILAGROS DE GUZMAN | E47: RATTAN CUTTING PERMIT | G47: BRGYS. DIKAPANIKIAN, AND PALTIC, DINGALAN AURORA | H47: Tree Cutting Permit | J47: FBI conducted; For FPIC (with work order) | K47: For FPIC process
A48: 46 | B48: III | C48: 45139 | D48: Rufino Bantog | E48: LIMESTONE & ORDINARY EARTH MATERIALS QUARRY PROJECT DENOMINATED AS AQP-B-860-21 | G48: Brgy. Bayabas, Doña Remedios Trinidad, Bulacan | H48: Sand and Gravel | J48: FBI conducted ; For FPIC (with work Order) | K48: For FPIC process
A49: 47 | B49: III | C49: 45352 | D49: MR. RAMIL P. RAMOS | E49: EXPLORATION PERMIT DENOMINATED AS EXPA000270 III | G49: Brgy. Maguisguis, Botolan, Zambales | H49: Mining Project | J49: for FBI (with work order) | K49: For FBI
... A51: 49 | B51: III | C51: 45383 | D51: Mr. Laurence O. Cruz | E51: SOCIALIZED INDUSTRIAL FOREST MANAGEMENT AGREEMENT (SIFMA) | G51: Brgy. Kalawakan, Doña Remedios Trinidad, Bulacan | H51: Forest Management Project | J51: For FBI (with work order dated May 2024) | K51: For FBI
A52: 50 | B52: III | C52: 45413 | D52: Citicore Wind Energy Corporation | E52: Bataan-Zambales Cw Wind Power Project | F52: 9.7 Billion | G52: Bataan and Zambales | H52: Energy Project | J52: Deliberated; the proponent requested for a 2nd CEB session | K52: FPIC Completed
A53: 51 | B53: III | C53: 45475 | D53: LOCAL GOVERNMENT OF SAN MARCELINO | E53: Concreting of Farm-to-Market Road and Installation of Solar Lights | H53: Road Project | J53: for validation (with work order) | K53: For Validation
A54: 52 | B54: III | C54: 45474 | D54: ALBA RENEWABLES PHILIPPINES | E54: PRELIMINARY STUDIES FOR THE BOTOLAN WIND POWER PROJECT | G54: Brgy. Pita and Brgy. Bayan-bayanan, Dinalupihan, Bataan | H54: Energy Project | I54: Cadmang Reserva AD, Mabanglit AD, Poonbato-Owaog Nebloc AD and Bucao-Calibungan AD | J54: ongoing mandatory FPIC acitvities | K54: Ongoing FPIC process
A55: 53 | B55: III | C55: 45505 | D55: ZACCHEUS FARM ESTATES 1918 | E55: QUARRY PERMIT APPLICATION | G55: Brgy. Biaan, Mariveles, Bataan | H55: Sand and Gravel | J55: FBI conducted; Proponent can't be contacted after the FBI | K55: In active CP application
A56: 54 | B56: III | C56: 45537 | D56: PHILIPPINE ATMOSPHERIC GEOPHYSICAL AND ASTRONOMICAL SERVICES ADMINISTRATION (PAGASA) | E56: BALER DOPPLER WEATHER RADAR STATION | G56: SITIO POKPOK NA BATO, BRGY. ZABALI, BALER, AURORA | H56: Government Project | J56: for validation (with work order) | K56: For Validation
A57: 55 | B57: III | C57: 45538 | D57: R GALAXY MINING CORPORATION | E57: EXPLORATION PERMIT DENOMINATED AS EXPA 000264 III | G57: Brgy. Buhawen, San Marcelino, Zambales | H57: Mining Project | J57: Done with Pre-FBI | K57: Ongoing FBI
A58: 56 | B58: III | C58: 45539 | D58: R GALAXY MINING CORPORATION | E58: EXPLORATION PERMIT APPLICATION DENOMINATED AS EXPA 000265 III | G58: Brgy. Batiawan, Subic, Zambales | H58: Mining Project | J58: Done with Pre-FBI | K58: Ongoing FBI
A59: 57 | B59: III | C59: 45540 | D59: R GALAXY MINING CORPORATION | E59: EXPLORATION PERMIT APPLICATION DENOMINATED AS EXPA 000263 III | G59: Brgy. Rabanes, San Marcelino, Zambales | H59: Mining Project | J59: For FBI (with work order) | K59: For FBI
A60: 58 | B60: III | C60: 45541 | D60: R GALAXY MINING CORPORATION | E60: EXPLORATION PERMIT APPLICATION DENOMINATED AS EXPA 000262 III | G60: Brgy. Rabanes, San Marcelino, Zambales | H60: Mining Project | J60: Done with Pre-FBI | K60: Ongoing FBI
A61: 59 | B61: III | C61: 45540 | D61: GREEN VALLEY COMPANY | E61: EXPLORATION PERMIT DENOMINATED AS EXPA 000268 III | G61: San Marcelino, Subic, and Castillejos, Zambales | H61: Mining Project | J61: for FBI (with work order) | K61: For FBI
A62: 60 | B62: III | C62: 45567 | D62: TALA ELEMENTARY SCHOOL | E62: Secure a valid document for the development of facilities of the school | G62: So. Tala, Brgy. Burgos, San Jose, Tarlac | H62: others | J62: for validation (with work order) | K62: For Validation
A63: 61 | B63: III | C63: 45568 | D63: NATIONAL GRID CORPORATION OF THE PHILIPPINES (NGCP) | E63: BALSIK-OLONGAPO/BALSIK-SBMA 230 KV TRANSMISSION LINE | G63: Provinces of Bataan and Zambales | H63: Energy Project | J63: for FBI (with work order) | K63: For FBI
A64: 62 | B64: III | C64: 45599 | D64: PHILIPPINE EAGLE FOUNDATION | E64: FIELD OBSERVATION, TRACKING, MONITORING, AND BLOOD EXTRACTION FOR GENOME ANALYSIS OF THE DISCOVERED PHILIPPINE EAGLES | G64: San Luis, Aurora and Nueva Ecija | H64: Research | J64: for FBI (with work order) | K64: For FBI
A65: 63 | B65: III | C65: 45642 | D65: Mrs. Julieta Bustos | E65: Tree Farm Lease Agreement (TFLA) | G65: Porac, Pampanga | H65: Forest Management Project | J65: For submission of lacking docs (with reply letter) | K65: Ongoing evaluation of CP application | L65: =COUNTIF(K1:K178, "Ongoing evaluation of CP application") -> 23
A66: 64 | B66: III | C66: 45658 | D66: Donald Kerwin Cezar | E66: Exploration Permit | G66: Sitio Usboy, San Mateo, Norzagaray, Bulacan | H66: Mining Project | J66: For FBI | K66: For FBI
A67: 65 | B67: III | C67: 45659 | D67: LGU Dipaculao | E67: Forest Land Use Agreement for Tourism purposes | G67: Brgy. Dinadiawan, Dipaculao, Aurora | H67: Forest Management Project | J67: For submission of lacking docs (with reply letter) | K67: Ongoing evaluation of CP application
A68: 66 | B68: III | C68: 45661 | D68: Mr. Arlino L. Marbella | E68: Socialized Industrial Forest Management Agreement (SIFMA) | G68: Brgy. Mambog, Botolan, Zambales | H68: Forest Management Project | J68: with response letter (awaiting for the submission of lacking docs) | K68: Ongoing evaluation of CP application
A69: 67 | B69: III | C69: 45662 | D69: Mr. Michael Kho Lao | E69: Socialized Industrial Forest Management Agreement (SIFMA) | G69: So. Cocong, Brgy. Kalawakan, DRT, Bulacan | H69: Forest Management Project | J69: with response letter (awaiting for the submission of lacking docs) | K69: Ongoing evaluation of CP application
A70: 68 | B70: III | C70: 45663 | D70: NGCP | E70: Special Land Use Permit (SLUP)-Transmission Line Right of Way | G70: Brgys. Sindol and Maloma, San Felipe, Zambales and Brgys. Longos, New San Juan, San Rafael and Mabanglit, Cabangan, Zambales | H70: Energy Project | J70: with response letter (awaiting for the submission of lacking docs) | K70: Ongoing evaluation of CP application
A71: 69 | B71: III | C71: 45664 | D71: Liezzel P. Aquino | E71: Special Land Use Agreement (SLUP) | G71: Brgy. Pinulot, Dinalupihan, Bataan | H71: Forest Management Project | J71: with response letter (awaiting for the submission of lacking docs) | K71: Ongoing evaluation of CP application
A72: 70 | B72: III | C72: 45665 | D72: Ramil Ramos | E72: EXPA 000270-III | G72: Iba and Palauig, Zambales | H72: Mining Project | J72: with response letter (awaiting for the submission of lacking docs) | K72: Ongoing evaluation of CP application
A73: 71 | B73: III | C73: 45666 | D73: BFAR | E73: Aquaculture and Mariculture Expansion and Invigoration Project | G73: Dibut, Aurora | H73: Others | J73: with work order | K73: For Validation
A74: 72 | B74: III | C74: 45667 | D74: NGCP | E74: Special Land Use Agreement (SLUP) -Transmission line Right of Way | G74: Botolan, Masinloc, and Sta. Cruz | H74: Energy Project | J74: with response letter (awaiting for the submission of lacking docs) | K74: Ongoing evaluation of CP application
A75: 73 | B75: III | C75: 45668 | D75: DENR | E75: ERDB | G75: Province of Zambales | H75: Government Project | J75: with response letter (awaiting for the submission of lacking docs) | K75: Ongoing evaluation of CP application
A76: 74 | B76: III | C76: 45691 | D76: LGU CARRANGLAN | E76: Construction of Obito Solar Power Irrigation System | G76: Sitio Obito, San Agustin, Carranglan, Nueva Ecija | H76: Energy Project | J76: with response letter | K76: Ongoing evaluation of CP application
A77: 75 | B77: III | C77: 45717 | D77: AP Renewable Energy Corporation | E77: Olongapo Solar Power Project | G77: Barangays Sta. Rita, Old Cabalan and New Cabalan, City of Olongapo in Zambales | H77: Energy Project | J77: (EVOSS) WFP for FPIC for Confirmation of proponent | K77: Ongoing evaluation of CP application
... A89: 87 | B89: III | C89: 45809 | D89: Movere Development Corporation | E89: Special Land Use Agreement (SLUP) | G89: So. Mandaloy, Taltal, Masinloc, Zambales | H89: Forest Management Project | J89: with response letter (awaiting for the submission of lacking docs) | K89: Ongoing evaluation of CP application
A90: 88 | B90: III | C90: 45809 | D90: EEI Power Corporation | E90: EEI Solar Power Inc. SPP | F90: 3142375000 | G90: Mabiga, Hermosa, Bataan | H90: Solar Power Project (Energy) | J90: reapplied through EVOSS on September 2025 | K90: Incomplete docs/clarification
A91: 89 | B91: III | C91: 45809 | D91: EEI Power Corporation | E91: Mabiga Energy Corp. Solar Power Project | F91: 10077812000 | G91: Mabiga, Hermosa, Bataan | H91: Solar Power Project (Energy) | J91: reapplied through EVOSS on September 2025 | K91: Incomplete docs/clarification
A92: 90 | B92: III | C92: 45810 | D92: PAPA Brgy. Camachile DRT Bulacan Upland Farmers Association, Inc. | E92: Community-Based Forest Management Agreement (CBFMA) | G92: So. Pelon, Brgy. Camachile, Doña Remedios Trinidad, Bulacan | H92: Forest Management Project | J92: With Work Order; For FBI | K92: For FBI
A93: 91 | B93: III | C93: 45811 | D93: Mr. Ridgeway Cabloy | E93: Socialized Industrial Forest Management Agreement (SIFMA) | G93: Brgy. Taltal, Masinloc, Zambales | H93: Forest Management Project | J93: with response letter (awaiting for the submission of lacking docs) | K93: Ongoing evaluation of CP application
A94: 92 | B94: III | C94: 45812 | D94: Calaanan-Digmala Upland Farmers Association Inc. | E94: Community-Based Forest Management Agreement (CBFMA) | G94: Bongabon, Nueva Ecija | H94: Forest Management Project | J94: with response letter (awaiting for the submission of lacking docs) | K94: Ongoing evaluation of CP application

Sheet REGION 4A
A1: NO | B1: REGION | C1: DATE OF FILING OF CP APPLICATION | D1: NAME OF PROPONENT | E1: NAME OF PROJECT | F1: PROJECT COST | G1: LOCATION | H1: Type of Project | I1: AFFECTED AD/ICC/IP (for CP with ongoing FPIC) | J1: STATUS OF APPLICATION | K1: Status
A3: 1 | B3: IVA | C3: 2018 | D3: Mrs. Teresita Santiago | E3: Agro-Forestry Farm with Eco-Tourism Project (Evening Wind) | G3: Rizal | H3: Eco-tourism | I3: Dumagat/Remontado | J3: For submission of FPIC Report | K3: Ongoing review by RRT | L3: =COUNTIF(K1:K74, "FPIC completed") -> 2
A4: 2 | B4: IVA | C4: 2020 | D4: Malvar Cousins Corporation | E4: Mt. Purro Nature Reserve project | G4: Rizal | H4: Eco-Tourism | I4: Dumagat/Remontado | J4: Reconstituted FPIC Team to resume FPIC Process; Ongoing conduct of FPIC Process | K4: FPIC activities ongoing | L4: =COUNTIF(K1:K74, "FPIC activities ongoing") -> 2
A5: 3 | B5: IVA | C5: 2020 | D5: Real Wind Energy Inc. | E5: Real Wind Energy Power Project-WESC No. 2019-09-133 | G5: Rizal | H5: Energy | I5: Dumagat/Remontado | J5: Assigned WESC to Giga Ace 6; Done conducting MOA negotiation; For issuance of Work Order reconstituting FPIC Team | K5: WESC assigned to Giga Ace 6, Inc.
A6: 4 | B6: IVA | C6: 2021 | D6: Reynaldo Fresno | E6: Agro-Forestry and Eco Tourist Camp Site Project | G6: Rizal | H6: Eco-Tourism | I6: Dumagat/Remontado | J6: Issued FPIC Work Order dated May 6, 2024 | K6: FPIC activities ongoing
A7: 5 | B7: IVA | C7: 2021 | D7: Mr. William Jaime Astrande | E7: The Peak Campsite | G7: Rizal | H7: Eco-Tourism | I7: Dumagat/Remontado | J7: For compliance of FPIC Team to the LAO and ADO findings | K7: Ongoing review by ADO
A8: 6 | B8: IVA | C8: 2021 | D8: Hernando Mandilag Jr | E8: The Apiary Mountain Camp and Farm | G8: Rizal | H8: Eco-Tourism | I8: Dumagat/Remontado | J8: For payment of FBI Fee by the proponent | K8: For FBI | L8: =COUNTIF(K1:K74, "For FBI") -> 3
A9: 7 | B9: IVA | C9: 2021 | D9: Real Wind Energy, Inc. | E9: 250 MW Real Wind Power Project WESC No. 2021-03-153 Phase 3 | G9: Quezon | H9: Energy | I9: Dumagat | J9: Assigned WESC to Giga Ace 6; Done conducting MOA negotiation; For issuance of Work Order reconstituting FPIC Team | K9: WESC assigned to Giga Ace 6, Inc.
A10: 8 | B10: IVA | C10: 2021 | D10: Ridges and Clouds | E10: SAPA | G10: Rizal | H10: Eco-Tourism | I10: Dumagat/Remontado | J10: For conduct of FBI | K10: For FBI
A11: 9 | B11: IVA | C11: 2021 | D11: Grace S. Bagnes | E11: Kamp Maysawa | G11: Rizal | H11: Eco-Tourism | I11: Dumagat/Remontado | J11: For conduct of FBI | K11: For FBI
A12: 10 | B12: IVA | C12: 2021 | D12: Engr. Ramon Lopez-Lazaro | E12: Rainbow 89 Ecopark Camping and Trekking | G12: Rizal | H12: Eco-Tourism | I12: Dumagat/Remontado | J12: For issuance of FPIC Work Order | K12: For FPIC | L12: =COUNTIF(K1:K74, "For FPIC") -> 1
A13: 11 | B13: IVA | C13: 44578 | D13: DPWH IV-A | E13: Construction of Gen. Nakar-Dingalan Road, Gen. Nakar Quezon | G13: Quezon | H13: Road Project | I13: Dumagat | J13: Awaiting compliance of Validation and proponent | K13: FPIC completed
A14: 12 | B14: IVA | C14: 44753 | D14: Orophil Stonecraft Inc | E14: EPA-IVA-190 | G14: Quezon | H14: Mining | I14: non-AD | J14: Preparation of FPIC Report | K14: Ongoing review by RRT
A15: 13 | B15: IVA | C15: 44897 | D15: LGU -Tanay Rizal | E15: CP Application for LGSF-Support to Barangay Devt Program of the NTF-ELCAC Proposed projects in Tanay Rizal ( Farm to Market Road Brgy. Daraitan, Tanay and Barangay Health Center in Brgy. Sto. Niño, Tanay, Rizal) | G15: Rizal | H15: Goverment Project-Infrastructure | I15: Dumagat/remontado | J15: Ongoing evaluation of Validation Report by TMSD | K15: FPIC completed
A16: 14 | B16: IVA | C16: 45008 | D16: Sierra View and Leisure Farms | E16: Sierra View Leisure Farm | G16: Tanay | H16: Eco-Tourism | I16: Dumagat/remontado | J16: Ongoing evaluation of FBI report by TMSD | K16: FBI completed | L16: =COUNTIF(K1:K74, "FBI completed") -> 1
A17: 15 | B17: IVA | C17: 2023 | D17: Bluerock Aggregate Corp | E17: AMA-IVA-196 | G17: Rizal | H17: Quarry | I17: Dumagat/Remontado | J17: Refiled application; For payment of FPIC Fee by the proponent | K17: For payment of FPIC Fee
A18: 16 | B18: IVA | C18: 45075 | D18: First Gen Visayas Energy, Inc. | E18: Laguna Wind Power Project | G18: Laguna and Quezon | H18: Energy | I18: Dumagat | J18: The proponent is currently requesting DOE the amendment of Contract Area | K18: Issued CNO | L18: 1
A19: 17 | B19: IVA | C19: 45551 | D19: DSWD FO IV-A | E19: Various Projects for PAMANA IP CDD | G19: General Nakar, Quezon | H19: Goverment Project-Infrastructure | I19: Dumagat/Remontado | J19: Issued Work Order on October 7, 2024 for conduct of validation | K19: For validation | L19: =COUNTIF(K1:K74, "For validation") -> 3
A20: 18 | B20: IVA | C20: 45565 | D20: DPWH Quezon 1st District, Lucban, Quezon | E20: Construction of Multi Purpose Building | G20: Tanauan, Real, Quezon | H20: Goverment Project-Infrastructure | I20: Dumagat/Remontado | J20: Issued Work Order on October 20, 2024 for conduct of validation | K20: For validation
A21: 19 | B21: IVA | C21: 45579 | D21: DOH CHD-IVA | E21: Various Projects for PMNP | G21: Quezon | H21: Goverment Project-Infrastructure | I21: Dumagat/Remontado, Agta, Aeta, Manide, Dumagat | J21: Issued Work Order on December 17, 2024 for conduct of validation | K21: For validation

Sheet REGION 4B
A1: NO | B1: REGION IVB - (PER SERVICE CENTER) | C1: DATE OF FILING OF CP APPLICATION | D1: NAME OF PROPONENT | E1: NAME OF PROJECT | F1: PROJECT COST | G1: LOCATION | H1: Type of Project | I1: AFFECTED AD/ICC/IP (for CP with ongoing FPIC) | J1: STATUS OF APPLICATION | K1: STATUS
A3: 1 | B3: MIMAROPA BROOKES POINT | C3: 42522 | D3: Redmont Consolidated Mines Corporation | E3: Exploration Permit Application (EPA) | G3: Brgy. San Isidra, Malinao and Calategas, Narra; Brgys. Latud and Taburi, Rizal, Bataraza, Palawan | H3: Mining | I3: Tagbanua ICCs | J3: Pala'wan for CEB and Tagbanua for evaluation of ADO and LAO | K3: FPIC completed | L3: =COUNTIF(K1:K227, "FPIC completed") -> 13
A4: =A3+1 -> 2 | B4: MIMAROPA BROOKES POINT | C4: 43353 | D4: Power Source Philippines Inc. Represented by Ramon De Guzman | E4: Microgrid Project | G4: Brgy. Candawaga and Culasian, Rizal, Palawan | H4: Energy | I4: Pala'wan ICCs | J4: For submission of FPIC Book; - for verification from Mam Au | K4: FPIC completed
A5: =A4+1 -> 3 | B5: MIMAROPA BROOKES POINT | C5: 43556 | D5: Mr. Robert Cyrus B. Mayor | E5: Forest Land Use Agreement for Tourism (FLAGt) | G5: Apo. Island, Brgy. Sebaring, Balabac, Palawan | H5: Eco-Tourism | I5: Molbog ICCs | J5: FBI conducted but proponent failed to submit additional requirement. | K5: In active CP application | L5: =COUNTIF(K1:K227, "In active CP application") -> 87
A6: =A5+1 -> 4 | B6: MIMAROPA BROOKES POINT | C6: 43704 | D6: Robert Cyrus Mayor | E6: Recreation Island | G6: Brgy. Sebaring, Bugsok Island, Balabac, Palawan | H6: Eco-Tourism | I6: Molbog ICCs | J6: FBI conducted but proponent failed to submit additional requirement. | K6: In active CP application
A7: =A6+1 -> 5 | B7: MIMAROPA BROOKES POINT | C7: 44004 | D7: Berong Nickel Corporation (BNC) represented by Ms. Deborah A. Arquino, OIC Community Relations | E7: Ship Loading Project | G7: Sitio Little Baguio, Brgy. Maasin, Quezon, Palawan | H7: Others | I7: Pala'wan ICCs | J7: with MOA signing. For CEB delberation. FPIC Book for submission. | K7: FPIC completed
A8: =A7+1 -> 6 | B8: MIMAROPA BROOKES POINT | C8: 44229 | D8: Donna Q. Fuentes | E8: Commercial Sand and Gravel | G8: Brgy. Pangobilian, Brooke's Point, Palawan | H8: Sand and Gravel | I8: Pala'wan ICCs | J8: FBI conducted but proponent failed to submit additional requirement. Dormant Application | K8: In active CP application
A9: =A8+1 -> 7 | B9: MIMAROPA BROOKES POINT | C9: 44279 | D9: DPWH, Region IV-B (MIMAROPA) | E9: Balabac Military Runway | G9: Brgy. Catagupan, Balabac, Palawan | H9: Government | I9: Molbog ICCs | J9: For completion of MOA Negotiation - already operating without MOA . | K9: Ongoing FPIC process | L9: 24
A10: =A9+1 -> 8 | B10: MIMAROPA BROOKES POINT | C10: 44354 | D10: Mr. Roberto R. Del Moro | E10: Commercial Sand And Gravel Permit | G10: Isumbo River, Brgy. Pulot Interior, Sofronio Española, Palawan | H10: Sand and Gravel | I10: Pala'wan ICCs | J10: No follow up from the applicant | K10: In active CP application
A11: =A10+1 -> 9 | B11: MIMAROPA BROOKES POINT | C11: 44461 | D11: Redmont Consolidated Mines Corporation | E11: Proposed Exploration Project | G11: Brgy. San Isidro, Calategas and Malinao, Narra, Brgy. Malatgao and Sumbling, Bataraza and Brgys. Latud and Taburi, Rizal, Palawan | H11: Mining | I11: Pala'wan ICCs | J11: Pala'wan- for CEB and Tagbanua - waiting for the Evaluation of ADO and LAO | K11: FPIC completed
A12: =A11+1 -> 10 | B12: MIMAROPA BROOKES POINT | C12: 44480 | D12: Kalahi CIDSS Pamana IP CDD | E12: Improvement of 1-Unit School Handwashing Facility with Elevated Water Tank/Improvement of Recovery Facility with Construction of 2-Unit Comfort Room/ Construction of 1-Unit of Concrete Footbridge Prepair of Water System | G12: Barangay Malihud, Bataraza, Palawan | H12: Government | I12: Pala'wan ICCs | J12: for Community Validation | K12: For Validation | L12: =COUNTIF(K1:K227, "For Validation") -> 19
A13: =A12+1 -> 11 | B13: MIMAROPA BROOKES POINT | C13: 44708 | D13: Rio Tuba Nickel Mining and Coral Bay Nickel Corporation | E13: Level II Water System into Level III Water System | G13: Brgys. Sandoval, Culandum, Iwahig, Igang-igang, Sarong and Ocayan, Bataraza, Palawan | H13: Water System | I13: Pala'wan ICCs | J13: For MOA Validation | K13: Ongoing FPIC process
A14: =A13+1 -> 12 | B14: MIMAROPA BROOKES POINT | C14: 42860 | D14: Beatriz Acabado | E14: Almaciga Resin Gathering Permit | G14: Barangays Berong and Aramaywan, Quezon, Palawan | H14: Others | I14: Tagbanua ICCs | J14: Memorandum No. 2012-06-352 Series of 2012 - Validation conducted and Report Submitted to Regional Office for Issuance of CP | K14: Validation completed | L14: =COUNTIF(K1:K227, "Validation completed") -> 8
A15: =A14+1 -> 13 | B15: MIMAROPA BROOKES POINT | C15: 42797 | D15: Municipal Government of Sofronio Española | E15: LGU Water Sysytem Project | G15: Pulot Center, Sofronio Española, Palawan | H15: Water System | I15: Pala'wan ICCs | J15: Endorsed by Administrative Officer IV/OIC Delos Santos Last Oct. 20, 2021 for approval of WFP for validation | K15: For Validation
A16: =A15+1 -> 14 | B16: MIMAROPA BROOKES POINT | C16: 43681 | D16: Myrna Mendoza | E16: Forest Land Use Agreement (FLAg) | G16: Sitio Dinamdam, Barangay Panitian, Quezon, Palawan | H16: Others | I16: Pala'wan ICCs | J16: Work Order 2019-09 Series of 2019 - For Issuance of Work Order;For submission of FBI Report to Regional Office; | K16: FBI completed | L16: =COUNTIF(K1:K227, "FBI completed") -> 25
A17: =A16+1 -> 15 | B17: MIMAROPA BROOKES POINT | C17: 43802 | D17: Berong Nickel Corporation (BNC) represented by Ms. Deborah A. Arquino, OIC Community Relations | E17: Ship Loading Project (Tidepole Anchorage) | G17: Sitio Marintub, Brgy. Maasin, Quezon, Palawan | H17: Others | I17: Pala'wan ICCs | J17: Endorsed by Provincial Officer Parangue Last Feb. 24, 2020 For reconstitution of FPIC team and continuation of FPIC Process; For Submission of FPIC book to Region | K17: FPIC completed
A18: =A17+1 -> 16 | B18: MIMAROPA BROOKES POINT | C18: 43480 | D18: Ryan Angelo Dela Fuente | E18: Commercial Sand and Gravel Project CPA (PLW) No. 778 | G18: Barangay National Higway, Poblacion, Narra, Palawan | H18: Sand and Gravel | I18: Tagbanua ICCs | J18: Memorandum No. 2019-02-084 Series of 2019 for issuance of Work Order for FBI. No follow up by the applicant | K18: In active CP application
A19: =A18+1 -> 17 | B19: MIMAROPA BROOKES POINT | C19: 43809 | D19: Citinickel Mines and Development Corporation | E19: Mineral Production Sharing Agreement Project | G19: Narra and Sofronio Española, Palawan | H19: Mining | I19: Tagbanua and Pala'wan ICCs | J19: Endorsed by RD Almonte last Mar. 5, 2020 for issuance of Work Order for FBI. as per MOA signed 2007, and expire 2032. | K19: In active CP application
A20: =A19+1 -> 18 | B20: MIMAROPA BROOKES POINT | C20: 44039 | D20: Smart FTX Communication represented by Angelito Sanchez | E20: Smart Communications Rizal-Taburi | G20: Brgy. Taburi, Rizal, Palawan | H20: Telecommunication | I20: Pala'wan ICCs | J20: Memorandum Order No. 23 2021 Series of 2021; Pre FPIC conducted and for approval of Work and Financial Plan for FPIC; No follow up from the proponent, send final notice | K20: In active CP application
A21: =A20+1 -> 19 | B21: MIMAROPA BROOKES POINT | C21: 43962 | D21: John Gaspar S. Gagani | E21: Commercial San and Gravel Permit | G21: Brgy. Saraza, Brooke's Point, Palawan | H21: Sand and Gravel | I21: Pala'wan ICCs | J21: Work Order No. 91-2021 was issued last June 14, 2021 FBI conducted and report submitted for Issuance of CNO Issued | K21: FBI completed
A22: =A21+1 -> 20 | B22: MIMAROPA BROOKES POINT | C22: 43969 | D22: Eustaquio P. Cascara | E22: Commercial Sand and Gravel | G22: Dumangueña, Narra, Palawan | H22: Sand and Gravel | I22: Tagbanua ICCs | J22: Endorsed by AO IV/OIC Delos Santos last May 12, 2021 FBI conducted and report submitted for Issuance of CNO | K22: FBI completed
A23: =A22+1 -> 21 | B23: MIMAROPA BROOKES POINT | C23: 44265 | D23: Ali M. Porlucas | E23: Commercial Sand And Gravel Permit | G23: Brgy. Pulot Interior, Sofronio Española, Palawan | H23: Sand and Gravel | I23: Pala'wan ICCs | J23: Endorsed by AO IV Delos Santos last April 15, 2021 with approved WFP FBI conducted and report submitted for Issuance of CNO | K23: FBI completed
A24: =A23+1 -> 22 | B24: MIMAROPA BROOKES POINT | C24: 44267 | D24: Smart Communication represented by Troy G. Manito | E24: Smart FTX Project | G24: Brgy. Panalingaan, Rizal, Palawan | H24: Telecommunication | I24: Pala'wan ICCs | J24: Memorandum Order No. 23 2021 Series of 2021; Pre FPIC conducted and for approval of Work and Financial Plan for FPIC; No follow up from the proponent, send final notice | K24: In active CP application
A25: =A24+1 -> 23 | B25: MIMAROPA BROOKES POINT | C25: 44326 | D25: GLOBE Telecom Inc. represented by Mr. Marvin Mercado | E25: SLUP | G25: Sitio Catuayan, Brgy. Berong, Quezon, Palawan | H25: Telecommunication | I25: Tagbanua ICCs | J25: Work Order No. 2022-05-050 Series of 2022 for Pre FBI conference. No follow up by the proponent | K25: In active CP application
A26: =A25+1 -> 24 | B26: MIMAROPA BROOKES POINT | C26: 44506 | D26: Glenda A. Cruz | E26: Research Entitled: Biodiversity Conservation through Local Policy in Science Edication: A Pragmatic Research Design | G26: no data or document attached validating location of the proposed research. | H26: Research Project | I26: Pala'wan ICCs | J26: Lack of basic requirements under NCIP AO 1, s. 2012 - IKSP Validation conducted and Report submitted for Issuance of CP/Compliance | K26: Validation completed
A27: =A26+1 -> 25 | B27: MIMAROPA BROOKES POINT | C27: 43494 | D27: Mrs. Celestial M. Marin | E27: Commercial Sand and Gravel Quarry | G27: Pulot River, Brgy. Pulot Center, Sofronio | H27: Sand and Gravel | I27: Pala'wan ICCs | J27: Memorandum Order No. 53-2021 Series of 2021 FBI conducted and report submitted for Issuance of CNO | K27: FBI completed
A28: =A27+1 -> 26 | B28: MIMAROPA- ROXAS, PALAWAN | C28: 43340 | D28: Eddie A. Brook represented by Diana Galicia | E28: SAPA | G28: Brgy. Bebeladan, El Nido, Palawan | H28: Others | I28: Tagbanua ICCs | J28: no work order issued | K28: For FBI
A29: =A28+1 -> 27 | B29: MIMAROPA- ROXAS, PALAWAN | C29: 43349 | D29: Eugene C. Chiong, Jr. | E29: FLGMA | G29: Brgy. Bintuan, Coron, Palawan | H29: FLGMA | I29: no data or document attached | J29: Work order no: 2018-35 for FBI | K29: For FBI | L29: =COUNTIF(K1:K227, "For FBI") -> 21
A30: =A29+1 -> 28 | B30: MIMAROPA- ROXAS, PALAWAN | C30: 43446 | D30: Conrado N. D David | E30: CED Farm & Resort | G30: Sitio Logpond, Barangay Manlag, El Nido, Palawan | H30: Others | I30: no data/document | J30: WO#: 2019-11/ Pre FI conducted | K30: Ongoing FBI | L30: =COUNTIF(K1:K227, "Ongoing FBI") -> 6
A31: =A30+1 -> 29 | B31: MIMAROPA- ROXAS, PALAWAN | C31: 43453 | D31: LGU Busuanga | E31: Water System Project | G31: Brgy. Salvacion, Sto Niño, San Isidro, Maglalambay and Cheey in Busuanga, Palawan | H31: Water System | I31: Tagbanua ICCs | J31: With Memo #: 2019-03-167 re: Evaluation Report Additional Documents | K31: Validation completed
A32: =A31+1 -> 30 | B32: MIMAROPA- ROXAS, PALAWAN | C32: 43497 | D32: NAPOCOR | E32: 69KV Roxas -Taytay Tansmission Line Project | G32: National Highway, Roxaz to Taytay, Palawan | H32: Enegry | I32: no data or document attached | J32: for MOA renegotiation | K32: Ongoing FPIC process
A33: =A32+1 -> 31 | B33: MIMAROPA- ROXAS, PALAWAN | C33: 43501 | D33: Path Foundation Philippines Inc. | E33: Fish Right Project | G33: Calamianes Island Group, Palawan | H33: Others | I33: Tagbanua-Calamianes and Agutaynon ICCs | J33: With memo order no: 2019-10-640 re: Evaluation on the Pre-FBI Report | K33: Ongoing FBI
A34: =A33+1 -> 32 | B34: MIMAROPA- ROXAS, PALAWAN | C34: 43525 | D34: Quenny Michiko Raymundo | E34: Royal Island Hotel and Resort | G34: Sitio Malpok, Barangay Lajala, Coron, Palawan | H34: Road Project | I34: no data/document | J34: On going FPIC | K34: Ongoing FPIC process
A35: =A34+1 -> 33 | B35: MIMAROPA- ROXAS, PALAWAN | C35: 43565 | D35: Ms. Geraldine V. San Juan | E35: FlagT | G35: Coron, Palawan | H35: Others | I35: Tagbanua ICCs | J35: corrected documents submitted to the Regional Office for issuance of CNO | K35: FBI completed
A36: =A35+1 -> 34 | B36: MIMAROPA- ROXAS, PALAWAN | C36: 43685 | D36: Tederico G. Titangco | E36: Commercial Sand and Gravel Project CPA (PLW) No. 579-2 | G36: Sitio Barok, Barangay Cataban, Taytay, Palawan | H36: Sand and Gravel | I36: no IP/AD affected within the applied area | J36: Pre-FBI conference conducted and for issuance of memorandum order to conduct FPIC | K36: For FPIC process
A37: =A36+1 -> 35 | B37: MIMAROPA- ROXAS, PALAWAN | C37: 43698 | D37: Caya Coco Island Hotel represented by M. Lawrence Woodleigh | E37: Caya Coco Resort | G37: Sitio Talisay, Brgy. New Barangonan, Linapacan, Palawan | H37: Others | I37: Tagbanua ICCs | J37: for FPIC | K37: For FPIC process
A38: =A37+1 -> 36 | B38: MIMAROPA- ROXAS, PALAWAN | C38: 43710 | D38: Rosalina T. Molina-Gehrer | E38: FlagT | G38: Talking Island, Brgy. Calibangan, Linapacan, Palawan | H38: Eco-Tourism | I38: no data or document attached | J38: Pre-FBI conference conducted and after the GCQ the FBI will be conducted | K38: For FBI
A39: =A38+1 -> 37 | B39: MIMAROPA- ROXAS, PALAWAN | C39: 43717 | D39: Peter Roger Paul Ponnet | E39: Forest Land Use Agreement (FLAg) of Ina Residence | G39: Barangay Poblacion I, Coron, Palawan | H39: Others | I39: no IP/AD affected within the applied area | J39: Memo Order No: 2019-06-414 re: Evaluation Report | K39: FBI completed
A40: =A39+1 -> 38 | B40: MIMAROPA- ROXAS, PALAWAN | C40: 43770 | D40: Community Craft Association of the Philippines Inc. | E40: Scaling-up pf Community-based Enterprises in Coron and Busuanga, Northern Palawan through Forest Conservation | G40: Brgy. Bintuan, Coron Northern Palawan and Calawit Island, Brgy. Buluang Busuanga Northern Palawan | H40: Others | I40: no data or document attached | J40: Validation conducted | K40: Validation completed
A41: =A40+1 -> 39 | B41: MIMAROPA- ROXAS, PALAWAN | C41: 43775 | D41: Palawan Estate Corporation | E41: Forest Land Grazing Management Agreement (FLGMA) | G41: Barangay Lajala, Coron, Palawan | H41: FLGMA | I41: Tagbanua Calamianen | J41: For FPIC (1st meeting conducted) | K41: Ongoing FPIC process
A42: =A41+1 -> 40 | B42: MIMAROPA- ROXAS, PALAWAN | C42: 43801 | D42: The Turtle Sanctuary Palawan Core Inc. | E42: FLaT Application for Beach Resort | G42: Sitio Barong-barong, Brgy. Port Baton, San Vicente, Palawan | H42: Others | I42: no data or document attached | J42: memo #: 2021-02-02 Pre FBI conducted | K42: Ongoing FBI
A43: =A42+1 -> 41 | B43: MIMAROPA- ROXAS, PALAWAN | C43: 43833 | D43: Mr. Gerardo U. Abaniel | E43: Commercial Sand and Gravel | G43: Brgy. Langogan, Puerto Prinsesa, Palawan | H43: Sand and Gravel | I43: Tagbanua and Batak ICCs | K43: In active CP application
A44: =A43+1 -> 42 | B44: MIMAROPA- ROXAS, PALAWAN | C44: 43837 | D44: Ms. Rosalia T. Molina-Gehrer | E44: Forest Land Use Agreement (FLAgT) for Tourism Purposes | G44: Takiling Island, Brgy. Calibangbangan, Linapacan, Palawan | H44: Others | I44: no data or document attached | J44: Pre-FBI conference conducted and after the GCQ the FBI will be conducted | K44: For FBI
A45: =A44+1 -> 43 | B45: MIMAROPA- ROXAS, PALAWAN | C45: 43845 | D45: Evan Yousef Vinluan | E45: FlagT | G45: Sitio Abangan, Brgy. Guadalupe, Coron, Palawan | H45: Others | I45: no data or document attached | J45: WO#: 195-2021/ Pre FBI conducted | K45: Ongoing FBI
A46: =A45+1 -> 44 | B46: MIMAROPA- ROXAS, PALAWAN | C46: 43850 | D46: Municipal Government of Aborlan C/O Municipal Mayor | E46: Expansion of Aborlan Level III Water System in Brgy. Apoc-Apoc, Mabini and Magsaysay | G46: Brgy. Apoc-Apoc, Mabini and Magsaysay | H46: Water System | I46: Tagbanua ICCs | K46: In active CP application
A47: =A46+1 -> 45 | B47: MIMAROPA- ROXAS, PALAWAN | C47: 44012 | D47: Ecofarm System Resources, Inc | E47: Pearl Farm | G47: Capari Island, Brgy. San Isidro, Busuanga, Palawan | H47: Plantation | I47: Tagbanua Calamianen ICCs | J47: for FPIC/ Pre FPIC conducted | K47: Ongoing FPIC process
A48: =A47+1 -> 46 | B48: MIMAROPA- ROXAS, PALAWAN | C48: 44044 | D48: Philipe Fankhauser represented by Deogracias S. Velasco | E48: FlagT | G48: Talacanen Island, Brgy. Busybees, Taytay, Palawan | H48: Others | I48: Tagbanua Tandulanen ICCs | J48: for compilation of FPIC documents | K48: FPIC completed
A49: =A48+1 -> 47 | B49: MIMAROPA- ROXAS, PALAWAN | C49: 44062 | D49: Travisland Archipelago Inc. represented by Dr. Michael Relch & Mr. Gerson A. Fabon | E49: Resort | G49: Pesed Lagoon, Brgy. Banuang Daan, Coron, Palawan | H49: Others | I49: no data or document attached | J49: FPIC ongoing | K49: Ongoing FPIC process
A50: =A49+1 -> 48 | B50: MIMAROPA- ROXAS, PALAWAN | C50: 44077 | D50: Culna Renewable Energy Corp. | E50: Solar Energy Service Contract (SESC) Solar PV- Diesel Hybrid Power Generation | G50: Sitio Lalana, Brgy. San Miguel, Linapacan, Palawan | H50: Energy | I50: no data or document attached | J50: For FBI | K50: For FBI
A51: =A50+1 -> 49 | B51: MIMAROPA- ROXAS, PALAWAN | C51: 44078 | D51: Beatriz S. Zobel De Ayala | E51: SAPA for Organic Farming | G51: Sitio Maypa, Brgy. Pacol, Taytay, Palawan | H51: Others | I51: Tagbanua-Tandulanen ICCs | J51: FBI conducted | K51: FBI completed
A52: =A51+1 -> 50 | B52: MIMAROPA- ROXAS, PALAWAN | C52: 44081 | D52: The Heirs of Teofilo Gabuco respresented by Mr. Ramito Gabuco | E52: Social Industrial Forest Management Agreement (SIFMA) Application with DENR with an area od 9,657 square meters | G52: Sitio Pabuay, Brgy. Villa Paz, El Nido, Palawan | H52: Forest Management | I52: no data or document attached | J52: FBI conducted | K52: FBI completed
A53: =A52+1 -> 51 | B53: MIMAROPA- ROXAS, PALAWAN | C53: 44120 | D53: PLDT represented by Engr. Allan R. Plete | E53: Domestic Submarine Cable Project Area 2. Segment 29B | G53: Brgy. Turda, Coron, Palawan | H53: Telecommunication | I53: no data or document attached | J53: FPIC ongoing | K53: Ongoing FPIC process
A54: =A53+1 -> 52 | B54: MIMAROPA- ROXAS, PALAWAN | C54: 44123 | D54: FLV Energy Corporation | E54: Hybrid Power Project (Hikari 1 Hybrid Power Porject) | G54: Brgy. Bulalacao, Coron, Palawam | H54: Energy | I54: no data or document attached | J54: for issuance of mmorandum order to conduct FBI | K54: For FBI
A55: =A54+1 -> 53 | B55: MIMAROPA- ROXAS, PALAWAN | C55: 44123 | D55: Elmer B. Diokno | E55: Wood Products Trading | G55: Sitio Arado I, Brgy. Poblacion, Taytay, Palawan | H55: Others | I55: no data or document attached | J55: For FBI | K55: For FBI
A56: =A55+1 -> 54 | B56: MIMAROPA- ROXAS, PALAWAN | C56: 44127 | D56: Ramito Gabuco | E56: SIFMA | G56: So. Abuay, Brgy. Villa Paz, El Nido, Palawan | H56: Forest Management | I56: Tagbanua ICCs | J56: FBI conducted | K56: FBI completed
A57: =A56+1 -> 55 | B57: MIMAROPA- ROXAS, PALAWAN | C57: 44132 | D57: Elmer B. Diokno | E57: Wood and Products Trading | G57: Sitio Arado I, Brgy. Poblacion, Taytay, Palawan | H57: Others | I57: no data or document attached | J57: For FBI | K57: For FBI
A58: =A57+1 -> 56 | B58: MIMAROPA- ROXAS, PALAWAN | C58: 44134 | D58: Travisland Archipelago Inc., rep. by Dr. Michael Reich | E58: Floating Cottages | G58: Brgy. Banuang Daan, Coron, Palawan | H58: Others | I58: Tagbanua ICCs | J58: FPIC on going | K58: Ongoing FPIC process
... A80: =A79+1 -> 78 | B80: MIMAROPA- ROXAS, PALAWAN | C80: 44763 | D80: New Belvia Renewables,Inc. (NBRI) | E80: Solar Power Plant Project | G80: Brgy. Kemdeng, San Vicente, Palawan | H80: Energy | I80: no data or document attached | J80: Pre FBI conducted for signature of applicant in WFP | K80: For FBI
A81: =A80+1 -> 79 | B81: MIMAROPA- ROXAS, PALAWAN | C81: 08/ 26/ 2014 | D81: Coron Adventurist Resort Corporation | E81: FLAgt Project | G81: Nici Island Palawan, Barangay Luac, Culion, Palawan | H81: Others | I81: no IP/AD affected within the applied area | J81: FBI report submitted for issuance of CNO | K81: FBI completed
A82: =A81+1 -> 80 | B82: MIMAROPA- ROXAS, PALAWAN | C82: 42146 | D82: Gemmuel Fabia | E82: Commercial Sand and Gravel Project CPA (PLW) No. 679 | G82: Sugod River, Barangay Cheey, Busuanga, Palawan | H82: Sand and Gravel | I82: Tagbanua ICCs | J82: For submission of original title by the proponent for issuance of CNO. | K82: FBI completed
A83: =A82+1 -> 81 | B83: MIMAROPA- ROXAS, PALAWAN | C83: 42459 | D83: Malcapuya Regency Inc. | E83: Forest Land Use Agreement (FLAg) for Tourism | G83: Malcapuya Island, Barangay Bulalacao, Coron Palawan | H83: Others | I83: Tagbanua ICCs | J83: letter sent to the proponent on March, 2023; for MOA validation and signing | K83: Ongoing FPIC process
A84: =A83+1 -> 82 | B84: MIMAROPA- ROXAS, PALAWAN | C84: 43243 | D84: LGU of the Municipality San Vicente, Palawan | E84: Sanitary Landfill Project | G84: Sitio Canadgan, Barangay Alimangunuan,San Vicente, Palawan | H84: Government | I84: no data/document | J84: validation conducted | K84: Validation completed
A85: =A84+1 -> 83 | B85: MIMAROPA- ROXAS, PALAWAN | C85: 43276 | D85: El Nido Enclaves Resort | E85: Resort for Tourism Purposes | G85: Sitio Pangatangan, Barangay Pasadena, El Nido, Palawan | H85: Others | I85: no data/document | J85: FBI conducted | K85: FBI completed
A86: =A85+1 -> 84 | B86: MIMAROPA- ROXAS, PALAWAN | C86: 43390 | D86: Powersource Philippines Inc. | E86: Tumbod Electrification Project | G86: Barangay Tumbod, Taytay,Palawan | H86: Energy | I86: no data/document | J86: FBI was conducted from March 9 & 13, 2020 and the subsequent report was handcarried by the proponent on March 16, 2020 for issaunce of memorandum order to conduct FPIC process | K86: For FPIC process
A87: =A86+1 -> 85 | B87: MIMAROPA- ROXAS, PALAWAN | C87: 43423 | D87: Smart Communication Incorporated | E87: Construction of Cell Site Tower | G87: Barangay Buenavista, Coron, Palawan | H87: Telecommunication | I87: Tagbanua ICCs | J87: Memo Order No: 2018-07-354/ FBI conducted | K87: FBI completed
A88: =A87+1 -> 86 | B88: MIMAROPA- ROXAS, PALAWAN | C88: 43605 | D88: Rosesamy C. Apolinario | E88: Special Use Agreement for Protected Area | G88: Sitio Kiminawit, Barangay Bebeledan, El Nido, Palawan | H88: Others | I88: Tagbanua/Tandulanen ICC | J88: FBI report submitted and for issuance of memorandum order for the conduct of FPIC process | K88: For FPIC process
A89: =A88+1 -> 87 | B89: MIMAROPA- ROXAS, PALAWAN | C89: 43552 | D89: Lawrence R. Woodleigh | E89: Cayo-Coco Island Hostel | G89: Sitio Talisay, Barangay Barangunan, Linapacan, Palawan | H89: Others | I89: Tagbanua Calamian | J89: for FPIC | K89: For FPIC process
A90: =A89+1 -> 88 | B90: MIMAROPA- ROXAS, PALAWAN | C90: 43615 | D90: La Spiaggia Landholdings Corporation | E90: Native Guesthouse Development | G90: Sitio Lacdayan, Barangay Cheey, Busuanga, Palawan | H90: Others | I90: no IP/AD affected within the applied area | J90: For FBI after the GCQ is lifted. | K90: For FBI
A91: =A90+1 -> 89 | B91: MIMAROPA- ROXAS, PALAWAN | C91: 43640 | D91: LGU of San Vicente represented by Hon. Reynaldo D. Rodriguez, IPMR | E91: Renovation of Tribal Hall | G91: Barangay Alimanguaan, Sto. Nino, Binga, Caruray, Port Barton, all in San Vivcente Palawan | H91: Government | I91: Tagbanua-Tandulanen | J91: validation report submitted | K91: Validation completed
A92: =A91+1 -> 90 | B92: MIMAROPA- ROXAS, PALAWAN | C92: 43640 | D92: LGU of San Vicente | E92: Adoption of Ancestral Domain Investment Plan for Health 2018-2020 | G92: Barangay Alimanguan, Sto. Nino, Binga, Caruray and Port Barton, all in San Vicente Palawan | H92: Government | I92: no IP/AD affected within the applied area | J92: validation report submitted | K92: Validation completed
A93: =A92+1 -> 91 | B93: MIMAROPA- ROXAS, PALAWAN | C93: 43738 | D93: Frederick Sariego | E93: Commercial Sand and Gravel Project | G93: Malabnao River, Barangay San Rafael, Busuanga, Palawan | H93: Sand and Gravel | I93: no data/document | J93: For pre-FBI conference after the GCQ is lifted. | K93: For FBI
... A98: =A97+1 -> 96 | B98: MIMAROPA - PALAWAN PROVL OFFICE | C98: 2019 | D98: Abegail R. Tablazon | E98: Commercial Sand and Gravel | G98: Brgy. Maoyon, Puerto Princesa, Palawan | H98: Sand and Gravel | I98: no data or document attached | J98: FBI Conducted | K98: FBI completed
A99: =A98+1 -> 97 | B99: MIMAROPA - PALAWAN PROVL OFFICE | C99: 2019 | E99: Quarry | G99: Brgy. Maoyon, Puerto Princesa City, Palawan | H99: Sand and Gravel | I99: Tagbanua ICCs | K99: In active CP application
A100: =A99+1 -> 98 | B100: MIMAROPA - PALAWAN PROVL OFFICE | C100: 42068 | D100: Mr. Elroy John M. Hagerdorn | E100: SIFMA | G100: Brgy. Inarawan, Puerto Prinsesa, Palawan | H100: Forest Management | I100: Tagbanua ICCs | J100: FBI Conducted;( waiting for the issuance of CNO) | K100: FBI completed
A101: =A100+1 -> 99 | B101: MIMAROPA - PALAWAN PROVL OFFICE | C101: 42086 | D101: Edward S. Hagedorn represented by Bea V. Lucas | E101: Forest Land Use Agreement for Tourism Purposes (FLAgT) | G101: Rita Island, Barangay Bahile, Puerto Princesa City | H101: Others | I101: no data/document | J101: FBI Conducted (waiting for issuance of CNO) | K101: FBI completed
A102: =A101+1 -> 100 | B102: MIMAROPA - PALAWAN PROVL OFFICE | C102: 42114 | D102: Mr. Rafael Paulo F. Abesamis | E102: West Bacungan View Deck Project | G102: Sitio Nagtabon, Brgy. Bacungan, Puerto Prisensa City, Palawan | H102: Others | I102: Tagbanua ICCs | J102: No FPIC | K102: In active CP application
A103: =A102+1 -> 101 | B103: MIMAROPA - PALAWAN PROVL OFFICE | C103: 42258 | D103: Ms. Lilibeth N. Aribon | E103: Commercial Sand and Gravel Quarry | G103: Tugbuan River, Brgy. Babuyan, Puerto Prinsesa City, Palawan | H103: Sand and Gravel | I103: Tagbanua ICCs | J103: For FPIC | K103: In active CP application
A104: =A103+1 -> 102 | B104: MIMAROPA - PALAWAN PROVL OFFICE | C104: 42306 | D104: Cecelia M. Marcelo | E104: Commercial Sand and Gravel Permit No. 336 | G104: Barangay Sta. Lourdes, Puerto Princesa City, Palawan | H104: Sand and Gravel | I104: no data/document | J104: For FPIC | K104: In active CP application
A105: =A104+1 -> 103 | B105: MIMAROPA - PALAWAN PROVL OFFICE | C105: 42331 | D105: LGU of Aborlan, Palawan | E105: Water Supply Project | G105: Barangays of Sagpanagan, Culandanum,and Cabigaan,Aborlan, Palawan | H105: Water System | I105: no data/document | J105: No FPIC | K105: In active CP application
A106: =A105+1 -> 104 | B106: MIMAROPA - PALAWAN PROVL OFFICE | C106: 42360 | D106: National Irrigation Administration | E106: Ibato-Iraan Small Resevoir Irrigation Project | G106: Brgy.Sagpangan, Aborlan, Palawan | H106: Irrigation Project | I106: Tagbanua ICCs | J106: MOA | K106: In active CP application
A107: =A106+1 -> 105 | B107: MIMAROPA - PALAWAN PROVL OFFICE | C107: 43435 | D107: LGU of Aborlan, Palawan | E107: Concreting of Access Road and Construction of Evacuation Center | G107: Municipality of Aborlan | H107: Road Project | I107: no IP/AD affected within the applied area | J107: On process | K107: Ongoing Validation
A108: =A107+1 -> 106 | B108: MIMAROPA - PALAWAN PROVL OFFICE | C108: 2020 | D108: Maria Liza Dela Cruz | E108: Socialized Industrial Forest Management Agrement (SIFMA) | G108: Sitio Bubusawen, Baranagay Apurawan, Aborlan, Palawan | H108: Forest Management | I108: Tagbanua ICCs | J108: For FPIC | K108: For FPIC process
A109: =A108+1 -> 107 | B109: MIMAROPA - PALAWAN PROVL OFFICE | C109: 43861 | D109: Apolinario C. Bacaltos | E109: Sand and Gravel Project | G109: Brgy. Apurawan, Aborlan, Palawan | H109: Sand and Gravel | I109: Tagbanua ICCs | J109: For FBI | K109: For FBI
A110: =A109+1 -> 108 | B110: MIMAROPA - PALAWAN PROVL OFFICE | C110: 44055 | D110: MRS. Roselyn A, Palay | E110: Commercial Sand and Gravel | G110: Tanabag River, Brgy. Puerto Prinsesa City, Palawan | H110: Sand and Gravel | I110: Batak ICCs | J110: FBI Conducted | K110: FBI completed
A111: =A110+1 -> 109 | B111: MIMAROPA - PALAWAN PROVL OFFICE | C111: 44069 | D111: Mr, Edgar B. Eleazar | E111: Commercial Sand and Gravel | G111: Tugbuan River, Brgy. Babuyan, Puerto Prinsesa City, Palawan | H111: Sand and Gravel | I111: Tagbanua ICCs | J111: FBI Conducted | K111: FBI completed
... A117: =A116+1 -> 115 | B117: MIMAROPA - PALAWAN PROVL OFFICE | C117: 42061 | D117: Mr. Alejandro D. Cabingao | E117: Commercial Sand and Gravel CPA (PLW) No. 891 | G117: Brgy. Bagong Bayan, Puerto Princesa City, Palawan | H117: Sand and Gravel | I117: Tagbanua ICCs | J117: CP | K117: FPIC completed
A118: =A117+1 -> 116 | B118: MIMAROPA-ODIONGAN, ROMBLON CSC | C118: 2014 | D118: Sunwest Water & Electric Co., Inc. (SUWECO) | E118: HSC 2013-09-292 | G118: Libertad, Odiongan, Romblon | H118: Mini-hydropower | I118: Bantoanon | J118: Letter sent to Dir. Mario Marasigan of DOE re: submission on docs. | K118: Ongoing evaluation of CP application | L118: 8
A119: =A118+1 -> 117 | B119: MIMAROPA-ODIONGAN, ROMBLON CSC | C119: 2014 | D119: Sunwest Water & Electric Co., Inc. (SUWECO) | E119: HSC 2013-09-293 | G119: Gabawan | H119: Mini-hydropower | I119: Bantoanon | J119: Letter sent to Dir. Mario Marasigan of DOE re: submission on docs. | K119: Ongoing evaluation of CP application
A120: =A119+1 -> 118 | B120: MIMAROPA-ODIONGAN, ROMBLON CSC | C120: 2014 | D120: Sunwest Water & Electric Co., Inc. (SUWECO) | E120: HSC 2013-09-294 | G120: Sigcop | H120: Mini-hydropower | I120: Bantoanon | J120: Letter sent to Dir. Mario Marasigan of DOE re: submission on docs. | K120: Ongoing evaluation of CP application
A121: =A120+1 -> 119 | B121: MIMAROPA-ODIONGAN, ROMBLON CSC | C121: 2015 | D121: Sunwest Water & Electric Co., Inc. (SUWECO) | E121: HSC 2013-09-296 | G121: San Andres | H121: Mini-hydropower | I121: Ati | J121: Letter sent to Dir. Mario Marasigan of DOE re: submission on docs.; Memo Order No. 2015-06-393 DTD. 6/5/15 issued re evaluation of WFP for FBI | K121: In active CP application
A122: =A121+1 -> 120 | B122: MIMAROPA-ODIONGAN, ROMBLON CSC | C122: 2015 | D122: GMA Network | E122: Renewal of SLUP | G122: Triple Peak, San Isidro, Sta Maria | H122: Others | I122: Ati | J122: Work Order No. 2015-024 dtd. 02/17/15 issued re: Constitution of FBI Team; Work Order No. 2015-105 dtd. 09/30/15 issued re constitution of FPIC team; Letter dtd. 1/14/19 sent for submission of new endorsement for FLAG. Work Order No. 2015-024 dtd. 02/17/15 issued re: FOR FPIC . reconstitution of FPIC team | K122: For FPIC process
A123: =A122+1 -> 121 | B123: MIMAROPA-ODIONGAN, ROMBLON CSC | C123: 2018 | D123: Sunwest Water & Electric Co., Inc. (SUWECO) | E123: Solar Project | G123: 3 | H123: Energy | I123: Bantoanon | J123: Letter dtd. 4/19/18 sent re submission of requirements; Work Order No. 2019-36 dtd. April 29, 2019. | K123: In active CP application
A124: =A123+1 -> 122 | B124: MIMAROPA-ODIONGAN, ROMBLON CSC | C124: 2019 | D124: RICARTE M.MAGCALAYO | E124: NIPA PLANTATION | G124: So. Guba, Barangay Guinbirayan, Sta Fe | H124: Plantation | I124: Ati | J124: Letter dated October 22, 2019 was sent to the applicant re: lacking documents; Memo No. 2019-10-635 dated October 22, 2019 -Letter advise to Odiongan CSC. For completion of Application requirements | K124: Ongoing evaluation of CP application
A125: =A124+1 -> 123 | B125: MIMAROPA-ODIONGAN, ROMBLON CSC | C125: 2012 | D125: LGU of Ferrol, Romblon/ARCP2 | G125: Hinag-oman, Ferrol, Romblon | H125: Government | I125: Ati | J125: for release upon payment of fee. For release upon payment of the fee. | K125: Validation completed
A126: =A125+1 -> 124 | B126: MIMAROPA-ODIONGAN, ROMBLON CSC | C126: 2016 | D126: Provincial Government of Romblon | E126: Brgy Pato-o Proper to So. Aurora Farm to Market Road with Two Bridges | G126: Odiongan, Romblon | H126: Road Project | I126: Bantoanon | K126: In active CP application
A127: =A126+1 -> 125 | B127: MIMAROPA-ODIONGAN, ROMBLON CSC | C127: 2019 | D127: Romblon Electric Cooperative, Inc. | E127: 900 KW Wind Turbine Power Plant | G127: Bagacay, Lonos and Agnay | H127: Energy | I127: Bantoanon | K127: In active CP application
A128: =A127+1 -> 126 | B128: MIMAROPA-SAN JOSE OCCI MINDORO CSC | C128: 42801 | D128: Emerlito L. Ramos III | E128: Forest Land Grazing Management Agreement (FLGMA) | G128: Sitios Managbong, Batangan and Morong, Barangay Manoot, Rizal, Occidental Mindoro | H128: FLGMA | I128: no data/document | J128: Endorsed by Noe Raul A. Zoleta issued last August 03, 2017. For Cancellation of CP Application write letter of cancellatio . Proponent did not proceed. | K128: In active CP application
A129: =A128+1 -> 127 | B129: MIMAROPA-SAN JOSE OCCI MINDORO CSC | C129: 42958 | D129: Bluemax Tradelink Inc. | E129: Mineral Processing Permit | G129: Barangay Malaawan, Municipality of Rizal, Occidental Mindoro | H129: Mining | I129: no IP/AD affected within the applied area | J129: Work Order No. 2017-54 Series of 2017. Subject for FBI | K129: In active CP application
A130: =A129+1 -> 128 | B130: MIMAROPA-SAN JOSE OCCI MINDORO CSC | C130: 43490 | D130: NIA Occidental Mindoro | E130: Impounding Reservoir | G130: Sitio Matangcob, Paclolo, Magsaysay, Occidental | H130: Irrigation Project | I130: no data/document | J130: Memorandum No. 011-019 Series of 2019. For CP Application - Did not proceed . IP not in favor of project. | K130: In active CP application
A131: =A130+1 -> 129 | B131: MIMAROPA-SAN JOSE OCCI MINDORO CSC | C131: 43537 | D131: Elmer S. Francisco | E131: Forest Land Grazing Management Agreement (FLGMA) | G131: Sitio's Panarowan and Malawao, Barangay Naibuan, San Jose, Occidental Mindoro | H131: FLGMA | I131: Hanunuo Mangyan | J131: Endorsed by Noe Raul A. Zoleta last February 26, 2020 . No CP. Proponent did not proceed with the project. | K131: In active CP application
...

Sheet REGION 5
A1: NO | B1: REGION | C1: DATE OF FILING OF CP APPLICATION | D1: NAME OF PROPONENT | E1: NAME OF PROJECT | F1: PROJECT COST | G1: LOCATION | H1: Type of Project | I1: AFFECTED AD/ICC/IP (for CP with ongoing FPIC) | J1: STATUS OF APPLICATION | K1: STATUS
A3: 1 | B3: V | C3: 45170 | D3: Orophil Stonecraft Inc. (OSI) | E3: Mineral exploration denominated as EPA-IVA-190 | G3: Municipalities of Tagkawayan, and Labo, Provinces of Quezon and Camarines Norte | H3: Mining Project | I3: Labo AD/Manide | J3: Under compliance by the FPIC Team on the RRT recommendations; A Memorandum was issued to the FPIC Team to act on the request for reconsideration. | K3: FPIC completed | L3: =COUNTIF(K1:K74, "FPIC completed") -> 2
A4: =A3+1 -> 2 | B4: V | C4: 45524 | D4: Anncore Phils Venture Inc. | E4: Mineral exploration denominated as EXPA-000266-V | G4: Municipality of Capalonga , Province of Camarines Norte | H4: Mining Project | I4: Capalonga AD/Manide | J4: Pre-FBI Conference report was reviewed by the ORD, with comments, subject to revision by the FBI Team. A Memorandum was issued to the FBI Team, providing them a sample WFP, for proper guidance. | K4: For FBI | L4: 2
A5: =A4+1 -> 3 | B5: V | C5: 45344 | D5: Mr. Joselee O. Dacuba | E5: Patitinan Tigao Beach Resort/Forest Land Grazing Management Agreement (FLGMA) | G5: Patitinan, Sagñay, Camarines Sur | H5: FLGMA/Resort | I5: Sagñay AD/Agta/Agta-Tabangnon | J5: A letter was sent to the proponent on March 28, 2025, requiring them to submit an endorsement from CENRO, and a clear copy of the indicative map. A follow-up letter was likewise sent on June 19, 2025. | K5: Ongoing evaluation of CP application | L5: =COUNTIF(K1:K74, "Ongoing evaluation of CP application") -> 1
A6: =A5+1 -> 4 | B6: V | C6: 45008 | D6: LGU of Sagñay, Camarines Sur | E6: Sagñay Mariculture Park Project | G6: Turague, Sibaguan and Bongalon, Sagñay, Camarines Sur | H6: Eco-Tourism Project | I6: Sagñay AD/Agta/Agta-Tabangnon | J6: Memorandum Order No. ADO-RMD 2025-06-515, dated June 6, 2025, issued by ADO, on the Evaluation of the FPIC Report, was forwarded to the FPIC Team, which compliance is on process. | K6: FPIC completed
A7: =A6+1 -> 5 | B7: V | C7: 45520 | D7: Mr. Wilhelm L. Nieva | E7: Lologon Mountain Resort/Environmentally Critical Area (ECA) | G7: San Rafael, Buhi, Camarines Sur | H7: ECA/Resort | I7: Buhi AD/Agta/Agta-Tabangnon | J7: Decision Meeting & MOA Negotiation was conducted on June 9, 2025. | K7: Ongoing FPIC process | L7: =COUNTIF(K1:K74, "Ongoing FPIC Process") -> 2
A8: =A7+1 -> 6 | B8: V | C8: 45219 | D8: Mr. Manuel T. Pahuyo | E8: Dong Valenz Viewdeck Cafe and Abaca Trading | G8: Villaflorida, Ocampo, Camarines Sur | H8: restaurant/store | I8: Ocampo AD/Agta/Agta-Tabangnon | J8: Decision Meeting & MOA Negotiation was conducted on June 26, 2025. | K8: Ongoing FPIC process
A9: 7 | B9: V | C9: 45451 | D9: National Power Corporation | E9: 0.094 MW Atulayan Diesel Power Plant | G9: Atulayan, Sagñay, Camarines Sur | H9: Diesel Power Plant | I9: Sagñay AD/Agta/Agta-Tabangnon | J9: FBI Report was submitted on June 13, 2025; Under review by the RRT. | K9: For FPIC process
A10: 8 | B10: V | C10: 45810 | D10: Globe Telecom Inc. | E10: SLZ JEDI Core Backbone Project | G10: Sagñay, Camarines Sur | H10: Fiber Optic Backbone Installation | I10: Sagñay AD/Agta/Agta-Tabangnon | J10: WFP was approved; Order of Payment of FBI Fee was sent to the proponent, dated July 9, 2025. | K10: For FBI

Sheet REGION 67
A1: NO | B1: REGION | C1: YEAR | D1: DATE OF FILING OF CP APPLICATION | E1: NAME OF PROPONENT | F1: NAME OF PROJECT | G1: PROJECT COST | H1: LOCATION | I1: Type of Project | J1: AFFECTED AD/ICC/IP (for CP with ongoing FPIC) | K1: STATUS OF APPLICATION | L1: STATUS
B3: NIR - Negros Island Region (RA 1200) + Siquujor Reg 6 - Panay Island and Guimaras Reg 7 - Cebu and Bohol Reg 8 - Whole of Eastern Visayas
A4: 1 | B4: NIR | C4: 2007 | D4: 2007 | E4: Tree Kings, Inc. | F4: IFMA | G4: about 63,036,655 pesos (for 25 years of operation) | H4: Cabatuanan, Basay, Negros Occidental | I4: Forest Management Project | K4: No compliance to LA 51-22-14. | L4: Inactive CP application | M4: =COUNTIF(L1:L74, "In active CP Application") -> 0
A5: =A4+1 -> 2 | B5: NIR | C5: 2009 | D5: 2009 | E5: K & G Mineral Corporation | F5: Exploration Permit Application (EXPA-000158XIII) | G5: estimated cost of exploration: 2,030,000 pesos | H5: Cabatuanan, Basay, Negros Occidental | I5: Mining Project | L5: Inactive CP application
A6: =A5+1 -> 3 | B6: NIR | C6: 2011 | D6: 2011 | E6: HINOBA HOLDINGS, Phils. | F6: Application for Financial & Technical Assistance (AFTA 00002CO) | G6: 11,110,000 pesos | H6: Brgys. Alim, Asia, Buluangan, Damutan, Culipapa, Sangke, Hinoban, Negros Occidental; Brgys; Minaba, Kalamtukan, Tayawan, Cabatuanan, Bongalonan and Maglinao, Bayawan City, Negros Oriental | I6: Mining Project | K6: Feb 21, 2012: remanded back to the Region (lacking documents); submitted lacking docs on 06/11/12; with LAO recommendation (LO 038-06-12); areas in Negros Oriental: Awaiting LAO compliance (as of Oct. 28, 2014) | L6: Inactive CP application
A7: =A6+1 -> 4 | B7: NIR | C7: 2011 | D7: 2011 | E7: ATTY. MANUEL S. GO | F7: Exploration Permit Application (EXPA-0115VII) | G7: page 32: of FPIC report 2,193,000 pesos | H7: Brgy. Kalamtukan, Bayawan City, Negros Oriental | I7: Mining Project | L7: Inactive CP application
A8: =A7+1 -> 5 | B8: NIR | C8: 2012 | D8: 41191 | E8: NIA R6 | F8: Hilabangan River Irrigation Project | G8: estimated cost: 495 million pesos | H8: Bukidnon-ICC of Brgy. Tan-awan, Kabankalan City, Negros Occidental. | I8: Irrigation Project | K8: Finalization of Report coming from the FPIC Team of Negros Occidental Community Service Centers | L8: FPIC completed | M8: =COUNTIF(L1:L74, "FPIC Completed") -> 1
A9: =A8+1 -> 6 | B9: NIR | C9: 2019 | D9: 43780 | E9: SOC Resources, Inc. | F9: Exploration Permit Application denominated as EXPA-000228-VII | G9: No Data | H9: Basay, Negros Oriental | I9: Mining Project | J9: Bukidnon-Magahat | L9: Inactive CP application
A10: =A9+1 -> 7 | B10: NIR | C10: 2022 | D10: 44827 | E10: United Paragon Mining Corporation (UPMC) | F10: Renewal of two (2) Mineral Production Sharing Agreement (MPSA) denominated as (1) MPSA-092-97-VI and (2) MPSA-113-98-VI | G10: 209.941 million dollars (assumption at the time of application is 1$ = 43 pesos) | H10: (1) Brgy. Damutan, Hinoba-an, Negros Occidental (2) Brgy. Manlucahoc, Sipalay City and Municipality of Candoni, Negros Occidental | I10: Mining Project | J10: Bukidnon | K10: FBI already conducted. Awaiting for FBI Report submission as of March 2024 (according to the Field Office): UPMC is currently in the process of relinquishment procedures with DENR-MGB to exclude from UPMC tenement area the 65.3 ha overlapped portion; to date, FO is still waiting for the update from UPMC | L10: Inactive CP application
A11: =A10+1 -> 8 | B11: NIR | C11: 2022 | D11: 44844 | E11: Mr. Nestor V. Lim | F11: Exploration Permit denominated as EXPA-000243-VII | G11: 6005000 | H11: Barangays Banban, Mabato & Maaslum, Ayungon, Negros Oriental | I11: Mining Project | J11: Bukidnon ICC - Brgy. Banban | K11: for conduct of Community Assembly Updated as per FO (as of 2024): The proponent requested that to temporary hold their application (CP Issuance) because they still have other important documents to prepare | L11: Ongoing FPIC process | M11: =COUNTIF(L1:L74, "Ongoing FPIC Process") -> 3
J12: Bukidnon ICC - Brgy. Mabato
A13: =A11+1 -> 9 | B13: NIR | C13: 2022 | D13: 44873 | E13: Ms. Georgita F. Martinez | F13: Special Land Use Permit (SLUP) Silica Sand and Stone Quarrying | H13: Barangay Banban, Ayungon, Negros Oriental | I13: Sand and Gravel | J13: Bukidnon ICC of Brgys. Banban, Mabato and Maaslum, all of the Municipality of Ayungon, Negros Oriental | K13: Awaiting for proof of payment (FPIC); waiting for the final report of the Team (the Community issued a Resolution of Non-Consernt) | L13: For FPIC | M13: =COUNTIF(L1:L74, "For FPIC") -> 1
A14: =A13+1 -> 10 | B14: NIR | C14: 2023 | D14: 45170 | E14: Ayungon Forest Management Organization | F14: Community-Based Forest Management Organization | H14: Brgys. Mabato and Candana-ay, Ayungon, Negros Oriental | I14: Forest Management Project | J14: Bukidnon | K14: with FPIC Work Order (On-going) | L14: Ongoing FPIC process
A15: =A14+1 -> 11 | B15: NIR | C15: 2023 | D15: 2023 | E15: DSWD KALAHI CIDSS NCDDP AF | F15: Concreing of Access Road | H15: Purok Cory, Brgy. Pandanon, Don Salvador Benedicto, Negros Occidental | I15: Government Project | J15: Bukidnon | K15: Dec 12, 2024 - Re-issued work order for Assessment as per PO, they are requesting for the additional but pertinent documents from DSWD | L15: Ongoing evaluation of CP application | M15: =COUNTIF(L1:L74, "Ongoing Evaluation of CP Application") -> 2
A16: =A15+1 -> 12 | B16: NIR | C16: 2023 | D16: 2023 | E16: DSWD KALAHI CIDSS NCDDP AF | F16: Construction of 1-unit 2-classroom High School Building | H16: Brgy. Pinowayan, Don Salvador Benedicto, Negros Occidental | I16: Government Project | J16: Bukidnon | K16: Dec 12, 2024 - Re-issued work order for Assessment as per PO, they are requesting for the additional but pertinent documents from DSWD | L16: Ongoing evaluation of CP application
A17: =A16+1 -> 13 | B17: NIR | C17: 2024 | D17: January 2024 | E17: Limnelios Inc. | F17: 115.004 Mwp Silay Solar on Water PV Power Plant | H17: Brgy. Balaring, Silay, Negros Occidental | I17: Energy | K17: RO is waiting for the FBI report of the re-composed FBI Team | L17: For FBI | M17: =COUNTIF(L1:L74, "For FBI") -> 6
A18: =A17+1 -> 14 | B18: NIR | C18: 2024 | D18: January 2024 | E18: Greenislandspowernergy Corp. | F18: 98.397 MWp EB magalona Solar on Water PV Power Plant | H18: Brgy. Pasil, EB Magalona, Negros Occidental | I18: Energy | K18: FBI Team was re-composed; no further update from the proponent + not yet paying | L18: Inactive CP application
A19: =A18+1 -> 15 | B19: NIR | C19: 2024 | D19: 2024 | E19: Reynold Babor | F19: Industrial Sand and Gravel Permit | G19: 10500000 | H19: Poblacion, Bongalonan, Cabanatuan & Maglinao, Basay, Negros Oriental | I19: Sand and Gravel | J19: Bukidnon | K19: with FPIC Work Order (On-going) | L19: Ongoing FPIC process
A20: =A19+1 -> 16 | B20: NIR | C20: 2025 | D20: April 2025 | E20: Local Government of Kabankalan City, Negros Occidental | F20: Establishment of Local Conservation Area | H20: Brgy. Tagukon, Tampalaon, Oringao, Inapoy, Camingawan iin Kabankalan City, Negros Occidental | I20: Government Project | J20: Bukidnon | K20: CP was not signed by previous EC and commented that a MOA was needed; returned to the Validating Team for compliance | L20: Validation completed | M20: =COUNTIF(L1:L74, "Validation Completed") -> 2
A21: =A20+1 -> 17 | B21: NIR | C21: 2024 | D21: May 2024 | E21: Damutan Agroforestry Farmers Association Inc (DAFFAI) | F21: Community-Based Forest Management Agreement (CBFMA) | G21: 11261560 | H21: So. Soso, Brgys. Damutan in Hinobaan and Brgy. Gatuslao in Candoni, Negros Occidental | I21: Forest Management Project | J21: Bukidnon | K21: Requested for the re-compostion of the FBI Team (not-yet paid) | L21: For FBI
A22: =A21+1 -> 18 | B22: NIR | C22: 2025 | D22: April 2025 | E22: DENR-MGB | F22: Project ORE for the Advanced Characterization of Critical Minerals in Magmatic-Hyrdothermal Deposits | G22: 5049000 | H22: Brgys. Cabatuanan, Maglinao, Bongalonan, Cabalayangan, Actin and Linantayan in Basay, Negros Oriental | I22: Mining | J22: Bukidnon-Magahat | K22: waiting for payment (amount to be deposited in NCIP Account) | L22: For FBI
A23: =A22+1 -> 19 | B23: VI | C23: 2025 | D23: 45776 | E23: Camalig Minerals and Mining Corporation (CMMC) | F23: EXPA 000151VI | G23: 4310000 | H23: (Parcel 1) Brgys. Aglalana, Magdungao, Agtambo, Sarapan, Bacuranan Bayan, Sablongon, Imbang Grande, Talongonan and Jaguimitan in Passi City, Iloilo | I23: Mining | J23: TBD | K23: for FBI | L23: For FBI
H24: (parcel 2) portions of Brgys. Aglalana and Agsirab in Dumarao, Capiz | J24: Ati | K24: waiting for payment (amount to be deposited in NCIP Account) | L24: For FBI
F25: EXPA 000152VI | H25: Brgys. Aglalana, San Juan, Agsirab, Tagubong, Condingle, Tamulalud, Janguslob, Bungsuan and Lawa-an in Dumarao, Capiz | J25: Ati | K25: waiting for payment (amount to be deposited in NCIP Account) | L25: For FBI
A26: =A23+1 -> 20 | B26: VII | C26: 2025 | D26: May 2025 | E26: National Housing Authority | F26: 1. Sierra Bullones Eskaya Resettlement Project | G26: 39412000 | H26: 1. Brgy. Cantaub, Sierra Bullones, Bohol | I26: Government Project - Basic Services | J26: Eskaya | K26: Waiting for the submission of the Validation Report from the Team | L26: Validation completed
F27: 2. Pilar Eskaya Resettlement Project | G27: 19706000 | H27: 2. Brgy. Pilar, Lundag, Pilar, Bohol
A28: =A26+1 -> 21 | B28: VI | C28: 2025 | D28: 45821 | E28: PacificWind Renewables Corp. | F28: Aklan Wind Power Project | G28: 204972000 | H28: Malay and Buruanga, Aklan | I28: Energy | J28: Ati | K28: filed via EVOSS waiting for uploading of proof of payment for OR | L28: Completed (last February 5, 2026) | M28: =COUNTIF(L1:L74, "Ongoing FBI") -> 0
A29: =A28+1 -> 22 | B29: NIR | C29: 2025 | D29: 45821 | E29: PacificWind Renewables Corp. | F29: Mabinay Wind Power Project | G29: 248124000 | H29: Ayungon & Bindoy, Negros Oriental | I29: Energy | J29: Bukidnon and Ata | K29: filed via EVOSS FBI is currently being conducted (July 9-16) | L29: Completed (last January 13, 2026)

Sheet Summary (Status of Application)
A1: Summary of the CP Status Per Region as of July 28, 2025
A2: Regions | B2: Ongoing Evaluation of CP application | C2: For FBI | D2: FBI Ongoing | E2: FBI Completed | F2: For Validation | G2: Validation Ongoing | H2: Validation Completed | I2: For FPIC process | J2: FPIC Ongoing | K2: FPIC Completed | L2: FPIC on Hold | M2: In active CP Application | N2: No Status Indicated/Incomplete | O2: TOTAL
A3: CAR | B3: 10 | C3: 2 | D3: 3 | E3: 4 | F3: ='REGION 12'!$L$48 -> 0 | G3: ='REGION 12'!$L$48 -> 0 | H3: ='REGION 12'!$L$48 -> 0 | I3: 9 | J3: 16 | K3: 18 | L3: ='REGION 12'!$L$48 -> 0 | M3: 16 | N3: 1 | O3: =SUM(B3:N3) -> 79 | P3: 79
A4: I | B4: ='REGION 12'!$L$48 -> 0 | C4: ='REGION 12'!$L$48 -> 0 | D4: 0 | E4: ='REGION 12'!$L$48 -> 0 | F4: ='REGION 12'!$L$48 -> 0 | G4: ='REGION 12'!$L$48 -> 0 | H4: ='REGION 12'!$L$48 -> 0 | I4: 6 | J4: 27 | K4: 15 | L4: ='REGION 12'!$L$48 -> 0 | M4: 32 | N4: 1 | O4: =SUM(B4:N4) -> 81 | P4: 81
A5: II | B5: ='REGION 12'!$L$48 -> 0 | C5: 0 | D5: 14 | E5: ='REGION 12'!$L$48 -> 0 | F5: ='REGION 12'!$L$48 -> 0 | G5: 14 | H5: ='REGION 12'!$L$48 -> 0 | I5: 0 | J5: 11 | K5: 2 | L5: ='REGION 12'!$L$48 -> 0 | N5: ='REGION 12'!$L$48 -> 0 | O5: =SUM(B5:N5) -> 41 | P5: 41
A6: III | B6: 27 | C6: 18 | D6: 9 | E6: ='REGION 12'!$L$48 -> 0 | F6: 6 | G6: ='REGION 12'!$L$48 -> 0 | H6: 4 | I6: 16 | J6: 12 | K6: 18 | L6: ='REGION 12'!$L$48 -> 0 | M6: 4 | N6: ='REGION 12'!$L$48 -> 0 | O6: =SUM(B6:N6) -> 114 | P6: 114
A7: IV-A | B7: ='REGION 12'!$L$48 -> 0 | C7: 3 | D7: 0 | E7: 1 | F7: 3 | G7: ='REGION 12'!$L$48 -> 0 | H7: 0 | I7: 2 | J7: 4 | K7: 5 | L7: ='REGION 12'!$L$48 -> 0 | M7: 0 | N7: 1 | O7: =SUM(B7:N7) -> 19 | P7: 19
A8: IV-B | B8: 8 | C8: 21 | D8: 6 | E8: 25 | F8: 19 | G8: 1 | H8: 8 | I8: 13 | J8: 24 | K8: 13 | L8: ='REGION 12'!$L$48 -> 0 | M8: 87 | N8: ='REGION 12'!$L$48 -> 0 | O8: =SUM(B8:N8) -> 225 | P8: 225
A9: V | B9: 1 | C9: 2 | D9: 0 | E9: 2 | F9: ='REGION 12'!$L$48 -> 0 | G9: ='REGION 12'!$L$48 -> 0 | H9: ='REGION 12'!$L$48 -> 0 | I9: 1 | J9: 2 | K9: ='REGION 12'!$L$48 -> 0 | L9: ='REGION 12'!$L$48 -> 0 | M9: ='REGION 12'!$L$48 -> 0 | N9: ='REGION 12'!$L$48 -> 0 | O9: =SUM(B9:N9) -> 8 | P9: 8
A10: VI/VII | B10: 2 | C10: 6 | E10: ='REGION 12'!$L$48 -> 0 | F10: ='REGION 12'!$L$48 -> 0 | G10: ='REGION 12'!$L$48 -> 0 | H10: 2 | I10: 1 | J10: 3 | K10: ='REGION 67'!$M$8 -> 1 | L10: ='REGION 12'!$L$48 -> 0 | M10: 7 | O10: =SUM(B10:N10) -> 22 | P10: 22
A11: IX | B11: 2 | C11: 5 | D11: 3 | E11: 54 | F11: ='REGION 12'!$L$48 -> 0 | G11: ='REGION 12'!$L$48 -> 0 | H11: 35 | I11: 13 | J11: 25 | K11: 35 | L11: 1 | M11: 12 | N11: 1 | O11: =SUM(B11:N11) -> 186 | P11: 186
A12: X | B12: ='REGION 12'!$L$48 -> 0 | C12: ='REGION 12'!$L$48 -> 0 | D12: 0 | E12: ='REGION 12'!$L$48 -> 0 | F12: ='REGION 12'!$L$48 -> 0 | G12: ='REGION 10'!$L$71 -> 18 | H12: ='REGION 10'!$L$45 -> 1 | I12: 0 | J12: 11 | K12: ='REGION 10'!$L$62 -> 10 | L12: ='REGION 12'!$L$48 -> 0 | M12: ='REGION 10'!$L$3 -> 8 | N12: ='REGION 10'!$L$5 -> 24 | O12: =SUM(B12:N12) -> 72 | P12: 72
A13: XI | B13: 4 | C13: 9 | D13: 1 | E13: 6 | F13: 25 | G13: ='REGION 12'!$L$48 -> 0 | H13: 22 | I13: 29 | J13: 32 | K13: 537 | L13: 1 | M13: 242 | N13: 1018 | O13: =SUM(B13:N13) -> 1926 | P13: 1926 | Q13: =O13-P13 -> 0
A14: XII | B14: 0 | C14: ='REGION 12'!$L$51 -> 0 | D14: 0 | E14: ='REGION 12'!$L$47 -> 2 | F14: ='REGION 12'!$L$48 -> 0 | G14: ='REGION 12'!$L$49 -> 0 | H14: 20 | I14: ='REGION 12'!$L$48 -> 0 | J14: ='REGION 12'!$L$48 -> 0 | K14: ='REGION 12'!$L$52 -> 20 | L14: ='REGION 12'!$L$46 -> 0 | M14: ='REGION 12'!$L$54 -> 1 | N14: ='REGION 12'!$L$53 -> 0 | O14: =SUM(B14:N14) -> 43 | P14: 43
A15: XIII | B15: 2 | C15: 4 | D15: 2 | E15: ='REGION 13'!$N$292 -> 4 | F15: ='REGION 13'!$N$293 -> 20 | G15: 12 | H15: ='REGION 13'!$N$301 -> 31 | I15: 5 | J15: 1 | K15: ='REGION 13'!$N$299 -> 17 | L15: ='REGION 13'!$N$291 -> 4 | M15: ='REGION 13'!$N$300 -> 9 | N15: 186 | O15: =SUM(B15:N15) -> 297 | P15: 297
A16: TOTAL | B16: =SUM(B3:B15) -> 56 | C16: =C15+C14+C13+C12+C11+C10+C9+C8+C7+C6+C5+C4+C3 -> 70 | D16: =SUM(D3:D15) -> 38 | E16: =E15+E14+E13+E12+E11+E10+E9+E8+E7+E6+E5+E4+E3 -> 98 | F16: =F15+F14+F13+F12+F11+F10+F9+F8+F7+F6+F5+F4+F3 -> 73 | G16: =G15+G14+G13+G12+G11+G10+G9+G8+G7+G6+G5+G4+G3 -> 45 | H16: =H15+H14+H13+H12+H11+H10+H9+H8+H7+H6+H5+H4+H3 -> 123 | I16: =SUM(I3:I15) -> 95 | J16: =SUM(J3:J15) -> 168 | K16: =SUM(K3:K15) -> 691 | L16: =L15+L14+L13+L12+L11+L10+L9+L8+L7+L6+L5+L4+L3 -> 6 | M16: =M15+M14+M13+M12+M11+M10+M9+M8+M7+M6+M5+M4+M3 -> 418 | N16: =N15+N14+N13+N12+N11+N10+N9+N8+N7+N6+N5+N4+N3 -> 1232 | O16: =O15+O14+O13+O12+O11+O10+O9+O8+O7+O6+O5+O4+O3 -> 3113

Sheet REGION 9
B1: REGION | C1: DATE OF FILING OF CP APPLICATION | D1: NAME OF PROPONENT | E1: NAME OF PROJECT | F1: PROJECT COST | G1: LOCATION | H1: Type of Project | I1: AFFECTED AD/ICC/IP (for CP with ongoing FPIC) | J1: STATUS OF APPLICATION | K1: STATUS
A3: 1 | B3: IX | C3: 44414 | D3: LGU TIGBAO | E3: 18 VARIOUS PROJECT UNDER KC PAMANA IP CDD OF DSWD | G3: 18 BARANGAYS, TIGBAO, ZDS | H3: Government project | J3: On-Going FPIC process | K3: Ongoing FPIC process
A4: 2 | B4: IX | C4: 44447 | D4: PENRO-PLGU ZAMBO. DEL SUR | E4: PROPOSED VARIOUS BARANGAY DEVELOPMENT PROJECTS | G4: 2ND DISTRICT OF ZDS | H4: Government project | J4: On-Going FPIC process | K4: Ongoing FPIC process
A5: 3 | B5: IX | C5: 44447 | D5: PENRO-PLGU ZAMBO. DEL SUR | E5: PROPOSED VARIOUS BARANGAY DEVELOPMENT PROJECTS | G5: 1ST DISTRICT OF ZDS | H5: Government project | J5: On-Going FPIC process | K5: Ongoing FPIC process
A6: 4 | B6: IX | C6: 44264 | D6: BAMBOO INTEGRATED WORKS ASSOCIATION (BIWA) | E6: COMMUNITY-BASE FOREST MANAGEMENT AGREEMENT (CBFMA) | G6: SINDANGAN,ZAMBO.NORTE | H6: Forest Management Project | J6: On-Going FPIC process | K6: Ongoing FPIC process
A7: 5 | B7: IX | G7: LEON B. POSTIGO, LEON B. POSTIGO | H7: Forest Management Project | K7: Ongoing FPIC process
A8: 6 | B8: IX | C8: 2011 | D8: 31st Century Mining Corp. | E8: Mineral Production Sharing Agreement (MPSA)(APSA 114-IX) | G8: Peñarranda, Shiolan, & Lacnapan, Kabasalan, Zamboanga, Sibugay | H8: mining project | J8: LO. 39-7-11 (with recommendation) With mining moratorium in the Zamboanga Peninsula; ER Commissioner has already endorsed to ADO for technical evaluation | K8: In active CP Application
A9: 7 | B9: IX | C9: 2011 | D9: National Grid Corporation | E9: Aurora- Polanco 138 KV Transmission Line | G9: Municipalities of Sergio Osmeña, Sr., Piñan and Polanco, Zamboanga del Norte | H9: energy project | J9: Awaiting LAO Compliance (as of 03-13-14) and Legal Opinion No.19-05-03-19 | K9: FPIC Completed
A10: 8 | B10: IX | C10: 41449 | D10: EURO HYDRO POWER (ASEA) HOLDINGS, INC. | E10: MINI HYDRO ELECTRIC POWER PLANT | G10: Barangay Morob, Leon B. Postigo, Zamboanga del Norte | H10: energy project | I10: LEON B. POSTIGO AD | J10: Pending FPIC process | K10: Ongoing FPIC process
A11: 9 | B11: IX | C11: 2017 | D11: Subanen ICCs/IPs of CADT 075 | E11: EPR application | G11: Siayan, Zambaoanga del Norte | H11: EPR | J11: No compliance to Memo RMD-ADO-22-2023-1 dated January 9, 2023 | K11: Validation completed
A12: 10 | B12: IX | C12: 42811 | D12: LEONILO P. ZULUETA | E12: Minahang Bayan | G12: Barangay Milad, Polanco, Zamboanga del Norte | H12: mining project | I12: POLANCO AD | J12: Pending FPIC process | K12: Ongoing FPIC process
A13: 11 | B13: IX | C13: 42867 | D13: IPIL-ITWD-DPWH | E13: WATER SUPPLY SYSTEM EXPANSION PROJECT | G13: BARANGAYS DOMANDAN, BACALAN, TENAN, UPPER PANGI, PANGI, AND SANITO, ALL IN THE MUNICIPALITY OF IPIL, ZAMBOANGA SIBUGAY | H13: Water System | I13: IPIL AD | J13: Received Legal Opinion no. 14-24-05-23 dated May 24, 2023 for compliance of the FPIC team. FPIC team Recompost with Memo. Order no. 06-653-23 dated June 2, 2023 | K13: FPIC Completed
A14: 12 | B14: IX | C14: 2018 | D14: KARSON MINING AND TRADING CORPORATION (KMTC) | E14: APSA 00120-IX | G14: BARANGAY TIGBUCAY AND TIGPALAY, TUNGAWAN, ZSP | H14: mining project | I14: TUNGAWAN AD | J14: No compliance from the proponent to the Legal Findings in the MOA | K14: FPIC Completed
A15: 13 | B15: IX | C15: 43712 | D15: NIA | E15: Small Irrigation Project CY 2019 | G15: Municipality of Siayan, Zamboanga del Norte | H15: irrigation project | I15: SIAYAN AD | J15: Pending FPIC process | K15: For FPIC process
A16: 14 | B16: IX | C16: 43710 | D16: ESR CONSTRUCTION & DEVELOPMENT CORPORATION | E16: Installation of One (1) Unit Batching Plant | G16: Brgy. Calamba, Kalawit, Zamboanga del Norte | H16: Others | I16: KALAWIT AD | J16: Dormant Application | K16: In active CP Application
A17: 15 | B17: IX | C17: 43500 | D17: GERARD NATHANIEL R. REYES | E17: FOREST LAND USE AGREEMENT (FLAG) FOR 8.342 HAS. SALTWORK PROJECT | G17: BARANGAGY LOGOY DIUTAY, BARANGAY TALON-TALON, ALL IN THE ZAMBOANGA CITY | H17: Others | I17: TALON-TALON AD | J17: Pending FPIC process | K17: Ongoing FPIC process
A18: 16 | B18: IX | C18: 43500 | D18: MS. REMEDIOS R. REYES | E18: FOREST LAND USE AGREEMENT (FLAG) FOR 7.04 HAS. SALTWORK PROJECT | G18: LOGOY DIUTAY, BARANGAY TALON-TALON, ALL IN THE ZAMBOANGA CITY | H18: Others | I18: TALON-TALON AD | J18: Pending FPIC process | K18: Ongoing FPIC process
A19: 17 | B19: IX | C19: 2017 | D19: WEE DEE PING | E19: RENEWAL OF IFMA-018 | G19: BARANGAY MANTIVOH, SIBUCO, ZAMBOANGA DEL NORTE | H19: Forest Management Project | I19: SIBUCO AD | J19: Pending FPIC process | K19: Ongoing FPIC process
A20: 18 | B20: IX | C20: 42600 | D20: OLIVER CHAN | E20: CONSTRUCTION OF HYDROPOWER PLANT | G20: LIMPAPA AND PATALON, ALL IN THE ZAMBOANGA CITY | H20: energy project | I20: LPL ICC CADT | J20: Pending FPIC process | K20: Ongoing FPIC process
A21: 19 | B21: IX | C21: 43059 | D21: RICK ROBINSON K. ROBINS | E21: ISAG NO. 000457-IX | G21: LAYAWAN RIVER, DE VENTA PERLA, ALL IN THE MUNICIPALITY OF POLANCO, ZAMBOANGA DEL NORTE | H21: Sand and Gravel | I21: POLANCO AD | J21: Pending FPIC process | K21: Ongoing FPIC process
A22: 20 | B22: IX | C22: 43271 | D22: MINARDO BATOON | E22: ISAG 00052-IX | G22: LAYAWAN RIVER, MILAD & DE VENTA PERLA, ALL IN THE MUNICIPALITY OF POLANCO, ZAMBOANGA DEL NORTE | H22: Sand and Gravel | I22: POLANCO AD | J22: Pending FPIC process | K22: Ongoing FPIC process
A23: 21 | B23: IX | C23: 43888 | D23: ACES WATER SUPPLY AND DEVELOPMENT CORPORATION/MS. PILAR N.A SOLIS, AWSDC REPRESENTATIVE | E23: WATER SUPPLY | G23: BARANGAY SULO, NAGA, ZAMBOANGA SIBUGAY | H23: Water System | I23: NAGA AD | J23: Pending FPIC process | K23: Ongoing FPIC process
A24: 22 | B24: IX | C24: 43979 | D24: ALSON ENERGY DEVELOPMENT CORPORATION (AEDC) | E24: 8 MW SINDANGAN 1 HYDROELECTRIC POWER PROJECT WITH HCS NO. 2019-03-802 | G24: BARANGAY PANGE, SIAYAN, ZAMBOANGA DEL NORTE | H24: energy project | I24: SIAYAN AD | J24: The compliance of the FPIC Team was endorsed to the LAO and ADO on July 14, 2025 for the Siayan 1 Project at Labangon Dumingag | K24: FPIC Completed
A25: 23 | B25: IX | E25: 7 MW SINDANGAN 2 HYDROELECTRIC POWER PROJECT WITH HSC NO. 2019-03-803 | G25: BARANGAY MACASING, SIAYAN, ZAMBOANGA DEL NORTE | H25: energy project | I25: SIAYAN AD | K25: FPIC Completed
A26: 24 | B26: IX | C26: 44039 | D26: MR. ARNEL D. VICTORIANO | E26: ISAG NO. 00065-IX | G26: BARANGAY MOYO, SIAYAN, ZAMBOANGA DEL NORTE | H26: Sand and Gravel | I26: SIAYAN AD | J26: Waiting for the FPIC report | K26: FPIC Completed
A27: 25 | B27: IX | C27: 44022 | D27: MS. RACHEL ANNE WONG DIOSMANO | E27: ISAG NO. 00071-IX | G27: BARANGAY MIATAM, KATIPUNAN, ZAMBOANGA DEL NORTE | H27: Sand and Gravel | I27: KATIPUNAN AD | J27: Waiting for the FPIC compliance | K27: FPIC Completed
A28: 26 | B28: IX | C28: 44154 | D28: MR. RODOLFO N. CARPILA | E28: ISAG NO. 00073-IX | G28: BARANGAY PARANGLUMBA, SIAYAN, ZAMBOANGA DEL NORTE | H28: Sand and Gravel | I28: SIAYAN AD | J28: Waiting for the FPIC report | K28: FPIC Completed
A29: 27 | B29: IX | C29: 44291 | D29: MR. ALBERTO D. LANDIAO | E29: MINAHANG BAYAN (SMALL SCALE MINING APPLICATION) | G29: BARANGAY MATIGDAO, BALIGUIAN ZDN | H29: mining project | I29: BALIGUIAN AD | J29: The MOA is for review of the PLO | K29: FPIC Completed
A30: 28 | B30: IX | C30: 44333 | D30: NIA | E30: KALUYAHAN SMALL IRRIGATION PROJECT | G30: BARANGAY KALUYAHAN, SIOCON ZDN | H30: irrigation project | I30: SIOCON AD | J30: On-Going FPIC process | K30: Ongoing FPIC process
A31: 29 | B31: IX | C31: 44356 | D31: LGU GUTALAC | E31: 33 VARIOUS PROJECT UNDER KC PAMANA IP CDD OF DSWD | G31: 33 BARANGAYS, GUTALAC, ZDN | H31: Government project | J31: On-Going FPIC process | K31: Ongoing FPIC process
A32: 30 | B32: IX | C32: 44323 | D32: DPWH 1ST DISTRICT ENGINEERINGNOFOFFICE | E32: Construction/Improvement of Access Roads leading to Declared Tourism Destination NRJ leading to Sunop Cave and Waterfalls (Sta. 02+221-Sta. 02+374.25) | G32: Brgy. Sunop, DUMINGAG, ZDS | H32: Road project | J32: On-Going FPIC process | K32: Ongoing FPIC process
A33: 31 | B33: IX | C33: 44323 | D33: DPWH 1ST DISTRICT ENGINEERINGNOFOFFICE | E33: Construction/Improvement of Access Roads leading to Declare Tourism Destination NRJ leading to Simata Adventure Park (Sta. 02+465.20-Sta. 03+017.50) | G33: Brgy. Simata, MOLAVE ZDS | H33: Road project | J33: On-Going FPIC process | K33: Ongoing FPIC process
A34: 32 | B34: IX | C34: 44323 | D34: DPWH 1ST DISTRICT ENGINEERINGNOFOFFICE | E34: Construction/Improvement of Access Roads leading to Declared Tourism Destination NRJ leading to Bugwak Spring (Sta. 02+790.00 – Sta. 03+007.60) | G34: Brgy. Lower Dimalinao, MOLAVE, ZDS | H34: Road project | J34: On-Going FPIC process | K34: Ongoing FPIC process
A35: 33 | B35: IX | C35: 44323 | D35: DPWH 1ST DISTRICT ENGINEERINGNOFOFFICE | E35: Construction/Improvement of Access Roads leading to Declared Tourism Destination NRJ leading to Josefina Masapak Waterfalls (Sta. 02+095.65 – Sta. 02+278.65) | G35: Brgy. Ebarle, JOSEFINA ZDS | H35: Road project | J35: On-Going FPIC process | K35: Ongoing FPIC process
A36: 34 | B36: IX | C36: 44323 | D36: DPWH 1ST DISTRICT ENGINEERINGNOFOFFICE | E36: Construction/Improvement of Access Roads leading to Declared Tourism Destination NRJ leading to Philippines Eagle Sanctuary (Sta. 00+820 – Sta. 01+030) | G36: Brgy. Dakayakan, MIDSALIP ZDS | H36: Road project | J36: On-Going FPIC process | K36: Ongoing FPIC process
A37: 35 | B37: IX | C37: 44323 | D37: DPWH 1ST DISTRICT ENGINEERINGNOFOFFICE | E37: Construction/Improvement of Access Roads leading to Declared Tourism Destination NRJ Pagadian City-Zamboanga City Road leading to Palpalan Peak, Pagadian City, Zambaonga del Sur (Sta. 04+306-Sta. 04+420.70 and Sta 05+215.84-Sta. 05+337.01) | G37: Pagadian City, ZDS | H37: Road project | J37: On-Going FPIC process | K37: Ongoing FPIC process
A38: 36 | B38: IX | C38: 44323 | D38: DPWH 1ST DISTRICT ENGINEERINGNOFOFFICE | E38: Construction/Improvement of Access Roads leading to Declared Tourism Destination NRJ leading to Eden Park Panoramic View/Zipline and Shrine Brgy. Bayabas to Brgy. Acad, Aurora, Zamboanga del Sur (Sta. 03+614-Sta. 03+876.50) | G38: Brgy. Bayabas to Brgy. Acad, AURORA, ZDS | H38: Road project | J38: No report submitted to the Region | K38: Validation completed
A39: 37 | B39: IX | C39: 44323 | D39: DPWH 1ST DISTRICT ENGINEERINGNOFOFFICE | E39: Construction/Improvement of Access Roads leading to Declared Tourism Destination NRJ leading to Balas River Cruise (Sta. 04+621 – Sta. 04+849) | G39: Brgy. Balas, AURORA, ZDS | H39: Road project | J39: FBI COMPOSITION ALREADY TRANSMITTED TO PO ZDS | K39: For FBI
A40: 38 | B40: IX | C40: 44323 | D40: DPWH 1ST DISTRICT ENGINEERINGNOFOFFICE | E40: Construction/Improvement of Access Roads leading to Declared Tourism Destination Calolot Boulevard, NRJ Jct. Aurora-Ozamis City Road, leading to Calolot Mountain Resort | G40: Tambulig, ZDS | H40: Road project | J40: No report submitted to the Region | K40: Validation completed
A41: 39 | B41: IX | C41: 44323 | D41: DPWH 1ST DISTRICT ENGINEERINGNOFOFFICE | E41: Construction/Improvement of Access Roads leading to Trades, Industries and Economic Zone, NRJ to Bobongan to Brgy. Poblacion in support of Engineered Bamboo, Ramon Magsaysay, Zamboanga del Sur (Sta. 00+000-Sta. 00+126.82, Sta. 00+000-Sta. 00+275.44, Sta. 00+460.64-Sta. 00+619.40 | G41: Ramon Magsaysay, ZDS | H41: Road project | J41: FBI COMPOSITION ALREADY TRANSMITTED TO PO ZDS | K41: For FBI
A42: 40 | B42: IX | C42: 44323 | D42: DPWH 1ST DISTRICT ENGINEERINGNOFOFFICE | E42: Construction/Improvement of Access Roads leading to Trades, Industries and Economic Zone, Tukuran Coco Activated Carbon, Zamboanga del Sur | G42: Tukuran, Zamboanga del Sur | H42: Road project | J42: FBI COMPOSITION ALREADY TRANSMITTED TO PO ZDS | K42: For FBI
... A46: 44 | B46: IX | C46: 44320 | D46: DPWH RIX | E46: FEASIBILITY STUDY OF THE PROPOSED KATIPUNAN-DUMINGAG ROAD | G46: KATIPUNAN, ZDN | H46: Road project | J46: THE FBI REPORT OF THE FBI TEAM OF ZDN HAS ALREADY SUBMITTED TO CO AND THE FPIC TEAM FOR THE AREA WITH THE AD RECOMMEND FOR THE FPIC PROCESS SECTION 24 | K46: For FPIC process
A47: 45 | G47: SERGIO OSMEÑA, ZDN | H47: Road project | K47: For FPIC process
A48: 46 | B48: IX | C48: 44307 | D48: LGU BALIGUIAN | E48: NOYNOYAN KOLIBUGAN VILLAGE IP HOUSING PROJECT | G48: BALIGUIAN, ZDN | H48: Government project | I48: Baliguian AD | J48: No report submitted to the Region | K48: Validation completed
A49: 47 | B49: IX | C49: 44293 | D49: LGU R.T. LIM | E49: UPGRADING OF LOCAL ACCESS ROAD | G49: BARANGAY MABINI, RTLIM ZSP | H49: Government project | J49: No report submitted to the Region | K49: Validation completed
A50: 48 | B50: IX | C50: 44266 | D50: LGU R.T. LIM | E50: MALUBAL SUBANEN IP HOUSING PROJECT | G50: BARANGAY MALUBAL, RTLIM ZSP | H50: Government project | J50: No report submitted to the Region | K50: Validation completed
A51: 49 | B51: IX | C51: 44243 | D51: LGU PAYAO | E51: PROPOSED DEVELOPMENT OF PANDILUSAN ISLAND | G51: PANDILUSAN ISLAND, PAYAO, ZSP | H51: Government project | I51: Payao AD | J51: No report submitted to the Region | K51: Validation completed
A52: 50 | B52: IX | C52: 44243 | D52: LGU PAYAO | E52: JC'S TALISAY ECOPARK AND BEACH RESORT | G52: POBLACION, PAYAO, ZDS | H52: Government project | I52: Payao AD | J52: No FPIC report submitted to the Regional Office | K52: Validation completed
A53: 51 | B53: IX | C53: 44399 | D53: MR. RAYMUND E. LACORTE | E53: ISAG NO. 00089-IX | G53: BARANGAY MIATAN, KATIPUNAN, ZDN | H53: Sand and Gravel | J53: No report submitted to the Region | K53: FPIC Completed
A54: 52 | B54: IX | C54: 44424 | D54: LGU LILOY, ZDN | E54: FARM TO MARKET ROAD PROJECTS | G54: BARANGAYS BANIGAN, SAN MIGUEL, PATAWAG, COMPRA, MALILA, VILLA M, TEJERO, PUNTA, STA. CRUZ, AND LAMAO, LILOY, ZDN | H54: Road project | J54: no report submitted to the Region | K54: Validation completed
A55: 53 | B55: IX | C55: 44406 | D55: MR. SONNY JR. A. YAGAO | E55: ISAG NO. 00088-IX | G55: BARANGAY SUPON, BAYOG, ZDS | H55: Sand and Gravel | J55: no report submitted to the Region | K55: FPIC Completed
A56: 54 | B56: IX | C56: 44406 | D56: MR. RODULFO D. HILOT, JR. | E56: ISAG NO. 00087-IX | G56: BARANGAYS MALUBO, DELUSOM, AND PANAGAAN, ,MAHAYAG, ZDS | H56: Sand and Gravel | I56: Mahayag AD | J56: FOR FPIC | K56: FPIC Completed
A57: 55 | B57: IX | C57: 44390 | D57: PLGU ZAMBOANGA DEL NORTE | E57: ROAD PROJECTS | G57: BARANGAYS BAGUMBAYAN AND NAZARETH, SERGIO OSMEÑA, ZDN | H57: Road project | J57: no report submitted to the Region | K57: Validation completed
A58: 56 | B58: IX | C58: 44390 | D58: PLGU ZAMBOANGA DEL NORTE | E58: REHAB/IMPROVEMENT OF MIDATAG ACCESS ROAD | G58: BARANGAY MIDATAG, LEON B. POSTIGO,ZAMBO.NORTE | H58: Road project | J58: no report submitted to the Region | K58: Validation completed
A59: 57 | B59: IX | E59: CONSTRUCTION OF 2 UNITS SINGLE BARREL RCBC, 2 UNITS SPILLWAY & REHAB/IMPROVEMENT OF TINUYOP ACCESS ROAD (SITIO BALIK2X-SITIO KASONG-SITIO LILIK ROAD SECTION) | G59: BARANGAY TINUYOP, LEON B. POSTIGO, ZAMBO.NORTE | H59: Road project | K59: Validation completed
A60: 58 | B60: IX | C60: 44417 | D60: MS. MARIA EDNA A. CHIONG | E60: ISAG | G60: BARANGAY LACNAPAN,KABASALAN, ZAMBO.SIBUGAY | H60: Sand and Gravel | I60: AD Kabasalan | J60: FOR FPIC | K60: For FPIC process
A61: 59 | B61: IX | C61: 44474 | D61: LGU KUMALARANG, ZAMBO. DEL SUR | E61: IMPROVEMENT/CONCRETING OF GUSOM FARM TO MARKET ROAD | G61: BARANGAY GUSOM, KUMALARANG, ZDS | H61: Road project | J61: no report submitted to the Region | K61: Validation completed
A62: 60 | B62: IX | C62: 44470 | D62: SAN ISIDRO UPLAND FARMERS CONSUMER COOPERATIVE | E62: COMMUNITY-BASE FOREST MANAGEMENT AGREEMENT (CBFMA) | G62: BARANGAY SAN ISIDRO,SAN MIGUEL,ZDS | H62: Forest Management Project | J62: no report submitted to the Region | K62: FPIC Completed
A63: 61 | B63: IX | C63: 44470 | D63: SINGCLOT NATIONAL GREENING PROGRAM CONSUMER COOPERATIVE (SNGPCC) | E63: COMMUNITY-BASE FOREST MANAGEMENT AGREEMENT (CBFMA) | G63: BARANGAY SINGCLOT,GUIPOS,ZDS | H63: Forest Management Project | J63: Composition already transmitted to the PO of ZDS | K63: For FPIC process
A64: 62 | B64: IX | C64: 44461 | D64: MS. CRESENCIA I. ESCONDE | E64: IBOG-IBOG SA TILUBOG FAMILY PARK AND SWIMMING POOL | G64: PUROK 2 TILUBOG,NAGA,ZAMBO.SIBUGAY | H64: Others | I64: NAGA AD | J64: For Compliance to the Legal Opinion Of LAO | K64: FPIC Completed
A65: 63 | B65: IX | C65: 44481 | D65: PNOC EXPLORATION CORPORATION (PNOC EC) | E65: COAL OPERATING CONTRACT (COC) NO. 204 | G65: MUNICIPALITY OF MALANGAS,ZAMBO.SIBUGAY | H65: Energy project | J65: For Compliance to the CEB Requirements Before issuance of CP | K65: FPIC Completed
A66: 64 | B66: IX | C66: 44476 | D66: MS. MAEBELLE T. PADAYHAG | E66: ISAG NO. 00090-IX | G66: BARANGAY OBAY, POLANCO, ZAMBO.NORTE | H66: Sand and Gravel | J66: no report submitted to the Region | K66: FPIC Completed
A67: 65 | B67: IX | G67: BARANGAY SINAMAN,DIPOLOG,ZAMBO.NORTE | H67: Sand and Gravel | K67: FPIC Completed
A68: 66 | B68: IX | C68: 44440 | D68: DPWH 3RD ENGINEERING DISTRICT | E68: 25 VARIOUS PROJECTS CY 2021 FUNDED BY THE DEPARTMENT OF PUBLIC WORKS AND HIGHWAYS (DPWH) | G68: 1ST DISTRICT OF ZDN | H68: Road project | J68: no report submitted to the Region | K68: Validation completed
A69: 67 | B69: IX | C69: 44440 | D69: LGU PIÑAN, ZDN | E69: PROPOSED FARM TO MARKET ROAD PROJECTS | G69: BARANGAYS STA. FE AND SIKITAN,PIÑAN,ZAMBO.NORTE | H69: Road project | J69: no report submitted to the Region | K69: Validation completed
A70: 68 | B70: IX | C70: 44442 | D70: LGU DIMATALING, ZDS | E70: CONSTRUCTION OF 100 IP HOUSING PROJECT | G70: PUROK 3, POBLACION,DIMATALING,ZDS | H70: Government project | J70: no report submitted to the Region | K70: Validation completed
A71: 69 | B71: IX | C71: 44536 | D71: MS. GEMMA J. MILITANTE | E71: ISAG NO. 00084-IX | G71: BARANGAY MILAD, POLANCO, ZAMBO.NORTE | H71: Sand and Gravel | I71: CADT 075 | J71: For FPIC | K71: For FPIC process
A72: 70 | B72: IX | C72: 44358 | D72: DPWH 2ND DISTRICT ENGINEERING OFFICE OF ZAMBOANGA SIBUGAY | E72: CONSTRUCTION/IMPROVEMENT OF ACCESS ROADS LEADING TO DECLARE TOURISM DESTINATION NRJ LEADING TO MALUBAL FALLS R. T. LIM | G72: BARANGAY MALUBAL,R.T. LIM, ZAMBO.SIBUGAY | H72: Road project | J72: no report submitted to the Region | K72: Validation completed
A73: 71 | B73: IX | C73: 44361 | D73: Dir. Cayamombao D. Dia, CESO III | E73: APPLICATION OF DEPARTMENT OF PUBLIC WORKS AND HIGHWAYS (DPWH) RIX FOR THE 11 PROPOSED PROJECTS FOR THE CY 2021 | G73: SERGIO OSMENA, SINDANGAN, SIAYAN, KATIPUNAN, LEON B POSTIGO, TAMPILISAN AND LABASON, ZAMBO.NORTE | H73: Road project | J73: no report submitted to the Region | K73: Validation completed
A74: 72 | B74: IX | C74: 44384 | D74: LGU Midsalip | E74: PROPOSED THERE(3) VARIOUS PROJECTS OF KALAHI CIDSS PAMANA IP CDD | G74: BRGY. CABALURAN, MUNICIPALITY OF MIDSALIP, ZDS | H74: Government project | J74: no report submitted to the Region | K74: Validation completed
A75: 73 | B75: IX | C75: Sept. 1, 2021 | D75: PENRO-PLGU, ZDS | E75: PROPOSED VARIOUS BARANGAY DEVELOPMENT PROJECTS | G75: 2ND DISTRICT OF ZDS | H75: Government project | J75: no report submitted to the Region | K75: Validation completed
A76: 74 | B76: IX | C76: 44529 | D76: VICTOR A. CONSUNJI PRESIDENT OF SIRAWAI PLYWOOD AND LUMBER CORP. | E76: EXPA NO. 000139-IX | G76: MINICIPALITY OF SIRAWAI, ZAMBO. NORTE | H76: mining project | J76: no report submitted to the Region | K76: FPIC Completed
A77: 75 | B77: IX | C77: 44531 | D77: LGU MOLAVE | E77: PROPOSE CONCRETING OF FARM TO MARKET ROADS | G77: BRGY. RIZAL, LOWER DIMALINAO, CULO, BRGY. ALICIA AND PARASAN ALL IN THE MUNICIPALITY OF MOLAVE ZDS | H77: Road project | J77: no report submitted to the Region | K77: Validation completed
A78: 76 | B78: IX | C78: 44519 | D78: LGU MUTIA ZAMBOANGA DEL NORTE | E78: PROPOSED CONSTRUCTION OF LEVEL II POTABLE WATER SUPPLY | G78: BRGY. ALVENDA, BUENA SUERTE, TINGLAN, SAN MIGUEL AND TOTONGAN ALL IN THE MUNICIPALITY OF MUTIA ZAMBO. NORTE | H78: Water system | J78: With ADO Observation for Compliance of FPIC Team | K78: Validation completed
A79: 77 | B79: IX | C79: 44215 | D79: LGU DIMATALING, ZDS | E79: PROPOSED CONSTRUCTION OF ONE HUNDRED (100) HOUSING UNITS | G79: PRK 3. POBLACION, DIMATALING ZDS | H79: Government project | J79: no report submitted to the Region | K79: Validation completed
A80: 78 | B80: IX | C80: 44386 | D80: JOEVERLY B. ARNAN MINICIPAL FINANCE IP CDD | E80: PROPOSED VARIOUS PROJECTS FUNDED BY THE KC-PAMANA-IP-CDD-BATCH 2 OF CYCLE 3 OF DEPARTMENT OF SOCIAL WELFARE AND DEVELOPMENT (DSWD) | G80: BRGY. SHIOLAN, KABASALAN ZAMBO. SIBUGAY | H80: Government project | J80: no report submitted to the Region | K80: Validation completed
A81: 79 | B81: IX | C81: 44544 | D81: MR. EDMUNDO S. VALLECER | E81: ISAG NO. 00091-IX | G81: BRGY. PIÑAMAR, MUNICIPALITY OF ROXAS ZAMBO. NORTE | H81: Sand and Gravel | J81: The proponent didn't finish the FPIC Process | K81: In active CP Application
A82: 80 | B82: IX | C82: 44348 | D82: DPWH RIX | E82: PROPOSED KATIPUNAN-DUMINGAG ROAD | G82: DUMINGAG ZDS | H82: Road project | J82: no report submitted to the Region | K82: Validation completed
A83: 81 | B83: IX | C83: 44540 | D83: NASRODIN T. DACULA | E83: LACNAPAN SMALL MINING | G83: BRGY. LACNAPAN, KABASALAN, ZAMBO. SIBUGAY | H83: Mining Project | I83: Kabasalan AD | J83: For FPIC | K83: For FPIC process
A84: 82 | B84: IX | C84: 44399 | D84: NIA RIX | E84: PROPOSED SMALL IRRIGATION PROJECT | G84: BRGY. DENOYAN, SIAYAN, AND BRGY. LAGAG, SINDANGAN, ZDN | H84: Irrigation Project | I84: Siayan AD | J84: For FPIC | K84: For FPIC process
A85: 83 | B85: IX | C85: 44552 | D85: UPMO-FCMC-DPWH | E85: PROPOSAL ALIGNMENT COVERS 12, 256 KILOMETERS | G85: MUNICIPALITY OF MAHAYAG, MOLAVE, TAMBULIG, ZDS | H85: Road project | J85: No report submitted to the Region | K85: Validation completed
A86: 84 | B86: IX | C86: 44439 | D86: PLGU ZAMBOANGA SIBUGAY | E86: 6 PROPOSE VARIOUS PROJECTS OF BARANGAY DEVELOPMENT PLAN (BDP) | G86: BRGY. GUINOMAN, DIPALAHAN, ZSP | H86: Government project | J86: Waiting for the FBI Team Compliance (Project Profile) | K86: Ongoing evaluation of the CP application
A87: 85 | B87: IX | C87: 44439 | D87: PLGU ZAMBOANGA SIBUGAY | E87: 8 PROPOSED VARIOUS PROJECTS OF BARANGAY DEVELOPMENT PLAN (BDP) | G87: BRGY. BALAGON, SIAY, ZSP | H87: Government project | J87: Waiting for the FBI Team Compliance (Project Profile) | K87: Ongoing evaluation of the CP application
A88: 86 | B88: IX | C88: 44439 | D88: PLGU ZAMBOANGA SIBUGAY | E88: 13 PROPOSED VARIOUS PROJECTS OF BARANGAY DEVELOPMENT PLAN (BDP) | G88: BARANGAYS LACNAPAN AND TAMPILISAN, MUN. KABASALAN, ZSP | H88: Government project | J88: no report submitted to the Region | K88: Validation completed
A89: 87 | B89: IX | C89: 44390 | D89: MR. OMAR R. MARCIAL | E89: ISAG APPLICATION | G89: BARANGAY UPPER TUNGAWAN, ZAMBO.SIBUGAY | H89: Sand and Gravel | J89: no report submitted to the Region | K89: FPIC Completed
A90: 88 | B90: IX | C90: 44364 | D90: DPWH ZAMBOANGA DEL SUR 1ST DISTRICT ENGINEERING OFFICE | E90: PROPOSED 16 ROAD IMPROVEMENT PROJECTS | G90: 1ST DISTRICT OF ZDS | H90: Road project | J90: no report submitted to the Region | K90: Validation completed
A91: 89 | B91: IX | C91: 44606 | D91: PROVINCIAL LOCAL GOVERNMENT UNIT (PLGU) OF ZAMBOANGA DEL SUR | E91: PROPOSED REHABILITATION/IMPROVEMENT OF GAWIL-BOLISONG-TIGUHA ROAD | G91: KUMALARANG AND LAPUYAN,ZDS | H91: Road project | J91: no report submitted to the Region | K91: Validation completed
A92: 90 | B92: IX | C92: 44629 | D92: NATIONAL IRRIGATION MANAGEMENT OFFICE (DZSIMO) | E92: PROPOSEPROJECT CARPOC-LUBUSAN AND CANAL STRUCTURES | G92: BARANGAY CARPOC AND LUBUSAN, LAPUYAN, ZDS | H92: Irrigation Project | I92: AD LAPUYAN | J92: For FPIC | K92: For FPIC process
A93: 91 | B93: IX | C93: 44600 | D93: LGU OF LABANGAN | E93: PROPOSED HOUSING PROJECT | G93: BRGY. LANGAPOD, COGONAN AND NUBORAN, LABANGAN, ZDS | H93: Government project | J93: FOR REVIEW THE FBI REPORT | K93: Validation completed
A94: 92 | B94: IX | C94: 44417 | D94: HON. EDUARDO D. RALACION MUNICIPAL MAYOR | E94: PROPOSED EIGHT (8) VARIOUS PROJECTS OF KALAHI CIDSS PAMANA IP CDD | G94: MUNICIPALITY OF LABANGAN | H94: Government project | J94: no report submitted to the Region | K94: Validation completed
A95: 93 | B95: IX | C95: 44417 | D95: LGU SOMINOT | E95: PROPOSED SIX (6) VARIOUS PROJECTS OF KALAHI CIDSS PAMANA IF CDD | G95: MUNICIPALITY OF SOMINOT, ZDS | H95: Government project | J95: no report submitted to the Region | K95: Validation completed
A96: 94 | B96: IX | C96: 44417 | D96: LGU PAGADIAN CITY | E96: PROPOSED SIX (6) VARIOUS PROJECTS OF KALAHI CIDSS PAMANA IF CDD | G96: MUNICIPALTY OF PAGADIAN CITY, ZDS | H96: Government project | J96: no report submitted to the Region | K96: Validation completed
A97: 95 | B97: IX | D97: LUCIANO TANGLANAN | E97: Manifestation of Intention to Exercise Priority Rights to Natural Resources | G97: CADT RO9-SIN-0908-075 (Sindangan, Leon B. Postigo, Godod, Zamboanga del Norte) | H97: EPR | J97: Waiting for compliance of RO to LAO's Opinion | K97: Validation completed
A98: 96 | B98: IX | D98: Everhydro Corporation | E98: 1.7Megawatt run of river hydro power plant | G98: Brgys,Labuan,Patalon and Limpapa,Zamboanga City | H98: energy project | J98: Waiting for compliance of RO to LAO's Opinion No.05-22-03-22 dated March 21, 2022 | K98: FPIC Completed
A99: 97 | B99: IX | C99: 44642 | D99: SIBUGAY UNITED SMALL SCALE MINING COOPERATIVE (SUSSMICO) | E99: DECLARATION OF PEOPLE'S SMALL-SCALE MINING AREA (PSSMA)/ MINAHANG BAYAN (MB) | G99: BRGY. J.S. PERFECTO AND SAN FERNANDINO, R.T. LIM, ZAMBO SIBUGAY | H99: mining project | J99: no report submitted to the Region | K99: FPIC Completed
A100: 98 | B100: IX | C100: 44642 | D100: SUNTRIA CORPORATION | E100: APPLICATION FOR EXPLORATION PERMIT DENOMINATED AS EXPA NO. 00153-IX | G100: SIBUCO, ZAMBO.NORTE | H100: mining project | J100: Pending Application | K100: Ongoing FPIC process
A101: 99 | B101: IX | C101: 44642 | D101: SANLOREZO MINES. INC. | E101: APPLICATION FOR EXPLORATION PERMIT DENOMINATED AS EXPA NO. 00154-IX | G101: SIBUCO, ZAMBO.NORTE, ZAMBO.CITY | H101: mining project | J101: Pending Application | K101: Ongoing FPIC process
A102: 100 | B102: IX | C102: 44642 | D102: STRONG GROUP HOLDINGS, INC. | E102: APPLICATION FOR THE EXPLORATION PERMIT DENOMINATED AS EXPA NO. 00155-IX | G102: KATIPUNAN AND SERGIO OSMENA, ZAMBO.SIBUGAY | H102: mining project | J102: Pending FBI; Dormant Applciation | K102: In active CP Application
A103: 101 | B103: IX | C103: 44579 | D103: NATIONAL IRRIGATION ADMINISTRATION | E103: FEASIBILITY STUDY FOR TITAY SMALL RESERVOIR IRRIGATION PROJECT (SRIP) | G103: TITAY, ZAMBO.SIBUGAY | H103: irrigation project | J103: on going FBI | K103: Ongoing FBI
A104: 102 | B104: IX | C104: 44613 | D104: NATIONAL GRID CORPORATION OF PHILIPPINES (NGCP) | E104: APPLICATION OF FOR THE INSTALLATION OF TRANSMISSION LINES | G104: POLANCO, PINAN, SERGIO OSMENA, ZAMBO.NORTE | H104: energy project | J104: on going FBI | K104: Ongoing FBI
...

Sheet REGION 10
A1: NO | B1: REGION | C1: DATE OF FILING OF CP APPLICATION | D1: NAME OF PROPONENT | E1: NAME OF PROJECT | F1: PROJECT COST | G1: LOCATION | H1: Type of Project | I1: AFFECTED AD/ICC/IP (for CP with ongoing FPIC) | J1: STATUS OF APPLICATION | K1: STATUS
A3: 1 | B3: X | C3: 2015 | D3: ABCEDE | E3: CBFMA | G3: Brgy., Pualas, Don Carlos, Bukidnon | H3: Forest Management Project | J3: Proponent is no more interested to pursue | K3: In active CP application | L3: =COUNTIF(K1:K74, "In active CP Application") -> 8
A4: =A3+1 -> 2 | B4: X | C4: 2015 | D4: Sta. Clara Power Corporation | E4: Can-ayan Hydro Electric Power Plant | G4: Brgy., Can-ayan and Kalasungay, Malaybalay City, Bukidnon | H4: Energy Project | J4: Proponent is no more interested to pursue | K4: In active CP application
A5: =A4+1 -> 3 | B5: X | C5: 2015 | D5: Felix Y. Manalo Foundation | E5: Eco-Farming Project of Iglesia ni Cristo | G5: Brgys., Rogongon, Mainit, Panoroganan, Kalilangan of Iligan City, LDN | H5: Plantation Project | I5: Higaonon ICCs/IPs of Bayug AD | K5: No Status indicated | L5: =COUNTIF(K1:K74, "No Status Indicated") -> 24
A6: =A5+1 -> 4 | B6: X | C6: 2015 | D6: Bukidnon Higaonon Tribal Association | E6: Minahang Bayan | G6: Sitio Guitaan, Brgy. Maligaya, Malaybalay City, Bukidnon | H6: Mining Project | I6: BUHITA | J6: Proponent is no more interested to pursue | K6: In active CP application
A7: =A6+1 -> 5 | B7: X | C7: 2015 | D7: BLGU-Gango | E7: Minahang Bayan | G7: Sitio Manlauyan, Gango, Libona, Buk. | H7: Mining Project | I7: LIBHIGAD | J7: BLGU-requested a meeting with RD | K7: In active CP application
A8: =A7+1 -> 6 | B8: X | C8: 2016 | D8: DPWH | E8: East-West Lateral Road connecting Agusan del Sur to Bukidnon | G8: Brgy., Mandahikan, Anlugan, Mandaing of the Province of Bukidnon | H8: Road Project | K8: No Status indicated
A9: =A8+1 -> 7 | B9: X | C9: 2016 | D9: NAPOCOR | E9: Pulangi IV HE Plant Dredging/Desilting Phase II | G9: Kiantig, San Jose, Quezon, Bukidnon | H9: Energy Project | K9: No Status indicated
A10: =A9+1 -> 8 | B10: X | C10: 2016 | D10: HEDCOR Bukidnon, Inc. | E10: 70MWs Run-of-River Hydropower Plant | G10: Brgy. San Lorenzo, Kitaotao, Bukidnon | H10: Energy Project | I10: FEMMATRICS | K10: No Status indicated
A11: =A10+1 -> 9 | B11: X | C11: 2016 | D11: Muslim-Christian Free Farmers Association (MCFFAI) | E11: CBFMA | G11: Sitio Kibaritan, Malinao, Kalilangan, Buk. | H11: Forest Management Project | J11: Proponent is no more interested to pursue | K11: In active CP application
A12: =A11+1 -> 10 | B12: X | C12: 2016 | D12: Vidal Poultry Breeder | E12: Water System | G12: Kaatuan, Lantapan, Bukidnon | H12: Water System | K12: No Status indicated
A13: =A12+1 -> 11 | B13: X | C13: 2016 | D13: DAEA ENC Philippine Power Corp. | E13: 5MW Solar Power Plant | G13: Sitio Olaligan, Brgy., Tugaya, Valencia City, Bukidnon | H13: Energy Project | J13: ON GOING FBV | K13: Ongoing Validation
A14: =A13+1 -> 12 | B14: X | C14: 2016 | D14: DPWH | E14: Construction of Puntian-Arakan Road | G14: Brgy. Puntian, Quezon and Brgys., Kitubo and Pagan, Kitaotao, Buk. | H14: Road Project | K14: No Status indicated
A15: =A14+1 -> 13 | B15: X | C15: 2016 | D15: DPWH | E15: Construction of Damulog-Kibawe-Kitaotao East-West Lateral Road) | G15: SH Omonay, Damulog, Sanipon, Kibawe and Sinuda, Kitaotao, Province of Bukidnon | H15: Road Project | K15: No Status indicated
A16: =A15+1 -> 14 | B16: X | C16: 2016 | D16: Felix Y. Manalo Foundation | E16: Eco-Farming Project of Iglesia ni Cristo | G16: Brgys., Guinoyuran, Lilingayon, Lourdesand Mt. Nebo, Valencia City, Buk. | H16: Plantation Project | K16: No Status indicated
A17: =A16+1 -> 15 | B17: X | C17: 2016 | D17: Mr. Ignacio Gamba Jr. | E17: Renewal of Quarry Permit | G17: Brgy. Poblacion, Libona, Buk. | H17: Sand and Gravel | K17: No Status indicated
A18: =A17+1 -> 16 | B18: X | C18: 2016 | D18: MPC Balingasag Power Station | E18: Reforestation Project | G18: Brgy., Kibanban, Balingasag, Mis. Or. | H18: Plantation Project | I18: Higaonon ICCs/IPs in Balatukan AD | J18: The application was forwarded to ADO for review and no update since then | K18: In active CP application
A19: =A18+1 -> 17 | B19: X | C19: 2017 | D19: DPWH | E19: Construction of Bukidnon-Iligan Road Project | G19: Brgy. Lantud, Talakag, Bukidnon | H19: Road Project | I19: Higaonon ICCs/IPs in Basak Lantud | K19: No Status indicated
A20: =A19+1 -> 18 | B20: X | C20: 2017 | D20: FGen Taholoan Hydro Corporation (FTHT) | E20: 39MW Tagoloan Hydroelectric Power Project | G20: Impasug-ong | H20: Energy Project | K20: No Status indicated
A21: =A20+1 -> 19 | C21: 2017 | D21: Cambi Agro Industries Corporation | E21: Agro Forestry Porject | G21: within BUHITA AD, Malaybalay City, Buk. | H21: Others | I21: BUHITA AD | K21: No Status indicated
A22: =A21+1 -> 20 | B22: X | C22: 2017 | D22: DPWH | E22: Jct. Sayre Highway Dalirig- Kisolon Bypass Road (Dalirig-Vista Villa-San Roque-Kisolon including Right of Way and Bridge project | G22: Municipalities of Manolo Fortich and Sumilao, Province of Bukidnon | H22: Road Project | K22: No Status indicated
A23: =A22+1 -> 21 | B23: X | C23: 2017 | D23: Dana Fresh Fruits Corporation | E23: Cavendish Banana Plantation | H23: Plantation Project | J23: The proponent did not appear during the Pre-Con | K23: In active CP application
A24: =A23+1 -> 22 | B24: X | C24: 2017 | D24: Davao Agricultural Ventures Corporation | E24: Extraction of Water | G24: Balangay 10,Brgy., Merangeran, Municipality of Quezon, Buk. | H24: Water System | I24: QUEMTRAS CADT | K24: No Status indicated
A25: =A24+1 -> 23 | B25: X | C25: 2017 | D25: Davao Agricultural Ventures Corporation | E25: Water Irrigation System | G25: Mulita River, Brgy., Maraymaray, Don Carlos, Buk. | H25: Irrigation Project | K25: No Status indicated
A26: =A25+1 -> 24 | B26: X | C26: 2018 | D26: Meadowland Developers Inc. | E26: 1.8MW Umalag 1 and 2.5MW Umalag 2 HEPP | G26: Brgy. Balubal, Cagayan de Oro City, Mis. Occ. | H26: Energy Project | K26: No Status indicated
A27: =A26+1 -> 25 | B27: X | C27: 2018 | D27: Engr. Enrique V. Angeles | E27: Renewalof Phyllite Schist Quarry Permit | G27: Brgy. Maluko, Manolo Fortich, Bukidnon | H27: Sand and Gravel | K27: No Status indicated
A28: =A27+1 -> 26 | B28: X | C28: 2018 | D28: LGU-Malaybalay City | E28: Malaybalay Water System Project | G28: Brgy., Dalwangan, Malaybalay City, Buk. | H28: Water System | K28: No Status indicated
A29: =A28+1 -> 27 | B29: X | C29: 2018 | D29: Del Monte Philppines Inc. | E29: Pineapple Plantation | G29: Mun. of Balingasag and Claveria, Mis. Or. | H29: Plantation Project | K29: No Status indicated
A30: =A29+1 -> 28 | B30: X | C30: 2018 | D30: Del Monte Philppines Inc. | E30: Pineapple Plantation | G30: Brgy. Kinawe, Libona, Bukidnon | H30: Plantation Project | K30: No Status indicated
A31: =A30+1 -> 29 | B31: X | C31: 2018 | D31: Apo Macote Communal Irrigation Association (AMCIA) | E31: Rehabilitation of Irrigation Project | G31: Purok-1,3,and 6, Brgy., Apo Macote, Malaybalay City | H31: Irrigation Project | K31: No Status indicated
A32: =A31+1 -> 30 | B32: X | C32: 2018 | D32: J's Continental Philippines Corporation | E32: Oil Palm Plantation | G32: Sitio Bayawa, Brgy., Siloo and Sitio Linabo of Brgy., San Luis, all of Malitbog Bukidnon | H32: Plantation Project | K32: No Status indicated
A33: =A32+1 -> 31 | B33: X | C33: 2018 | D33: Pulangi Hydropower Corporation (PHPC) | E33: South Pulangi Hydroelectric Power Plant | G33: Municipalities of Damulog,Dangcagan,Kibawe, and Kitaotao all in the province of Bukidnon | H33: Energy Project | K33: No Status indicated
A34: =A33+1 -> 32 | B34: X | C34: 2018 | D34: WHK Manufacturinf and Trading Corporation | E34: Renewal of Mineral Processing Permit | H34: Mining Project | K34: No Status indicated
A35: =A34+1 -> 33 | B35: X | C35: 2010 | D35: San Roque Agro-Forestry Development Multi-Purpose Cooperative | E35: Community Based Forest Management Agreement (CBFMA) | G35: Kamanikan, Gingoog, City | H35: Forest Management Project | J35: Waiting for compliance of RO to LAO's Opinion | K35: FPIC completed
A36: =A35+1 -> 34 | B36: X | C36: 2010 | D36: MEDVIL Farms, Inc. | E36: Poultry Raising Project | G36: Tawas, Kitaotao, Bukidnon | H36: Others | J36: Waiting for compliance of RO to CEB's comment | K36: FPIC completed
A37: =A36+1 -> 35 | B37: X | C37: 2010 | D37: Mindanao Astoria Mining Corporation | E37: Exploration Permit Application | G37: Mahayahay, Manitao, Nangcaon, Opol, Misamis Oriental | H37: Mining Project | J37: For CEB deliberation; with ADO's endorsement dated March 2016; Endorsed to the Ethnographic Commissioner for deliberation on March 6, 2017 | K37: FPIC completed
A38: =A37+1 -> 36 | B38: X | C38: 2011 | D38: MR. VICENTICO A. BUTA | E38: Exploration Permit Application (EXPA-000114-X) | G38: Brgy. Bugsok and Gango, Libona, Bukidnon | H38: Mining Project | J38: Remanded back to Region due to Transfer of Assignment to Wan Mount International Group, Inc., Awaiting compliance A.O. 1 s 2012 Sec. 8 & 30 | K38: In active CP application
A39: =A38+1 -> 37 | B39: X | C39: 2010 | D39: CLUBRINTA MINING CORP. | E39: Mineral Exploration Permit Application | G39: Sagungsungan, Nangcaon, Opol, Misamis Oriental | H39: Mining Project | J39: Waiting for compliance of RO to LAO's Opinion No. 21-5-11 | K39: FPIC completed
A40: =A39+1 -> 38 | B40: X | C40: 2011 | D40: BOUNTIFUL GEOMINES, INC. | E40: Mineral Exploration Permit Application | G40: Upper Malitbog, Awang, Opol, Misamis Oriental | H40: Mining Project | J40: Waiting for compliance of RO to ADO's evaluation | K40: FPIC completed
A41: =A40+1 -> 39 | B41: X | C41: 2019 | D41: Rio Verde Water Consortium, Inc. | E41: Forest Land Use Agreement | G41: Brgy.Pulas,Municipality of Baungon,Bukidnon | H41: Others | J41: Presented twice to the CEB; No compliance to the directives of the CEB submitted yet | K41: FPIC completed
A42: =A41+1 -> 40 | B42: X | C42: 2011 | D42: PILIPINAS MINING RESOURCES, INC. | E42: Exploration Permit Application (EXPA-107-X) | G42: Brgy. Capitan Bayong of Impasug-ong and Brgy. Banayan, Bukidnon | H42: Mining Project | J42: Waiting for compliance of RO to ADO's evaluation | K42: FPIC completed
A43: =A42+1 -> 41 | B43: X | C43: 2007 | D43: Mandahican Farmers Developers Association | E43: Community Solicited Project for CBFMA | G43: Mandahican, Cabanglasan, Bukidnon | H43: Forest Management Project | J43: Waiting for compliance of RO to LAO's Opinion | K43: FPIC completed
A44: =A43+1 -> 42 | B44: X | C44: 2015 | D44: Philnewriver Power Corporation | E44: 5MW and 4.5MW Hydro Electric Power Project | G44: Baragay Kiabo, Malibog, Bukidnon and Barangays Siloo and San Luis, Malitbog, Bukidnon | H44: Energy Project | J44: No compliance to Legal Advisory 51-06-07-18 | K44: FPIC completed
A45: =A44+1 -> 43 | B45: X | C45: 2024 | D45: DPWH-10 | E45: CONSTRUCTION OF CDOC-ILIGAN , HINTERLAND ROAD, JCT.CDO CAMP KIBARITAN ROAD-DOMINOROG ROAD, DANSOLIHON-JCT.IBR ROGONGON, ILIGAN CITY | G45: CDOC-ILIGAN HINTERLAND ROAD,JCT. CDO CAMP KIBARITAN ROAD-DOMINOROG, DANSOLIHON,ROGONGON ILIGAN CITY AND CAGAYAN DE ORO CITY | H45: Road Project | J45: SUBJECT FOR REVIEW | K45: Validation completed | L45: =COUNTIF(K1:K74, "Validation Completed") -> 1
A46: =A45+1 -> 44 | B46: X | C46: 2024 | D46: MISAMIS UNIVERSITY | E46: CENTER FOR ADVOCACY ON EXTENTION SERVICES (MU-CARES)FACILITY | G46: BARANGAY FERTIG HILLS TANGUB CITY, MISAMIS OCCIDENTAL | H46: Others | J46: ONGOING FPIC | K46: Ongoing FPIC process
A47: =A46+1 -> 45 | B47: X | C47: 2024 | D47: MR. MANOLITO GARCES | E47: COFFEE PLANTATION WITHIN THE MULTIPLE USE ZONE OF KALATUNGAN NATURAL RANGE | G47: BARANGAY CONCEPTION, PANGATUCAN BUKIDNON | H47: Plantation Project | J47: ONGOING FPIC | K47: Ongoing FPIC process
A48: =A47+1 -> 46 | B48: X | C48: 2024 | D48: GAMBA CONSTRUCTION AND AGRI VENTURES DEVELOPMENT INC. | E48: QUARRY | G48: SITIO BUGSOK, BARANGAY POBLACION LIBONA | H48: Sand and Gravel | J48: ONGOING FPIC | K48: Ongoing FPIC process
A49: =A48+1 -> 47 | B49: X | C49: 2024 | D49: DPWH-10 | E49: CONSTRUCTION OF JCT. MARAMAG ROAD-BARANGAY SAN MIGUEL -BARANGAY MARAYMARAY ROAD | G49: MARAMAG BUKIDNON | H49: Road Project | J49: ONGOING FBV WORK ORDER NO. R10-112924-00277 | K49: Ongoing Validation
A50: =A49+1 -> 48 | B50: X | C50: 2024 | D50: DPWH- BUKIDNON | E50: CONSTRUCTION OF TUGOP, BRIDGE ALONG PULANGI RIVER-BARANGAY TUGOP-SAN FERNANDO BUKIDNON | G50: BARANGAYS TUGOP AND SAN FERNANDO BUKIDNON | H50: Road Project | J50: ONDOING FBV,WORK ORDER NO. R10-112824-00272 | K50: Ongoing Validation
A51: =A50+1 -> 49 | B51: X | C51: 2024 | D51: DPWH- BUKIDNON | E51: CONSTRUCTION OF BRIDGE ALONG PULANGI RIVER-DUMALAGUING-IMPASUG-ONG BUKIDNON | G51: BARANGAY DUMALAGUING, IMPASU-ONG BUKIDNON | H51: Road Project | J51: ONGOING FBV, WORK ORDER NO. R10-112824-00273 | K51: Ongoing Validation
A52: =A51+1 -> 50 | B52: X | C52: 2024 | D52: DPWH-BUKIDNON | E52: CONCRETING OF ROAD LEADING TO MOMMUNAL RANCH IMPASUG-ONG BUKIDNON | G52: BARANGAY CAPITANBAYONG, IMPASUG-ONG BUKIDNON | H52: Road Project | J52: ONGOING FBV, WORK ORDER NO. R10-112824-00274 | K52: Ongoing Validation
A53: =A52+1 -> 51 | B53: X | C53: 2024 | D53: DPWH-BUKIDNON | E53: CONSTRUCTION OF WATER SUPPLY SYSTEM | G53: BARANGAY DALWANGAN, MALAYBALAY CITY, BUKIDNON | H53: Water System | J53: ONGOING FBV,WORK ORDER NO. R10-112824-00275 | K53: Ongoing Validation
A54: =A53+1 -> 52 | B54: X | C54: 2024 | D54: BUREAU OF FISHERIES AQUATIC RESOURCES 10 | E54: CONSTRUCTION OF FISHERIES INTRGRATED LABORATORY TO IMPROVE REGULATORY SERVICES AND SUSTAINABLE OPERATION | G54: BARANGAY MACABALAN CDOC | H54: Government Project | J54: ONGONG FBV -WORK ORDER NO. R10-112524-00270 | K54: Ongoing Validation
A55: =A54+1 -> 53 | B55: X | C55: 2024 | D55: DPWH-10 | E55: CONSTRUCTION OF MALAYBALAY BY PASS ROAD EXTENTION (MAPAYAG BUGCAON-LANTAPAN ROAD SECTION | G55: LATAPAN AND MALAYBALAY CITY | H55: Road Project | J55: ONGOING FBV-WORK ORDER NO. R10-112524-00269 | K55: Ongoing Validation
A56: =A55+1 -> 54 | B56: X | C56: 2024 | D56: PROVINCIAL GOVERNEMNT OF LANAO DEL NORTE | E56: CONCRETING OF BARANGAY INAGUNGAN , BARANGAY DARIMBANG, BARANGAY PANALAWAN AND TAGOLOAN LANAO DEL NORTE | G56: BARANGAY TAGOLOAN LANAO DEL NORTE | H56: Road Project | J56: ONGOING FV WORK ORDER NO. 120924-00268 | K56: Ongoing Validation
A57: =A56+1 -> 55 | B57: X | C57: 2024 | D57: UNIVERSITY OF SCIENCE AND TECHNOLOGY OF SOUTHERN PHILIPPINES | E57: UTILIZATION OF WHITE CORN GRITS AS STAPLE FOR IMPROVED NUTRITION, DISEASE PREVENTION AND MANAGEMENT IN CLAVERIA MISAMIS ORIENTAL | G57: CLAVERIA MISAMIS ORIENTAL | H57: Government Project | J57: ONGOING FBV, WORK ORDER NO. R10-112024-00267 | K57: Ongoing Validation
... A61: =A60+1 -> 59 | B61: X | C61: 2025 | D61: DEPARTMENT OF ENVIRONMENT AND NATURAL RESOURCES | E61: CONSTRUCTION OF ACCESS ROAD WITHIN THE BUFFER ZONE, MT. KALATUNGAN RANGE NATURAL PRAK | G61: BARANGAY CALAPAT, TAGBAK, TALAKAG BUKIDNON | H61: Road Project | J61: FBV WORK ORDER NUMBER R10-011525-00279 | K61: Ongoing Validation
A62: =A61+1 -> 60 | B62: X | C62: 2025 | D62: Del Monte Philppines Inc. | E62: Pineapple Plantation | G62: Sitio Kining-kining, Brgy. Pualas, Don Carlos, Bukidnon | H62: Plantation Project | J62: For compliance comments from Comm. Pinky | K62: FPIC completed | L62: =COUNTIF(K1:K74, "FPIC Completed") -> 10
A63: =A62+1 -> 61 | B63: X | C63: 2025 | D63: UPC Bio Energy IP IV Corp. | E63: Sustainable Industrial Agro-Forestry Project | G63: Sitio Impahanong, Bayawa, Biyawon of San Luis, Malitbog, Bukidnon | H63: Forest Management Project | J63: FPIC Work Order Number R10-FPIC-00211 | K63: Ongoing FPIC process | L63: =COUNTIF(K1:K74, "Ongoing FPIC Process") -> 11
A64: =A63+1 -> 62 | B64: X | C64: 2025 | D64: Ms. Kimberly Claire P. Madriaga | E64: Cloudscape Nature Park | G64: Purok 3, Barangay Kibalabag, Malaybalay City, Bukidnon | H64: Eco-tourism Project | J64: FPIC Work Order Number R10-FPIC-00206 | K64: Ongoing FPIC process
A65: =A64+1 -> 63 | B65: X | C65: 2025 | D65: M&B Poultry Farm Corporation | E65: Egg Layer Farming Project | G65: Bagocbog, Opol, MIsamis Oriental | J65: FPIC Work Order Number R10-FPIC-00204 | K65: Ongoing FPIC process
A66: =A65+1 -> 64 | B66: X | C66: 2025 | D66: Universal Harvester Dairy Farms Inc. | E66: Forest Land Grazing Management Agreement | G66: Brgy. San Miguel and Brgy. Base Camp, Maramag, Bukidnon | H66: FLGMA | J66: FPIC Work Order Number R10-FPIC-00202 | K66: Ongoing FPIC process
A67: =A66+1 -> 65 | B67: X | C67: 2025 | D67: Mr. Nelboy M. Indao | E67: Commercial Sand and Gravel | G67: Brgy. White Kulaman, Kitaotao, Bukidnon | H67: Sand and Gravel | J67: FPIC Work Order Number R10-FPIC-00250 | K67: Ongoing FPIC process
A68: =A67+1 -> 66 | B68: X | C68: 2025 | D68: Apex Aggregates and Exploration Inc | E68: River Quarry Permit | G68: Sitio Sita, Sinuda, Bukidnon | H68: Sand and Gravel | J68: FPIC Work Order Number R10-FPIC-00228 | K68: Ongoing FPIC process
A69: =A68+1 -> 67 | B69: X | C69: 2025 | D69: Mr. Garmin Jerico M. Bajo | E69: Reel Place | G69: Lorega, Kitaotao, Bukidnon | H69: Eco-tourism Project | J69: FPIC Work Order Number R10-FPIC-00227 | K69: Ongoing FPIC process
A70: =A69+1 -> 68 | B70: X | C70: 2025 | D70: Tangent and Renewables Inc. | E70: 5MW Culaman Hydropower Project | G70: Poblacion, Sumilao, Bukidnon | H70: Energy Project | J70: FPIC Work Order Number R10-FPIC-00221 | K70: Ongoing FPIC process
A71: =A70+1 -> 69 | B71: X | C71: 2025 | D71: DPWH-2nd DIstrict Bukidnon | E71: Application of Gratuitus Special Use Permit (GSUP) | G71: Palacapao, Quezon, Bukidnon | H71: Goverment | J71: FBV Work Order Number R10-FBV-0352 | K71: Ongoing Validation | L71: =COUNTIF(K1:K74, "Ongoing Validation") -> 18
A72: =A71+1 -> 70 | B72: X | C72: 2025 | D72: DENR | E72: Abaca Production and Agroforestry | G72: Gingoog, Misamis Oriental | H72: Goverment | J72: FBV Work Order Number R10-FBV-00349 | K72: Ongoing Validation
A73: =A72+1 -> 71 | B73: X | C73: 2025 | D73: Varraco | E73: Establishment of Smart Nursery | G73: MILLALITRA AD, Talakag, Bukidnon | J73: FBV Work Order Number R10-FBV-00329 | K73: Ongoing Validation
A74: =A73+1 -> 72 | B74: X | C74: 2025 | D74: DOTR | E74: Bukidnon Airport Development Project | G74: Maraymaray, Don Carlos, Bukidnon | H74: Government | J74: FBV Work Order Number R10-FBV-00310 | K74: Ongoing Validation

Sheet REGION 11
B1: REGION | C1: DATE OF FILING OF CP APPLICATION | D1: NAME OF PROPONENT | E1: NAME OF PROJECT | F1: PROJECT COST | G1: LOCATION | H1: Type of Project | I1: AFFECTED AD/ICC/IP (for CP with ongoing FPIC) | J1: STATUS OF APPLICATION | K1: STATUS
A3: 1 | B3: 11 | C3: 2007 | D3: LEGENDA MINES, INC. | E3: Exploration Permit Application (EXPA-000097-XI) | G3: Municipality of Sta. Maria and Malita, Davao del Sur | H3: Mining Projects | J3: Proponent inactive. Will coordinate with DENR-MGB to contact the proponent and get office address to send notice of inaction. | K3: In active CP application
A4: 2 | B4: 11 | C4: 2010 | D4: LIAN JU MINING CORPORATION | E4: Exploration Permit Application (EXPA-00021-XI) | G4: Brgys. Limbaan, Del Monte, Patrecio, Sta. Fe and El Salvador of New Corella | H4: Mining Projects | J4: Based on the reply letter from the MGB XI, their appeal was denied and affirmed by MGB CO on April 29, 2019. | K4: In active CP application
A5: 3 | B5: 11 | C5: 2011 | D5: RUSHFIELD MINING CORP. | E5: Exploration Project (EXPA-114) | G5: Brgy. Holy Cross, Old Macopa and San Ignacio, Mun. of Manay; and Brgys. Ompao, Tomoaong, Maganda, Limot, Tubaon, and Cabayagan, Mun. of Tarragona, Provine of Davao Oriental | H5: Mining Projects | J5: Based on the reply letter from the MGB XI, their appeal was denied and affirmed by MGB CO on April 29, 2019. | K5: In active CP application
A6: 4 | B6: 11 | C6: 2012 | D6: NGCP | E6: Matanao-Gensan 138kV T/L Project | G6: Municipality of Kiblawan | H6: Energy Project | J6: There is a need to meet with NCIP Region 12. The application covers 2 Regions, FPIC was conducted separately. | K6: For FPIC process
A7: 5 | B7: 11 | C7: 2014 | D7: Mandaya, Manobo, Mangguangan and Dibabawon ICCs/IPs | E7: Exercise of Priority Rights (EPR) | G7: Municipalities of Monkayo and Compostella, all of Compostella Valley, Province of Davao Oriental and Cateel, Davao Oriental | H7: EPR - Mining | J7: The application was initially presented to the CEB. It was referred back to the community to comply with the process as provided in the guidelines. The Provincial Office was directed to conduct consultation with the IPS of the 4 IP Groups to verify their intent to pursue this plan and discuss the existing guidelines and prevailing situation in the AD with FPICs given to some investors. | K7: For Validation
A8: 6 | B8: 11 | C8: 2014 | D8: NGCP | E8: Malita-Matanao 230 kV T/L Project located at Sta. Maria, Davao Occidental | G8: Sta. Maria and Malita, Davao Occidental | H8: Energy Project | I8: Tagakaulo and Blaan ICCs/IPs | J8: Proponent was inactive for several years and only made a follow-up of the CP application in October 2023 that they request for the CP. The Provincial Team members will meet to review the completeness of the FPIC documents. It was originally covered by NCIP Davao del Sur, but the project area is now under NCIP Davao Occidental. | K8: In active CP application
A9: 7 | B9: 11 | C9: 2015 | D9: GLOBAL SIBAGAT HYDROPOWER CORPORATION | E9: 32.0 MW CASAUMAN RIVER HYDROPOWER PROJECT | G9: Barangays Del Pilar, Holy Cross, Rizal, San Ignacio, and Zaragoza, Municipality of Manay, Davao Oriental | H9: Energy Project | I9: Mandaya | J9: The CP application was presented on the 5th Regular En Banc Session of the 9th Commission May 4, 2022. One of the recommendations is to include the barangays covered on the new CADT Application of the Mandaya ICCs/IPs of Manay in the community consultation. The FPIC Team complied with that but the barangays covered on these community consultations have new demands on the terms and conditions that will be part of the new Supplemental MOA. As of the present, the Proponent and the IPS has yet to agree and negotiations are still incomplete. | K9: Ongoing FPIC process
A10: 8 | B10: 11 | C10: 2018 | D10: CARAGA A1 HYDROPOWER CORPORATION (formerly Volga Power Corporation) | E10: 6.5 MW CARAGA A1 Hydro Electric Power Project | G10: Sitio Sangab, Barangay Pichon, Municipality of Caraga, Davao Oriental | H10: Energy Project | I10: Mandaya | J10: After the conduct of the review and evaluation of the RRT of the FPIC Final Report on March 2024, most of the significant recommendations are geared towards the enhancement of the MOA, thus, going back to the community is necessary, which up to this date has not yet been conducted. Proponent is notified and provided with RRT Report. | K10: Ongoing FPIC process
A11: 9 | B11: 11 | C11: 2018 | D11: CARAGA A1 HYDROPOWER CORPORATION (formerly Volga Power Corporation) | E11: 4.5 MW CARAGA A3 HYDRO ELECTRIC POWER PROJECT | G11: Sitio Sangab, Barangay Pichon, Municipality of Caraga, Davao Oriental | H11: Energy Project | I11: Mandaya | J11: As the FPIC Process of this application was completed ahead of the other 2 HEPs, the Proponent suggested that all 3 HEPPs will be forwarded to ADO at once, when compliance on the recommendations of the RRT for the 2 HEPs will be completed. | K11: Ongoing FPIC process
A12: 10 | B12: 11 | C12: 2019 | D12: POWER SOURCE PHILIPPINES, INC. | E12: Construction of Power Plant | G12: Brgy. Mabila, Balut Island, Municipality of Sarangani | H12: Energy Project | I12: Blaan | J12: There is a need to have the MOA resigned because NCIP was represented by the Regional Director. In addition, there are provisions that needs to be improved. Application enrolled in EVOSS System. | K12: Ongoing FPIC process
A13: 11 | B13: 11 | C13: 2021 | D13: Rodolfo Hao | E13: Proposed Agro-Forestry & Eco-Tourism | G13: Purok Elian Brgy. Marilog Proper, Marilog, D.C. | H13: Eco-Tourism Project | J13: For MOA Validation and Signing; Draft MOA already forwarded to Proponent | K13: Ongoing FPIC process
A14: 12 | B14: 11 | C14: 2021 | D14: Carlito Degracia | E14: Proposed Agro-Forestry & Eco-Tourism | G14: Crossing Sambunutan, Brgy. Malamba, Marilog | H14: Eco-Tourism Project | J14: Proponent, inactive of his application. Notice will be sent. | K14: Ongoing FPIC process
A15: 13 | B15: 11 | C15: 2021 | D15: Dean Carl Golez | E15: Proposed Agro-Forestry & Eco-Tourism | G15: Crossing Sambunutan, Brgy. Malamba, Marilog | H15: Eco-Tourism Project | J15: Proponent, inactive of his application. Notice will be sent. | K15: Ongoing FPIC process
A16: 14 | B16: 11 | C16: 2021 | D16: Atty. Eistein Taghoy | E16: Proposed Agro-Forestry & Eco-Tourism | G16: Crossing Sambunutan, Brgy. Malamba, Marilog | H16: Eco-Tourism Project | J16: Proponent, inactive of his application. Notice will be sent. | K16: Ongoing FPIC process
A17: 15 | B17: 11 | C17: 2021 | D17: Dan Justin Eslabon | E17: Proposed Agro-Forestry & Eco-Tourism | G17: Crossing Sambunutan, Brgy. Malamba, Marilog | H17: Eco-Tourism Project | J17: Proponent, inactive of his application. Notice will be sent. | K17: Ongoing FPIC process
A18: 16 | B18: 11 | C18: 2021 | D18: Atherine Anne Motas | E18: Proposed Agro-Forestry & Eco-Tourism | G18: Crossing Sambunutan, Brgy. Malamba, Marilog | H18: Eco-Tourism Project | J18: Proponent, inactive of her application. Notice will be sent. | K18: Ongoing FPIC process
A19: 17 | B19: 11 | C19: 2021 | D19: Marisol Diono | E19: High Value Organic Crops | G19: Sitio Malikongkong/Mundo | H19: Others | J19: Proponent, inactive of her application. Notice will be sent. | K19: Ongoing FPIC process
A20: 18 | B20: 11 | C20: 2021 | D20: Sophia Bernadette Eslabon | E20: Waste to Energy | G20: Sitio Kabagbahangan, Brgy. Suawan | H20: Others | J20: Proponent, inactive of his application. Notice will be sent. | K20: Ongoing FPIC process
A21: 19 | B21: 11 | C21: 2021 | D21: Marivic Motas | E21: Livestock Development | G21: Purok Namnam/Mahhabok East Marahan/Elian | H21: Others | J21: Proponent, inactive of his application. Notice will be sent. | K21: Ongoing FPIC process
A22: 20 | B22: 11 | C22: 2021 | D22: Robert Bellarmine Bajores | E22: Bulk Water/Hydro Electric Power | G22: Suawan River, Brgy. Suawan, Marilog Dist. | H22: Energy Project | J22: Proponent, inactive of his application. Notice will be sent. | K22: Ongoing FPIC process
A23: 21 | B23: 11 | C23: 2021 | D23: Michael Jimenez | E23: Proposed Agro-Forestry & Eco-Tourism | G23: Brgy. Marilog Proper, Marilog District | H23: Eco-Tourism Project | J23: For Pre-FPIC Conference. | K23: Ongoing FPIC process
A24: 22 | B24: 11 | C24: 2021 | D24: Edgar Rico | E24: Proposed Agro-Forestry Project | G24: Brgy, Marilog Proper, arilog District, Davao City | H24: Others | J24: Proponent, inactive of his application. Notice will be sent. | K24: In active CP application
... A32: 30 | B32: 11 | C32: 2021 | D32: Zaldy Serrano | E32: Tourism Dev't (Rest Houses & Cottages & Rest. & Coffee Shop | G32: Sitio Pamuhatan, Brgy. Marilog, Marilog District, Davao City | H32: Others | J32: Proponent, inactive of her application. Notice will be sent. | K32: In active CP application
A33: 31 | B33: 11 | C33: 2021 | D33: Rosal Genabe | E33: Proposed Eco-Tourism Development | G33: Datu Salumay, Marilog, District, Davao City | H33: Eco-Tourism Project | J33: For Reports Submission to RO | K33: FPIC completed | L33: 1
A34: 32 | B34: 11 | C34: 2021 | D34: Semplicio Areja II | E34: Proposed Eco-Tourism Development | G34: Brgy. Malabog, Paquibato District, Davao City | H34: Eco-Tourism Project | J34: Endorsed to Office of Ethnographic Commissioner through ADO for review | K34: FPIC completed | L34: 1
A35: 33 | B35: 11 | C35: 2021 | D35: Marie Joan L. Areja | E35: Proposed Eco-Tourism Development | G35: Sitio Balugo, Brgy. Malabog, Paquibato District, Davao City | H35: Eco-Tourism Project | J35: Endorsed to Office of Ethnographic Commissioner through ADO for review | K35: FPIC completed | L35: 1
A36: 34 | B36: 11 | C36: 2021 | D36: PLDTInc. & Smart Communications, Inc. | E36: Proposed Fiber Optic Cable to the Base Transceiver Station | G36: Marilog, Davao City | H36: Telecommunication | J36: For Pre-FBI Conference with the proponent. | K36: For FBI
A37: 35 | B37: 11 | C37: 2021 | D37: ClaudMaru Restaurant Rainforest | E37: ClaudMaru Restaurant Rainforest | G37: Upper Marahan, Marilog Proper, Marilog Dist., Davao City | H37: Others | J37: MOA Validated. Report for submission to RRT | K37: FPIC completed | L37: 1
A38: 36 | B38: 11 | C38: 2021 | D38: Sherife Dane Aldueso | E38: Establishment of Febris Cold Spring In-land Resort | G38: Purok 7, Brgy. Andap, New Bataan, DDO | H38: Others | J38: FBI conducted. For submission of FBI report | K38: FBI completed
A39: 37 | B39: 11 | C39: 2021 | D39: Dannes Pilapil | E39: Beach Resort | G39: Baybay, Mampising, Brgy. Tagnanan, Mabini, DDO | H39: Others | J39: Will send notice of inaction to the proponent. | K39: In active CP application
A40: 38 | B40: 11 | C40: 2021 | D40: Ronilo Pilapil | E40: Beach Resort | G40: Baybay, Mampising, Brgy. Tagnanan, Mabini, DDO | H40: Others | J40: Will send notice of inaction to the proponent. | K40: In active CP application
A41: 39 | B41: 11 | C41: 2021 | D41: Yuden Ann Fuentes | E41: Beach Resort | G41: Baybay, Mampising, Brgy. Tagnanan, Mabini, DDO | H41: Others | J41: Will send notice of inaction to the proponent. | K41: In active CP application
A42: 40 | B42: 11 | C42: 2021 | D42: Ruben Pilapil | E42: Beach Resort | G42: Baybay, Mampising, Brgy. Tagnanan, Mabini, DDO | H42: Others | J42: Will send notice of inaction to the proponent. | K42: In active CP application
A43: 41 | B43: 11 | C43: 2021 | D43: Delilah Pilapil Patigdas | E43: Beach Resort | G43: Baybay, Mampising, Brgy. Tagnanan, Mabini, DDO | H43: Others | J43: Will send notice of inaction to the proponent. | K43: In active CP application
A44: 42 | B44: 11 | C44: 2021 | D44: Susan Frazer | E44: Private Resort | G44: Purok 17, Batiano, Brgy. Tagnanan, Mabini, DDO | H44: Others | J44: For preparation and submission of FPIC report. | K44: FPIC completed | L44: 1
A45: 43 | B45: 11 | C45: 2021 | D45: Lanang Realty Devt. Corp. | E45: Port Facilities | G45: Shoreline of Brgy. Pindasan, Mabini, DDO | H45: Others | J45: Will send notice of inaction to the proponent. | K45: In active CP application
A46: 44 | B46: 11 | C46: 2021 | D46: Lapanday Properties Phil. Inc. | E46: Port Facilities | G46: Shoreline of Kopiat Island, Brgy. Pindasan, Mabini, DDO | H46: Others | J46: Will send notice of inaction to the proponent. | K46: In active CP application
A47: 45 | B47: 11 | C47: 2021 | D47: Emmalyn Pedro | E47: Beach Resort | G47: Mabini, DDO | H47: Others | J47: For preparation and submission of FPIC report. | K47: FPIC completed | L47: 1
A48: 46 | B48: 11 | C48: 2021 | D48: Elisa Omandac | E48: Beach Resort | G48: Mabini, DDO | H48: Others | J48: For preparation and submission of FPIC report. | K48: FPIC completed | L48: 1
A49: 47 | B49: 11 | C49: 2021 | D49: Romeo Salas, Sr. | E49: Beach Resort | G49: Purok 1, Mampising, Tagnanan, Mabini, DDO | H49: Others | J49: For preparation and submission of FPIC report. | K49: FPIC completed | L49: 1
A50: 48 | B50: 11 | C50: 2021 | D50: Carolin Caballero | E50: Beach Resort | G50: Purok 1, Mampising, Tagnanan, Mabini, DDO | H50: Others | J50: For preparation and submission of FPIC report. | K50: FPIC completed | L50: 1
A51: 49 | B51: 11 | C51: 2021 | D51: Elsie Taberara | E51: Beach Resort | G51: Purok 1, Mampising, Tagnanan, Mabini, DDO | H51: Others | J51: Will send notice of inaction to the proponent. | K51: In active CP application
A52: 50 | B52: 11 | C52: 2021 | D52: Josue Tesado | E52: Fish Cage, Ship, Boat Building | G52: Mabini, DDO | H52: Others | J52: For preparation and submission of FPIC report. | K52: FPIC completed | L52: 1
A53: 51 | B53: 11 | C53: 2021 | D53: Milagros Laurel | G53: Mabini, DDO | H53: Others | J53: For preparation and submission of FPIC report. | K53: FPIC completed | L53: 1
A54: 52 | B54: 11 | C54: 2021 | D54: Ivy Grace Labastida | E54: Beach Resort | H54: Others | J54: For preparation and submission of FPIC report. | K54: FPIC completed | L54: 1
A55: 53 | B55: 11 | C55: 2021 | D55: Eddielito Ypon | E55: Beach Resort | G55: Mampising, Tagnanan, Mabini, DDO | H55: Others | J55: Will send notice of inaction to the proponent. | K55: In active CP application
A56: 54 | B56: 11 | C56: 2021 | D56: Nelson Asumbrado | E56: Beach Resort | G56: Purok 1, Avocado, Brgy. Mampising, mabini, DDO | H56: Others | J56: For preparation and submission of FPIC report. | K56: FPIC completed | L56: 1
A57: 55 | B57: 11 | C57: 2021 | D57: Cristeline Formento | E57: Beach Resort | G57: Mabini, DDO | H57: Others | J57: For preparation and submission of FPIC report. | K57: FPIC completed | L57: 1
A58: 56 | B58: 11 | C58: 2021 | D58: Violeta Arquisal | E58: Beach Resort | G58: Mabini, DDO | H58: Others | J58: For preparation and submission of FPIC report. | K58: FPIC completed | L58: 1
A59: 57 | B59: 11 | C59: 2021 | D59: Jonathan Austero | E59: Beach Resort | G59: Batiano, Brgy. Tagnanan, Mabini, DDO | H59: Others | J59: Will send notice of inaction to the proponent. | K59: In active CP application
A60: 58 | B60: 11 | C60: 2021 | D60: Elviera Castigon | E60: Fish Cage, Ship, Boat Building | G60: Purok 2, San Antonio, Mabini, DDO | H60: Others | J60: For preparation and submission of FPIC report. | K60: FPIC completed | L60: 1
A61: 59 | B61: 11 | C61: 2021 | D61: Maura Vda de Figueroa | E61: Fish Pond | G61: Brgy. Cadunan, Mabini, DDO | H61: Others | J61: Will send notice of inaction to the proponent. | K61: In active CP application
A62: 60 | B62: 11 | C62: 2021 | D62: Alejandro Lapasaran Gacasan | E62: Beach Resort | G62: Brgy. San Antonio/Bayside View Vill., Panabo City | H62: Others | J62: Will send notice of inaction to the proponent. | K62: In active CP application
A63: 61 | B63: 11 | C63: 2021 | D63: Jenifer Villafuerte | E63: Beach Resort | H63: Others | J63: For preparation and submission of FPIC report. | K63: FPIC completed | L63: 1
A64: 62 | B64: 11 | C64: 2021 | D64: Wilfredo Briones & Katherine Briones | E64: Private Resort | G64: Mampising, Tagnanan, Mabini, DDO | H64: Others | J64: Will send notice of inaction to the proponent. | K64: In active CP application
A65: 63 | B65: 11 | C65: 2021 | D65: Marites Ronquillo | E65: Beach Resort | G65: Mabini, DDO | H65: Others | J65: For preparation and submission of FPIC report. | K65: FPIC completed | L65: 1
A66: 64 | B66: 11 | C66: 2021 | D66: Josephine Perez | E66: Beach Resort | G66: Mabini, DDO | H66: Others | J66: For preparation and submission of FPIC report. | K66: FPIC completed | L66: 1
A67: 65 | B67: 11 | C67: 2021 | D67: Mary Grace Ocot | E67: Beach Resort | G67: Mabini, DDO | H67: Others | J67: For preparation and submission of FPIC report. | K67: FPIC completed | L67: 1
A68: 66 | B68: 11 | C68: 2021 | D68: Tagnanan Carp Beneficiaries Coop. | E68: Beach Resort | G68: Mabini, DDO | H68: Others | J68: For preparation and submission of FPIC report. | K68: FPIC completed | L68: 1
A69: 67 | B69: 11 | C69: 2021 | D69: Aida Bock | E69: Beach Resort | G69: Mampising, Tagnanan, Mabini, DDO | H69: Others | J69: For preparation and submission of FPIC report. | K69: FPIC completed | L69: 1
A70: 68 | B70: 11 | C70: 2021 | D70: Emely Ormega | E70: Private Resort | H70: Others | J70: For preparation and submission of FPIC report. | K70: FPIC completed | L70: 1
A71: 69 | B71: 11 | C71: 2021 | D71: Ian Neo | E71: Beach Resort | G71: Manaklay, Pindasan, Mabini, DDO | H71: Others | J71: For preparation and submission of FPIC report. | K71: FPIC completed | L71: 1
A72: 70 | B72: 11 | C72: 2021 | D72: Mary Jean Poblacion | E72: Beach Resort | G72: Mahogany, Mampising, Tagnanan, Mabini, DDO | H72: Others | J72: Will send notice of inaction to the proponent. | K72: FPIC completed | L72: 1
A73: 71 | B73: 11 | C73: 2021 | D73: Marichelle Pilapil | E73: Beach Resort | H73: Others | J73: For preparation and submission of FPIC report. | K73: FPIC completed | L73: 1
A74: 72 | B74: 11 | C74: 2021 | D74: Marcelino Eroy | E74: Beach Resort | G74: Baybay, Mampising, Brgy. Tagnanan, Mabini, DDO | H74: Others | J74: Will send notice of inaction to the proponent. | K74: FPIC completed | L74: 1
A75: 73 | B75: 11 | C75: 2021 | D75: Rito Ocot | E75: Beach Resort | G75: Purok 1, Avocado, Brgy. Mampising, mabini, DDO | H75: Others | J75: For preparation and submission of FPIC report. | K75: FPIC completed | L75: 1
A76: 74 | B76: 11 | C76: 2021 | D76: Jogienelle Cepeda | E76: Beach Resort | G76: Mabini, DDO | H76: Others | J76: For preparation and submission of FPIC report. | K76: FPIC completed | L76: 1
